Workbook
Name DashboardMonths: 'Dashboard Calc'!$I$2:$I$13

Sheet Capa
A1: RELATÓRIO CLARO TROCA — TRADE-IN
A2: Painel de acompanhamento Brasil | visão executiva, regional, parceiros e operação semanal
A4: 📍 NAVEGAÇÃO DO RELATÓRIO
A6: ABA | B6: FINALIDADE
A7: Dashboard | B7: Resumo executivo mensal, KPIs, gráficos e prioridades regionais.
A8: TOP 10 Parceiros | B8: Ranking nacional por Attachment consolidado entre regionais.
A9: REGIONAL | B9: Cobertura de PDVs e desempenho por regional.
A10: GRUPOS ZERADOS | B10: Grupos com e sem Claro Troca por regional.
A11: GRUPOS | B11: Histórico mensal consolidado por grupo rede.
A12: PDVS | B12: Histórico e elegibilidade por ponto de venda.
A13: BASE | B13: Dados importados semanalmente do BI.
A14: INSTRUÇÕES | B14: Rotina de atualização e validações do relatório.
A17: 🔄 ROTINA SEMANAL
A19: 1 | B19: Anexe a nova extração do BI e use o prompt de atualização semanal.
A20: 2 | B20: Confirme que BASE e PDVS fecham no mesmo total de Claro Troca.
A21: 3 | B21: Use o Dashboard para direcionar as provocações às regionais.

Sheet Dashboard
A1: PAINEL EXECUTIVO — CLARO TROCA | M1: MÊS | N1: CLARO TROCA
A2: Visão Brasil para acompanhamento semanal de performance, cobertura e oportunidades regionais. | M2: 46023 | N2: ='Dashboard Calc'!J2 -> 2001
A3: 📅 MÊS | B3: 46235 | D3: ="Atualizado com "&TEXT(COUNTIFS(BASE!$A:$A,$B$3),"#,##0")&" PDVs na base do mês selecionado" -> Atualizado com 997,0 PDVs na base do mês selecionado | M3: 46054 | N3: ='Dashboard Calc'!J3 -> 1657
M4: 46082 | N4: ='Dashboard Calc'!J4 -> 2965
A5: 🔁 CLARO TROCA | D5: 📈 ATTACHMENT | G5: 🎯 PDVs ELEGÍVEIS | J5: 🧩 GRUPOS A ATIVAR | M5: 46113 | N5: ='Dashboard Calc'!J5 -> 2364
A6: =SUMIFS(BASE!$G:$G,BASE!$A:$A,$B$3) -> 3844 | D6: =IFERROR(SUMIFS(BASE!$G:$G,BASE!$A:$A,$B$3)/SUMIFS(BASE!$F:$F,BASE!$A:$A,$B$3),0) -> 0.12726791 | G6: =SUM('Dashboard Calc'!$E$2:$E$11) -> 937 | J6: ='GRUPOS ZERADOS'!D16 -> 110 | M6: 46143 | N6: ='Dashboard Calc'!J6 -> 2940
M7: 46174 | N7: ='Dashboard Calc'!J7 -> 3007
M8: 46204 | N8: ='Dashboard Calc'!J8 -> 5021
A9: ="💡 Em "&TEXT($B$3,"mmm/aa")&", o Brasil registrou "&TEXT($A$6,"#.##0")&" trocas e "&TEXT($D$6,"0,0%")&" de Attachment. Há "&TEXT($J$6,"#.##0")&" de "&TEXT('GRUPOS ZERADOS'!B16,"#.##0")&" grupos a ativar ("&TEXT('GRUPOS ZERADOS'!F16,"0%")&" zerados), reforçando o potencial comercial." -> 💡 Em ago/26, o Brasil registrou 3.844 trocas e 12,7% de Attachment. Há 110 de 159 grupos a ativar (69% zerados), reforçando o potencial comercial. | M9: 46235 | N9: ='Dashboard Calc'!J9 -> 3844
M10: ='Dashboard Calc'!I10 -> 46266 | N10: ='Dashboard Calc'!J10
M11: ='Dashboard Calc'!I11 -> 46296 | N11: ='Dashboard Calc'!J11
M12: ='Dashboard Calc'!I12 -> 46327 | N12: ='Dashboard Calc'!J12
M13: ='Dashboard Calc'!I13 -> 46357 | N13: ='Dashboard Calc'!J13
A25: ⚠️ PRIORIDADES REGIONAIS — MENOR CONVERSÃO | H25: 🏆 TOP 5 PARCEIROS — ATTACHMENT
A26: REGIONAL | B26: ELEGÍVEIS | C26: ATIVOS | D26: CONVERSÃO | E26: GAP | F26: SINAL | H26: RANK | I26: PARCEIRO | J26: SELLOUT | K26: TROCAS | L26: ATTACHMENT
A27: {=_xlfn.TAKE(_xlfn.SORTBY(_xlfn.HSTACK('Dashboard Calc'!$A$2:$A$11,'Dashboard Calc'!$E$2:$E$11,'Dashboard Calc'!$F$2:$F$11,'Dashboard Calc'!$G$2:$G$11,'Dashboard Calc'!$E$2:$E$11-'Dashboard Calc'!$F$2:$F$11),'Dashboard Calc'!$G$2:$G$11,1),5)} -> NO | B27: 24 | C27: 2 | D27: 0.083333333 | E27: 22 | F27: =IF(D27<10%,"CRÍTICA",IF(D27<25%,"ATENÇÃO","ACOMPANHAR")) -> CRÍTICA | H27: {=_xlfn.TAKE('TOP 10 Parceiros'!$A$8:$E$17,5)} -> 1 | I27: FAJULUTI | J27: 1656 | K27: 494 | L27: 0.29830918
A28: MG | B28: 89 | C28: 30 | D28: 0.33707865 | E28: 59 | F28: =IF(D28<10%,"CRÍTICA",IF(D28<25%,"ATENÇÃO","ACOMPANHAR")) -> ACOMPANHAR | H28: 2 | I28: HS TELECOM | J28: 3700 | K28: 1065 | L28: 0.28783784
A29: NE | B29: 75 | C29: 27 | D29: 0.36 | E29: 48 | F29: =IF(D29<10%,"CRÍTICA",IF(D29<25%,"ATENÇÃO","ACOMPANHAR")) -> ACOMPANHAR | H29: 3 | I29: VIRACLARO | J29: 21 | K29: 6 | L29: 0.28571429
A30: BA/SE | B30: 61 | C30: 26 | D30: 0.42622951 | E30: 35 | F30: =IF(D30<10%,"CRÍTICA",IF(D30<25%,"ATENÇÃO","ACOMPANHAR")) -> ACOMPANHAR | H30: 4 | I30: DOM BARRETO COMERCIAL LTDA - ME | J30: 81 | K30: 21 | L30: 0.25925926
A31: CO | B31: 187 | C31: 88 | D31: 0.47058824 | E31: 99 | F31: =IF(D31<10%,"CRÍTICA",IF(D31<25%,"ATENÇÃO","ACOMPANHAR")) -> ACOMPANHAR | H31: 5 | I31: BANDEIRA | J31: 313 | K31: 74 | L31: 0.23642173

Sheet REGIONAL
A1: CANAL AA |CLARO TROCA |REGIONAL
D4: QTDE PDVS
A5: REGIONAL | B5: PDVs | C5: ELEGÍVEIS | D5: COM TROCAS | E5: ZERADO | F5: COBERTURA TOTAL | G5: ZERADOS / ELEGÍVEIS
A6: SP1 | B6: =COUNTIFS(PDVS!G:G,A6) -> 70 | C6: =COUNTIFS(PDVS!G:G,A6,PDVS!J:J,"SIM") -> 70 | D6: =COUNTIFS(PDVS!$X:$X,D$5,PDVS!$G:$G,$A6,PDVS!J:J,"SIM") -> 40 | E6: =COUNTIFS(PDVS!$X:$X,E$5,PDVS!$G:$G,$A6,PDVS!$J:$J,"SIM") -> 30 | F6: =D6/B6 -> 0.57142857 | G6: =IFERROR(E6/C6,0) -> 0.42857143
A7: SP2 | B7: =COUNTIFS(PDVS!G:G,A7) -> 180 | C7: =COUNTIFS(PDVS!G:G,A7,PDVS!J:J,"SIM") -> 170 | D7: =COUNTIFS(PDVS!$X:$X,D$5,PDVS!$G:$G,$A7,PDVS!J:J,"SIM") -> 110 | E7: =COUNTIFS(PDVS!$X:$X,E$5,PDVS!$G:$G,$A7,PDVS!$J:$J,"SIM") -> 60 | F7: =D7/B7 -> 0.61111111 | G7: =IFERROR(E7/C7,0) -> 0.35294118
A8: RJ/ES | B8: =COUNTIFS(PDVS!G:G,A8) -> 97 | C8: =COUNTIFS(PDVS!G:G,A8,PDVS!J:J,"SIM") -> 97 | D8: =COUNTIFS(PDVS!$X:$X,D$5,PDVS!$G:$G,$A8,PDVS!J:J,"SIM") -> 72 | E8: =COUNTIFS(PDVS!$X:$X,E$5,PDVS!$G:$G,$A8,PDVS!$J:$J,"SIM") -> 25 | F8: =D8/B8 -> 0.74226804 | G8: =IFERROR(E8/C8,0) -> 0.25773196
A9: MG | B9: =COUNTIFS(PDVS!G:G,A9) -> 93 | C9: =COUNTIFS(PDVS!G:G,A9,PDVS!J:J,"SIM") -> 89 | D9: =COUNTIFS(PDVS!$X:$X,D$5,PDVS!$G:$G,$A9,PDVS!J:J,"SIM") -> 30 | E9: =COUNTIFS(PDVS!$X:$X,E$5,PDVS!$G:$G,$A9,PDVS!$J:$J,"SIM") -> 59 | F9: =D9/B9 -> 0.32258065 | G9: =IFERROR(E9/C9,0) -> 0.66292135
A10: PR/SC | B10: =COUNTIFS(PDVS!G:G,A10) -> 88 | C10: =COUNTIFS(PDVS!G:G,A10,PDVS!J:J,"SIM") -> 85 | D10: =COUNTIFS(PDVS!$X:$X,D$5,PDVS!$G:$G,$A10,PDVS!J:J,"SIM") -> 49 | E10: =COUNTIFS(PDVS!$X:$X,E$5,PDVS!$G:$G,$A10,PDVS!$J:$J,"SIM") -> 36 | F10: =D10/B10 -> 0.55681818 | G10: =IFERROR(E10/C10,0) -> 0.42352941
A11: RS | B11: =COUNTIFS(PDVS!G:G,A11) -> 81 | C11: =COUNTIFS(PDVS!G:G,A11,PDVS!J:J,"SIM") -> 79 | D11: =COUNTIFS(PDVS!$X:$X,D$5,PDVS!$G:$G,$A11,PDVS!J:J,"SIM") -> 46 | E11: =COUNTIFS(PDVS!$X:$X,E$5,PDVS!$G:$G,$A11,PDVS!$J:$J,"SIM") -> 33 | F11: =D11/B11 -> 0.56790123 | G11: =IFERROR(E11/C11,0) -> 0.41772152
A12: CO | B12: =COUNTIFS(PDVS!G:G,A12) -> 197 | C12: =COUNTIFS(PDVS!G:G,A12,PDVS!J:J,"SIM") -> 187 | D12: =COUNTIFS(PDVS!$X:$X,D$5,PDVS!$G:$G,$A12,PDVS!J:J,"SIM") -> 88 | E12: =COUNTIFS(PDVS!$X:$X,E$5,PDVS!$G:$G,$A12,PDVS!$J:$J,"SIM") -> 99 | F12: =D12/B12 -> 0.44670051 | G12: =IFERROR(E12/C12,0) -> 0.52941176
A13: BA/SE | B13: =COUNTIFS(PDVS!G:G,A13) -> 62 | C13: =COUNTIFS(PDVS!G:G,A13,PDVS!J:J,"SIM") -> 61 | D13: =COUNTIFS(PDVS!$X:$X,D$5,PDVS!$G:$G,$A13,PDVS!J:J,"SIM") -> 26 | E13: =COUNTIFS(PDVS!$X:$X,E$5,PDVS!$G:$G,$A13,PDVS!$J:$J,"SIM") -> 35 | F13: =D13/B13 -> 0.41935484 | G13: =IFERROR(E13/C13,0) -> 0.57377049
A14: NE | B14: =COUNTIFS(PDVS!G:G,A14) -> 96 | C14: =COUNTIFS(PDVS!G:G,A14,PDVS!J:J,"SIM") -> 75 | D14: =COUNTIFS(PDVS!$X:$X,D$5,PDVS!$G:$G,$A14,PDVS!J:J,"SIM") -> 27 | E14: =COUNTIFS(PDVS!$X:$X,E$5,PDVS!$G:$G,$A14,PDVS!$J:$J,"SIM") -> 48 | F14: =D14/B14 -> 0.28125 | G14: =IFERROR(E14/C14,0) -> 0.64
A15: NO | B15: =COUNTIFS(PDVS!G:G,A15) -> 43 | C15: =COUNTIFS(PDVS!G:G,A15,PDVS!J:J,"SIM") -> 24 | D15: =COUNTIFS(PDVS!$X:$X,D$5,PDVS!$G:$G,$A15,PDVS!J:J,"SIM") -> 2 | E15: =COUNTIFS(PDVS!$X:$X,E$5,PDVS!$G:$G,$A15,PDVS!$J:$J,"SIM") -> 22 | F15: =D15/B15 -> 0.046511628 | G15: =IFERROR(E15/C15,0) -> 0.91666667
A16: BR | B16: =SUM(B6:B15) -> 1007 | C16: =SUM(C6:C15) -> 937 | D16: =SUM(D6:D15) -> 490 | E16: =SUM(E6:E15) -> 447 | F16: =D16/B16 -> 0.48659384 | G16: =IFERROR(E16/C16,0) -> 0.47705443
C19: COM BOOST
C20: SEM REPASSE

Sheet TOP 10 Parceiros
A1: TOP 10 PARCEIROS BRASIL — ATTACHMENT | H1: Meses disponíveis
A2: Visão mensal consolidada por Grupo Rede, somando todas as regionais e sem corte mínimo de Sellout. | H2: {=_xlfn._xlws.SORT(_xlfn.UNIQUE(_xlfn._xlws.FILTER(BASE!$A$2:$A$10000,BASE!$A$2:$A$10000<>"")))} -> 46023
A3: MÊS | B3: 46235 | C3: LÍDER | D3: =IFERROR(INDEX(_xlfn.ANCHORARRAY($B$8),1,1),"") -> FAJULUTI | G3: =IFERROR(INDEX(_xlfn.ANCHORARRAY($B$8),1,4),0) -> 0.29830918 | H3: 46054
H4: 46082
A5: ="Em "&TEXT($B$3,"mmm")&"/"&TEXT(MOD(YEAR($B$3),100),"00")&", "&INDEX(_xlfn.ANCHORARRAY($B$8),1,1)&" lidera o Brasil com "&TEXT(INDEX(_xlfn.ANCHORARRAY($B$8),1,4),"0,0%")&" de Attachment: "&FIXED(INDEX(_xlfn.ANCHORARRAY($B$8),1,3),0,FALSE)&" Claro Trocas sobre "&FIXED(INDEX(_xlfn.ANCHORARRAY($B$8),1,2),0,FALSE)&" aparelhos de Sellout." -> Em ago/26, FAJULUTI lidera o Brasil com 29,8% de Attachment: 494 Claro Trocas sobre 1.656 aparelhos de Sellout. | H5: 46113
A6: RANKING NACIONAL | H6: 46143
A7: RANK | B7: PARCEIRO / GRUPO REDE | C7: SELLOUT | D7: CLARO TROCA | E7: ATTACHMENT | F7: Nº REGIONAIS | G7: REGIONAIS | H7: 46174
A8: {=_xlfn.SEQUENCE(ROWS(_xlfn.ANCHORARRAY(B8)))} -> 1 | B8: {=_xlfn.LET(_xlpm.m,$B$3,_xlpm.gr,IFERROR(BASE!$J$2:$J$10000,""),_xlpm.g,_xlfn.UNIQUE(_xlfn._xlws.FILTER(_xlpm.gr,(BASE!$A$2:$A$10000=_xlpm.m)*(_xlpm.gr<>""))),_xlpm.s,_xlfn.MAP(_xlpm.g,_xlfn.LAMBDA(_xlpm.x,SUMPRODUCT((BASE!$A$2:$A$10000=_xlpm.m)*(_xlpm.gr=_xlpm.x)*IFERROR(BASE!$F$2:$F$10000,0)))),_xlpm.t,_xlfn.MAP(_xlpm.g,_xlfn.LAMBDA(_xlpm.x,SUMPRODUCT((BASE!$A$2:$A$10000=_xlpm.m)*(_xlpm.gr=_xlpm.x)*IFERROR(BASE!$G$2:$G$10000,0)))),_xlpm.a,IFERROR(_xlpm.t/_xlpm.s,0),_xlfn.TAKE(_xlfn.SORTBY(_xlfn.HSTACK(_xlpm.g,_xlpm.s,_xlpm.t,_xlpm.a),_xlpm.a,-1,_xlpm.t,-1),MIN(10,ROWS(_xlpm.g))))} -> FAJULUTI | C8: 1656 | D8: 494 | E8: 0.29830918 | F8: {=IF(B8="","",COUNTA(_xlfn.UNIQUE(_xlfn._xlws.FILTER(IFERROR(BASE!$L$2:$L$10000,""),(BASE!$A$2:$A$10000=$B$3)*(IFERROR(BASE!$J$2:$J$10000,"")=B8)*(IFERROR(BASE!$L$2:$L$10000,"")<>"")))))} -> 2 | G8: {=IF(B8="","",_xlfn.TEXTJOIN(", ",TRUE,_xlfn._xlws.SORT(_xlfn.UNIQUE(_xlfn._xlws.FILTER(IFERROR(BASE!$L$2:$L$10000,""),(BASE!$A$2:$A$10000=$B$3)*(IFERROR(BASE!$J$2:$J$10000,"")=B8)*(IFERROR(BASE!$L$2:$L$10000,"")<>""))))))} -> MG, RJ/ES | H8: 46204
A9: 2 | B9: HS TELECOM | C9: 3700 | D9: 1065 | E9: 0.28783784 | F9: {=IF(B9="","",COUNTA(_xlfn.UNIQUE(_xlfn._xlws.FILTER(IFERROR(BASE!$L$2:$L$10000,""),(BASE!$A$2:$A$10000=$B$3)*(IFERROR(BASE!$J$2:$J$10000,"")=B9)*(IFERROR(BASE!$L$2:$L$10000,"")<>"")))))} -> 3 | G9: {=IF(B9="","",_xlfn.TEXTJOIN(", ",TRUE,_xlfn._xlws.SORT(_xlfn.UNIQUE(_xlfn._xlws.FILTER(IFERROR(BASE!$L$2:$L$10000,""),(BASE!$A$2:$A$10000=$B$3)*(IFERROR(BASE!$J$2:$J$10000,"")=B9)*(IFERROR(BASE!$L$2:$L$10000,"")<>""))))))} -> BA/SE, RJ/ES, SP2 | H9: 46235
A10: 3 | B10: VIRACLARO | C10: 21 | D10: 6 | E10: 0.28571429 | F10: {=IF(B10="","",COUNTA(_xlfn.UNIQUE(_xlfn._xlws.FILTER(IFERROR(BASE!$L$2:$L$10000,""),(BASE!$A$2:$A$10000=$B$3)*(IFERROR(BASE!$J$2:$J$10000,"")=B10)*(IFERROR(BASE!$L$2:$L$10000,"")<>"")))))} -> 1 | G10: {=IF(B10="","",_xlfn.TEXTJOIN(", ",TRUE,_xlfn._xlws.SORT(_xlfn.UNIQUE(_xlfn._xlws.FILTER(IFERROR(BASE!$L$2:$L$10000,""),(BASE!$A$2:$A$10000=$B$3)*(IFERROR(BASE!$J$2:$J$10000,"")=B10)*(IFERROR(BASE!$L$2:$L$10000,"")<>""))))))} -> SP2
A11: 4 | B11: DOM BARRETO COMERCIAL LTDA - ME | C11: 81 | D11: 21 | E11: 0.25925926 | F11: {=IF(B11="","",COUNTA(_xlfn.UNIQUE(_xlfn._xlws.FILTER(IFERROR(BASE!$L$2:$L$10000,""),(BASE!$A$2:$A$10000=$B$3)*(IFERROR(BASE!$J$2:$J$10000,"")=B11)*(IFERROR(BASE!$L$2:$L$10000,"")<>"")))))} -> 1 | G11: {=IF(B11="","",_xlfn.TEXTJOIN(", ",TRUE,_xlfn._xlws.SORT(_xlfn.UNIQUE(_xlfn._xlws.FILTER(IFERROR(BASE!$L$2:$L$10000,""),(BASE!$A$2:$A$10000=$B$3)*(IFERROR(BASE!$J$2:$J$10000,"")=B11)*(IFERROR(BASE!$L$2:$L$10000,"")<>""))))))} -> SP2
A12: 5 | B12: BANDEIRA | C12: 313 | D12: 74 | E12: 0.23642173 | F12: {=IF(B12="","",COUNTA(_xlfn.UNIQUE(_xlfn._xlws.FILTER(IFERROR(BASE!$L$2:$L$10000,""),(BASE!$A$2:$A$10000=$B$3)*(IFERROR(BASE!$J$2:$J$10000,"")=B12)*(IFERROR(BASE!$L$2:$L$10000,"")<>"")))))} -> 1 | G12: {=IF(B12="","",_xlfn.TEXTJOIN(", ",TRUE,_xlfn._xlws.SORT(_xlfn.UNIQUE(_xlfn._xlws.FILTER(IFERROR(BASE!$L$2:$L$10000,""),(BASE!$A$2:$A$10000=$B$3)*(IFERROR(BASE!$J$2:$J$10000,"")=B12)*(IFERROR(BASE!$L$2:$L$10000,"")<>""))))))} -> PR/SC
A13: 6 | B13: R & R HIPER COMERCIO LTDA | C13: 247 | D13: 51 | E13: 0.20647773 | F13: {=IF(B13="","",COUNTA(_xlfn.UNIQUE(_xlfn._xlws.FILTER(IFERROR(BASE!$L$2:$L$10000,""),(BASE!$A$2:$A$10000=$B$3)*(IFERROR(BASE!$J$2:$J$10000,"")=B13)*(IFERROR(BASE!$L$2:$L$10000,"")<>"")))))} -> 1 | G13: {=IF(B13="","",_xlfn.TEXTJOIN(", ",TRUE,_xlfn._xlws.SORT(_xlfn.UNIQUE(_xlfn._xlws.FILTER(IFERROR(BASE!$L$2:$L$10000,""),(BASE!$A$2:$A$10000=$B$3)*(IFERROR(BASE!$J$2:$J$10000,"")=B13)*(IFERROR(BASE!$L$2:$L$10000,"")<>""))))))} -> NE
A14: 7 | B14: ADESIENE NUNES MACHADO - ME | C14: 96 | D14: 19 | E14: 0.19791667 | F14: {=IF(B14="","",COUNTA(_xlfn.UNIQUE(_xlfn._xlws.FILTER(IFERROR(BASE!$L$2:$L$10000,""),(BASE!$A$2:$A$10000=$B$3)*(IFERROR(BASE!$J$2:$J$10000,"")=B14)*(IFERROR(BASE!$L$2:$L$10000,"")<>"")))))} -> 1 | G14: {=IF(B14="","",_xlfn.TEXTJOIN(", ",TRUE,_xlfn._xlws.SORT(_xlfn.UNIQUE(_xlfn._xlws.FILTER(IFERROR(BASE!$L$2:$L$10000,""),(BASE!$A$2:$A$10000=$B$3)*(IFERROR(BASE!$J$2:$J$10000,"")=B14)*(IFERROR(BASE!$L$2:$L$10000,"")<>""))))))} -> SP2
A15: 8 | B15: HARCOS COMERCIO E SERVICOS LTDA - EPP | C15: 1067 | D15: 210 | E15: 0.1968135 | F15: {=IF(B15="","",COUNTA(_xlfn.UNIQUE(_xlfn._xlws.FILTER(IFERROR(BASE!$L$2:$L$10000,""),(BASE!$A$2:$A$10000=$B$3)*(IFERROR(BASE!$J$2:$J$10000,"")=B15)*(IFERROR(BASE!$L$2:$L$10000,"")<>"")))))} -> 1 | G15: {=IF(B15="","",_xlfn.TEXTJOIN(", ",TRUE,_xlfn._xlws.SORT(_xlfn.UNIQUE(_xlfn._xlws.FILTER(IFERROR(BASE!$L$2:$L$10000,""),(BASE!$A$2:$A$10000=$B$3)*(IFERROR(BASE!$J$2:$J$10000,"")=B15)*(IFERROR(BASE!$L$2:$L$10000,"")<>""))))))} -> NE
A16: 9 | B16: CELNET COMERCIO E SERVICOS DE TELEFONIA LTDA ME | C16: 1186 | D16: 212 | E16: 0.17875211 | F16: {=IF(B16="","",COUNTA(_xlfn.UNIQUE(_xlfn._xlws.FILTER(IFERROR(BASE!$L$2:$L$10000,""),(BASE!$A$2:$A$10000=$B$3)*(IFERROR(BASE!$J$2:$J$10000,"")=B16)*(IFERROR(BASE!$L$2:$L$10000,"")<>"")))))} -> 1 | G16: {=IF(B16="","",_xlfn.TEXTJOIN(", ",TRUE,_xlfn._xlws.SORT(_xlfn.UNIQUE(_xlfn._xlws.FILTER(IFERROR(BASE!$L$2:$L$10000,""),(BASE!$A$2:$A$10000=$B$3)*(IFERROR(BASE!$J$2:$J$10000,"")=B16)*(IFERROR(BASE!$L$2:$L$10000,"")<>""))))))} -> CO
A17: 10 | B17: FLEX CELL | C17: 1904 | D17: 323 | E17: 0.16964286 | F17: {=IF(B17="","",COUNTA(_xlfn.UNIQUE(_xlfn._xlws.FILTER(IFERROR(BASE!$L$2:$L$10000,""),(BASE!$A$2:$A$10000=$B$3)*(IFERROR(BASE!$J$2:$J$10000,"")=B17)*(IFERROR(BASE!$L$2:$L$10000,"")<>"")))))} -> 3 | G17: {=IF(B17="","",_xlfn.TEXTJOIN(", ",TRUE,_xlfn._xlws.SORT(_xlfn.UNIQUE(_xlfn._xlws.FILTER(IFERROR(BASE!$L$2:$L$10000,""),(BASE!$A$2:$A$10000=$B$3)*(IFERROR(BASE!$J$2:$J$10000,"")=B17)*(IFERROR(BASE!$L$2:$L$10000,"")<>""))))))} -> NO, SP1, SP2

Sheet GRUPOS ZERADOS
A1: CANAL AA |CLARO TROCA |GRUPOS REDES
C4: GRUPOS REDES
A5: REG | B5: GRUPOS | C5: COM TROCAS | D5: ZERADO | E5: % COM VENDAS | F5: % ZERADOS
A6: SP1 | B6: =COUNTIFS(GRUPOS!C:C,A6,GRUPOS!$F:$F,"SIM") -> 9 | C6: =COUNTIFS(GRUPOS!$T:$T,$C$5,GRUPOS!$C:$C,$A6,GRUPOS!$F:$F,"SIM") -> 4 | D6: =COUNTIFS(GRUPOS!$T:$T,$D$5,GRUPOS!$C:$C,$A6,GRUPOS!F:F,"SIM") -> 5 | E6: =C6/B6 -> 0.44444444 | F6: =D6/B6 -> 0.55555556
A7: SP2 | B7: =COUNTIFS(GRUPOS!C:C,A7,GRUPOS!$F:$F,"SIM") -> 16 | C7: =COUNTIFS(GRUPOS!$T:$T,$C$5,GRUPOS!$C:$C,$A7,GRUPOS!F:F,"SIM") -> 10 | D7: =COUNTIFS(GRUPOS!$T:$T,$D$5,GRUPOS!$C:$C,$A7,GRUPOS!F:F,"SIM") -> 6 | E7: =C7/B7 -> 0.625 | F7: =D7/B7 -> 0.375
A8: RJ/ES | B8: =COUNTIFS(GRUPOS!C:C,A8,GRUPOS!$F:$F,"SIM") -> 10 | C8: =COUNTIFS(GRUPOS!$T:$T,$C$5,GRUPOS!$C:$C,$A8,GRUPOS!F:F,"SIM") -> 6 | D8: =COUNTIFS(GRUPOS!$T:$T,$D$5,GRUPOS!$C:$C,$A8,GRUPOS!F:F,"SIM") -> 4 | E8: =C8/B8 -> 0.6 | F8: =D8/B8 -> 0.4
A9: MG | B9: =COUNTIFS(GRUPOS!C:C,A9,GRUPOS!$F:$F,"SIM") -> 22 | C9: =COUNTIFS(GRUPOS!$T:$T,$C$5,GRUPOS!$C:$C,$A9,GRUPOS!F:F,"SIM") -> 4 | D9: =COUNTIFS(GRUPOS!$T:$T,$D$5,GRUPOS!$C:$C,$A9,GRUPOS!F:F,"SIM") -> 18 | E9: =C9/B9 -> 0.18181818 | F9: =D9/B9 -> 0.81818182
A10: PR/SC | B10: =COUNTIFS(GRUPOS!C:C,A10,GRUPOS!$F:$F,"SIM") -> 5 | C10: =COUNTIFS(GRUPOS!$T:$T,$C$5,GRUPOS!$C:$C,$A10,GRUPOS!F:F,"SIM") -> 4 | D10: =COUNTIFS(GRUPOS!$T:$T,$D$5,GRUPOS!$C:$C,$A10,GRUPOS!F:F,"SIM") -> 1 | E10: =C10/B10 -> 0.8 | F10: =D10/B10 -> 0.2
A11: RS | B11: =COUNTIFS(GRUPOS!C:C,A11,GRUPOS!$F:$F,"SIM") -> 5 | C11: =COUNTIFS(GRUPOS!$T:$T,$C$5,GRUPOS!$C:$C,$A11,GRUPOS!F:F,"SIM") -> 4 | D11: =COUNTIFS(GRUPOS!$T:$T,$D$5,GRUPOS!$C:$C,$A11,GRUPOS!F:F,"SIM") -> 1 | E11: =C11/B11 -> 0.8 | F11: =D11/B11 -> 0.2
A12: CO | B12: =COUNTIFS(GRUPOS!C:C,A12,GRUPOS!$F:$F,"SIM") -> 39 | C12: =COUNTIFS(GRUPOS!$T:$T,$C$5,GRUPOS!$C:$C,$A12,GRUPOS!F:F,"SIM") -> 7 | D12: =COUNTIFS(GRUPOS!$T:$T,$D$5,GRUPOS!$C:$C,$A12,GRUPOS!F:F,"SIM") -> 32 | E12: =C12/B12 -> 0.17948718 | F12: =D12/B12 -> 0.82051282
A13: BA/SE | B13: =COUNTIFS(GRUPOS!C:C,A13,GRUPOS!$F:$F,"SIM") -> 24 | C13: =COUNTIFS(GRUPOS!$T:$T,$C$5,GRUPOS!$C:$C,$A13,GRUPOS!F:F,"SIM") -> 5 | D13: =COUNTIFS(GRUPOS!$T:$T,$D$5,GRUPOS!$C:$C,$A13,GRUPOS!F:F,"SIM") -> 19 | E13: =C13/B13 -> 0.20833333 | F13: =D13/B13 -> 0.79166667
A14: NE | B14: =COUNTIFS(GRUPOS!C:C,A14,GRUPOS!$F:$F,"SIM") -> 17 | C14: =COUNTIFS(GRUPOS!$T:$T,$C$5,GRUPOS!$C:$C,$A14,GRUPOS!F:F,"SIM") -> 3 | D14: =COUNTIFS(GRUPOS!$T:$T,$D$5,GRUPOS!$C:$C,$A14,GRUPOS!F:F,"SIM") -> 14 | E14: =C14/B14 -> 0.17647059 | F14: =D14/B14 -> 0.82352941
A15: NO | B15: =COUNTIFS(GRUPOS!C:C,A15,GRUPOS!$F:$F,"SIM") -> 12 | C15: =COUNTIFS(GRUPOS!$T:$T,$C$5,GRUPOS!$C:$C,$A15,GRUPOS!F:F,"SIM") -> 2 | D15: =COUNTIFS(GRUPOS!$T:$T,$D$5,GRUPOS!$C:$C,$A15,GRUPOS!F:F,"SIM") -> 10 | E15: =C15/B15 -> 0.16666667 | F15: =D15/B15 -> 0.83333333
A16: BR | B16: =SUM(B6:B15) -> 159 | C16: =SUM(C6:C15) -> 49 | D16: =SUM(D6:D15) -> 110 | E16: =C16/B16 -> 0.3081761 | F16: =D16/B16 -> 0.6918239

Sheet GRUPOS
B6: GRUPOS | C6: REGIONAIS | D6: REPASSES | E6: BOOST LIBERADOS | F6: ELEGÍVEL | G6: 46023 | H6: 46054 | I6: 46082 | J6: 46113 | K6: 46143 | L6: 46174 | M6: 46204 | N6: 46235 | O6: 46266 | P6: 46296 | Q6: 46327 | R6: 46357 | T6: STATUS
B7: A C DE OLIVEIRA PINHEIRO & FILHO LTDA. | C7: NE | D7: =COUNTIFS(PDVS!H:H,"SIM",PDVS!C:C,B7) -> 0 | E7: =COUNTIFS(PDVS!C:C,B7,PDVS!I:I,"SIM") -> 0 | F7: =IF(AND(D7=0,E7>=1),"Sim",IF(D7>=1,"Não",IF(AND(D7=0,E7=0),"Sim",""))) -> Sim | G7: =SUMIFS(BASE!$G:$G,BASE!$L:$L,$C7,BASE!$J:$J,$B7,BASE!$A:$A,G$6) -> 0 | H7: =SUMIFS(BASE!$G:$G,BASE!$L:$L,$C7,BASE!$J:$J,$B7,BASE!$A:$A,H$6) -> 0 | I7: =SUMIFS(BASE!$G:$G,BASE!$L:$L,$C7,BASE!$J:$J,$B7,BASE!$A:$A,I$6) -> 0 | J7: =SUMIFS(BASE!$G:$G,BASE!$L:$L,$C7,BASE!$J:$J,$B7,BASE!$A:$A,J$6) -> 0 | K7: =SUMIFS(BASE!$G:$G,BASE!$L:$L,$C7,BASE!$J:$J,$B7,BASE!$A:$A,K$6) -> 0 | L7: =SUMIFS(BASE!$G:$G,BASE!$L:$L,$C7,BASE!$J:$J,$B7,BASE!$A:$A,L$6) -> 0 | M7: =SUMIFS(BASE!$G:$G,BASE!$L:$L,$C7,BASE!$J:$J,$B7,BASE!$A:$A,M$6) -> 0 | N7: =SUMIFS(BASE!$G:$G,BASE!$L:$L,$C7,BASE!$J:$J,$B7,BASE!$A:$A,N$6) -> 0 | ... R7: =SUMIFS(BASE!$G:$G,BASE!$L:$L,$C7,BASE!$J:$J,$B7,BASE!$A:$A,R$6) -> 0 | T7: =IF(AND(N7=0),"ZERADO","COM TROCAS") -> ZERADO
B8: A PLAY S COMERCIO E SERVICOS LTDA | C8: BA/SE | D8: =COUNTIFS(PDVS!H:H,"SIM",PDVS!C:C,B8) -> 0 | E8: =COUNTIFS(PDVS!C:C,B8,PDVS!I:I,"SIM") -> 1 | F8: =IF(AND(D8=0,E8>=1),"Sim",IF(D8>=1,"Não",IF(AND(D8=0,E8=0),"Sim",""))) -> Sim | G8: =SUMIFS(BASE!$G:$G,BASE!$L:$L,$C8,BASE!$J:$J,$B8,BASE!$A:$A,G$6) -> 0 | H8: =SUMIFS(BASE!$G:$G,BASE!$L:$L,$C8,BASE!$J:$J,$B8,BASE!$A:$A,H$6) -> 0 | I8: =SUMIFS(BASE!$G:$G,BASE!$L:$L,$C8,BASE!$J:$J,$B8,BASE!$A:$A,I$6) -> 0 | J8: =SUMIFS(BASE!$G:$G,BASE!$L:$L,$C8,BASE!$J:$J,$B8,BASE!$A:$A,J$6) -> 0 | K8: =SUMIFS(BASE!$G:$G,BASE!$L:$L,$C8,BASE!$J:$J,$B8,BASE!$A:$A,K$6) -> 0 | L8: =SUMIFS(BASE!$G:$G,BASE!$L:$L,$C8,BASE!$J:$J,$B8,BASE!$A:$A,L$6) -> 0 | M8: =SUMIFS(BASE!$G:$G,BASE!$L:$L,$C8,BASE!$J:$J,$B8,BASE!$A:$A,M$6) -> 0 | N8: =SUMIFS(BASE!$G:$G,BASE!$L:$L,$C8,BASE!$J:$J,$B8,BASE!$A:$A,N$6) -> 0 | ... R8: =SUMIFS(BASE!$G:$G,BASE!$L:$L,$C8,BASE!$J:$J,$B8,BASE!$A:$A,R$6) -> 0 | T8: =IF(AND(N8=0),"ZERADO","COM TROCAS") -> ZERADO
B9: A. L. DE OLIVEIRA & CIA LTDA | C9: CO | D9: =COUNTIFS(PDVS!H:H,"SIM",PDVS!C:C,B9) -> 0 | E9: =COUNTIFS(PDVS!C:C,B9,PDVS!I:I,"SIM") -> 1 | F9: =IF(AND(D9=0,E9>=1),"Sim",IF(D9>=1,"Não",IF(AND(D9=0,E9=0),"Sim",""))) -> Sim | G9: =SUMIFS(BASE!$G:$G,BASE!$L:$L,$C9,BASE!$J:$J,$B9,BASE!$A:$A,G$6) -> 0 | H9: =SUMIFS(BASE!$G:$G,BASE!$L:$L,$C9,BASE!$J:$J,$B9,BASE!$A:$A,H$6) -> 0 | I9: =SUMIFS(BASE!$G:$G,BASE!$L:$L,$C9,BASE!$J:$J,$B9,BASE!$A:$A,I$6) -> 0 | J9: =SUMIFS(BASE!$G:$G,BASE!$L:$L,$C9,BASE!$J:$J,$B9,BASE!$A:$A,J$6) -> 0 | K9: =SUMIFS(BASE!$G:$G,BASE!$L:$L,$C9,BASE!$J:$J,$B9,BASE!$A:$A,K$6) -> 0 | L9: =SUMIFS(BASE!$G:$G,BASE!$L:$L,$C9,BASE!$J:$J,$B9,BASE!$A:$A,L$6) -> 0 | M9: =SUMIFS(BASE!$G:$G,BASE!$L:$L,$C9,BASE!$J:$J,$B9,BASE!$A:$A,M$6) -> 0 | N9: =SUMIFS(BASE!$G:$G,BASE!$L:$L,$C9,BASE!$J:$J,$B9,BASE!$A:$A,N$6) -> 0 | ... R9: =SUMIFS(BASE!$G:$G,BASE!$L:$L,$C9,BASE!$J:$J,$B9,BASE!$A:$A,R$6) -> 0 | T9: =IF(AND(N9=0),"ZERADO","COM TROCAS") -> ZERADO
B10: AC BAYLONGUE | C10: SP1 | D10: =COUNTIFS(PDVS!H:H,"SIM",PDVS!C:C,B10) -> 0 | E10: =COUNTIFS(PDVS!C:C,B10,PDVS!I:I,"SIM") -> 1 | F10: =IF(AND(D10=0,E10>=1),"Sim",IF(D10>=1,"Não",IF(AND(D10=0,E10=0),"Sim",""))) -> Sim | G10: =SUMIFS(BASE!$G:$G,BASE!$L:$L,$C10,BASE!$J:$J,$B10,BASE!$A:$A,G$6) -> 0 | H10: =SUMIFS(BASE!$G:$G,BASE!$L:$L,$C10,BASE!$J:$J,$B10,BASE!$A:$A,H$6) -> 0 | I10: =SUMIFS(BASE!$G:$G,BASE!$L:$L,$C10,BASE!$J:$J,$B10,BASE!$A:$A,I$6) -> 0 | J10: =SUMIFS(BASE!$G:$G,BASE!$L:$L,$C10,BASE!$J:$J,$B10,BASE!$A:$A,J$6) -> 0 | K10: =SUMIFS(BASE!$G:$G,BASE!$L:$L,$C10,BASE!$J:$J,$B10,BASE!$A:$A,K$6) -> 0 | L10: =SUMIFS(BASE!$G:$G,BASE!$L:$L,$C10,BASE!$J:$J,$B10,BASE!$A:$A,L$6) -> 0 | M10: =SUMIFS(BASE!$G:$G,BASE!$L:$L,$C10,BASE!$J:$J,$B10,BASE!$A:$A,M$6) -> 0 | N10: =SUMIFS(BASE!$G:$G,BASE!$L:$L,$C10,BASE!$J:$J,$B10,BASE!$A:$A,N$6) -> 0 | ... R10: =SUMIFS(BASE!$G:$G,BASE!$L:$L,$C10,BASE!$J:$J,$B10,BASE!$A:$A,R$6) -> 0 | T10: =IF(AND(N10=0),"ZERADO","COM TROCAS") -> ZERADO
B11: ALEXANDRE CISOTTO LAN HOUSE E TELECOMUNICACOES ME | C11: SP1 | D11: =COUNTIFS(PDVS!H:H,"SIM",PDVS!C:C,B11) -> 0 | E11: =COUNTIFS(PDVS!C:C,B11,PDVS!I:I,"SIM") -> 1 | F11: =IF(AND(D11=0,E11>=1),"Sim",IF(D11>=1,"Não",IF(AND(D11=0,E11=0),"Sim",""))) -> Sim | G11: =SUMIFS(BASE!$G:$G,BASE!$L:$L,$C11,BASE!$J:$J,$B11,BASE!$A:$A,G$6) -> 0 | H11: =SUMIFS(BASE!$G:$G,BASE!$L:$L,$C11,BASE!$J:$J,$B11,BASE!$A:$A,H$6) -> 0 | I11: =SUMIFS(BASE!$G:$G,BASE!$L:$L,$C11,BASE!$J:$J,$B11,BASE!$A:$A,I$6) -> 0 | J11: =SUMIFS(BASE!$G:$G,BASE!$L:$L,$C11,BASE!$J:$J,$B11,BASE!$A:$A,J$6) -> 0 | K11: =SUMIFS(BASE!$G:$G,BASE!$L:$L,$C11,BASE!$J:$J,$B11,BASE!$A:$A,K$6) -> 0 | L11: =SUMIFS(BASE!$G:$G,BASE!$L:$L,$C11,BASE!$J:$J,$B11,BASE!$A:$A,L$6) -> 0 | M11: =SUMIFS(BASE!$G:$G,BASE!$L:$L,$C11,BASE!$J:$J,$B11,BASE!$A:$A,M$6) -> 0 | N11: =SUMIFS(BASE!$G:$G,BASE!$L:$L,$C11,BASE!$J:$J,$B11,BASE!$A:$A,N$6) -> 0 | ... R11: =SUMIFS(BASE!$G:$G,BASE!$L:$L,$C11,BASE!$J:$J,$B11,BASE!$A:$A,R$6) -> 0 | T11: =IF(AND(N11=0),"ZERADO","COM TROCAS") -> ZERADO
B12: ALFA CELULAR LTDA | C12: MG | D12: =COUNTIFS(PDVS!H:H,"SIM",PDVS!C:C,B12) -> 1 | E12: =COUNTIFS(PDVS!C:C,B12,PDVS!I:I,"SIM") -> 3 | F12: =IF(AND(D12=0,E12>=1),"Sim",IF(D12>=1,"Não",IF(AND(D12=0,E12=0),"Sim",""))) -> Não | G12: =SUMIFS(BASE!$G:$G,BASE!$L:$L,$C12,BASE!$J:$J,$B12,BASE!$A:$A,G$6) -> 0 | H12: =SUMIFS(BASE!$G:$G,BASE!$L:$L,$C12,BASE!$J:$J,$B12,BASE!$A:$A,H$6) -> 0 | I12: =SUMIFS(BASE!$G:$G,BASE!$L:$L,$C12,BASE!$J:$J,$B12,BASE!$A:$A,I$6) -> 0 | J12: =SUMIFS(BASE!$G:$G,BASE!$L:$L,$C12,BASE!$J:$J,$B12,BASE!$A:$A,J$6) -> 0 | K12: =SUMIFS(BASE!$G:$G,BASE!$L:$L,$C12,BASE!$J:$J,$B12,BASE!$A:$A,K$6) -> 0 | L12: =SUMIFS(BASE!$G:$G,BASE!$L:$L,$C12,BASE!$J:$J,$B12,BASE!$A:$A,L$6) -> 0 | M12: =SUMIFS(BASE!$G:$G,BASE!$L:$L,$C12,BASE!$J:$J,$B12,BASE!$A:$A,M$6) -> 0 | N12: =SUMIFS(BASE!$G:$G,BASE!$L:$L,$C12,BASE!$J:$J,$B12,BASE!$A:$A,N$6) -> 0 | ... R12: =SUMIFS(BASE!$G:$G,BASE!$L:$L,$C12,BASE!$J:$J,$B12,BASE!$A:$A,R$6) -> 0 | T12: =IF(AND(N12=0),"ZERADO","COM TROCAS") -> ZERADO
B13: AM3 TELECOM LTDA | C13: NO | D13: =COUNTIFS(PDVS!H:H,"SIM",PDVS!C:C,B13) -> 0 | E13: =COUNTIFS(PDVS!C:C,B13,PDVS!I:I,"SIM") -> 0 | F13: =IF(AND(D13=0,E13>=1),"Sim",IF(D13>=1,"Não",IF(AND(D13=0,E13=0),"Sim",""))) -> Sim | G13: =SUMIFS(BASE!$G:$G,BASE!$L:$L,$C13,BASE!$J:$J,$B13,BASE!$A:$A,G$6) -> 0 | H13: =SUMIFS(BASE!$G:$G,BASE!$L:$L,$C13,BASE!$J:$J,$B13,BASE!$A:$A,H$6) -> 0 | I13: =SUMIFS(BASE!$G:$G,BASE!$L:$L,$C13,BASE!$J:$J,$B13,BASE!$A:$A,I$6) -> 0 | J13: =SUMIFS(BASE!$G:$G,BASE!$L:$L,$C13,BASE!$J:$J,$B13,BASE!$A:$A,J$6) -> 0 | K13: =SUMIFS(BASE!$G:$G,BASE!$L:$L,$C13,BASE!$J:$J,$B13,BASE!$A:$A,K$6) -> 0 | L13: =SUMIFS(BASE!$G:$G,BASE!$L:$L,$C13,BASE!$J:$J,$B13,BASE!$A:$A,L$6) -> 0 | M13: =SUMIFS(BASE!$G:$G,BASE!$L:$L,$C13,BASE!$J:$J,$B13,BASE!$A:$A,M$6) -> 0 | N13: =SUMIFS(BASE!$G:$G,BASE!$L:$L,$C13,BASE!$J:$J,$B13,BASE!$A:$A,N$6) -> 0 | ... R13: =SUMIFS(BASE!$G:$G,BASE!$L:$L,$C13,BASE!$J:$J,$B13,BASE!$A:$A,R$6) -> 0 | T13: =IF(AND(N13=0),"ZERADO","COM TROCAS") -> ZERADO
B14: AMOS MUNIZ CORREIA - ME | C14: CO | D14: =COUNTIFS(PDVS!H:H,"SIM",PDVS!C:C,B14) -> 0 | E14: =COUNTIFS(PDVS!C:C,B14,PDVS!I:I,"SIM") -> 1 | F14: =IF(AND(D14=0,E14>=1),"Sim",IF(D14>=1,"Não",IF(AND(D14=0,E14=0),"Sim",""))) -> Sim | G14: =SUMIFS(BASE!$G:$G,BASE!$L:$L,$C14,BASE!$J:$J,$B14,BASE!$A:$A,G$6) -> 0 | H14: =SUMIFS(BASE!$G:$G,BASE!$L:$L,$C14,BASE!$J:$J,$B14,BASE!$A:$A,H$6) -> 0 | I14: =SUMIFS(BASE!$G:$G,BASE!$L:$L,$C14,BASE!$J:$J,$B14,BASE!$A:$A,I$6) -> 0 | J14: =SUMIFS(BASE!$G:$G,BASE!$L:$L,$C14,BASE!$J:$J,$B14,BASE!$A:$A,J$6) -> 0 | K14: =SUMIFS(BASE!$G:$G,BASE!$L:$L,$C14,BASE!$J:$J,$B14,BASE!$A:$A,K$6) -> 0 | L14: =SUMIFS(BASE!$G:$G,BASE!$L:$L,$C14,BASE!$J:$J,$B14,BASE!$A:$A,L$6) -> 0 | M14: =SUMIFS(BASE!$G:$G,BASE!$L:$L,$C14,BASE!$J:$J,$B14,BASE!$A:$A,M$6) -> 0 | N14: =SUMIFS(BASE!$G:$G,BASE!$L:$L,$C14,BASE!$J:$J,$B14,BASE!$A:$A,N$6) -> 0 | ... R14: =SUMIFS(BASE!$G:$G,BASE!$L:$L,$C14,BASE!$J:$J,$B14,BASE!$A:$A,R$6) -> 0 | T14: =IF(AND(N14=0),"ZERADO","COM TROCAS") -> ZERADO
B15: ANA PAULA TARGINO TRINDADE | C15: NE | D15: =COUNTIFS(PDVS!H:H,"SIM",PDVS!C:C,B15) -> 0 | E15: =COUNTIFS(PDVS!C:C,B15,PDVS!I:I,"SIM") -> 1 | F15: =IF(AND(D15=0,E15>=1),"Sim",IF(D15>=1,"Não",IF(AND(D15=0,E15=0),"Sim",""))) -> Sim | G15: =SUMIFS(BASE!$G:$G,BASE!$L:$L,$C15,BASE!$J:$J,$B15,BASE!$A:$A,G$6) -> 0 | H15: =SUMIFS(BASE!$G:$G,BASE!$L:$L,$C15,BASE!$J:$J,$B15,BASE!$A:$A,H$6) -> 0 | I15: =SUMIFS(BASE!$G:$G,BASE!$L:$L,$C15,BASE!$J:$J,$B15,BASE!$A:$A,I$6) -> 0 | J15: =SUMIFS(BASE!$G:$G,BASE!$L:$L,$C15,BASE!$J:$J,$B15,BASE!$A:$A,J$6) -> 0 | K15: =SUMIFS(BASE!$G:$G,BASE!$L:$L,$C15,BASE!$J:$J,$B15,BASE!$A:$A,K$6) -> 0 | L15: =SUMIFS(BASE!$G:$G,BASE!$L:$L,$C15,BASE!$J:$J,$B15,BASE!$A:$A,L$6) -> 0 | M15: =SUMIFS(BASE!$G:$G,BASE!$L:$L,$C15,BASE!$J:$J,$B15,BASE!$A:$A,M$6) -> 0 | N15: =SUMIFS(BASE!$G:$G,BASE!$L:$L,$C15,BASE!$J:$J,$B15,BASE!$A:$A,N$6) -> 0 | ... R15: =SUMIFS(BASE!$G:$G,BASE!$L:$L,$C15,BASE!$J:$J,$B15,BASE!$A:$A,R$6) -> 0 | T15: =IF(AND(N15=0),"ZERADO","COM TROCAS") -> ZERADO
B16: ANTONIO LINDOMAR DE OLIVEIRA EPP | C16: CO | D16: =COUNTIFS(PDVS!H:H,"SIM",PDVS!C:C,B16) -> 0 | E16: =COUNTIFS(PDVS!C:C,B16,PDVS!I:I,"SIM") -> 1 | F16: =IF(AND(D16=0,E16>=1),"Sim",IF(D16>=1,"Não",IF(AND(D16=0,E16=0),"Sim",""))) -> Sim | G16: =SUMIFS(BASE!$G:$G,BASE!$L:$L,$C16,BASE!$J:$J,$B16,BASE!$A:$A,G$6) -> 0 | H16: =SUMIFS(BASE!$G:$G,BASE!$L:$L,$C16,BASE!$J:$J,$B16,BASE!$A:$A,H$6) -> 0 | I16: =SUMIFS(BASE!$G:$G,BASE!$L:$L,$C16,BASE!$J:$J,$B16,BASE!$A:$A,I$6) -> 0 | J16: =SUMIFS(BASE!$G:$G,BASE!$L:$L,$C16,BASE!$J:$J,$B16,BASE!$A:$A,J$6) -> 0 | K16: =SUMIFS(BASE!$G:$G,BASE!$L:$L,$C16,BASE!$J:$J,$B16,BASE!$A:$A,K$6) -> 0 | L16: =SUMIFS(BASE!$G:$G,BASE!$L:$L,$C16,BASE!$J:$J,$B16,BASE!$A:$A,L$6) -> 0 | M16: =SUMIFS(BASE!$G:$G,BASE!$L:$L,$C16,BASE!$J:$J,$B16,BASE!$A:$A,M$6) -> 0 | N16: =SUMIFS(BASE!$G:$G,BASE!$L:$L,$C16,BASE!$J:$J,$B16,BASE!$A:$A,N$6) -> 0 | ... R16: =SUMIFS(BASE!$G:$G,BASE!$L:$L,$C16,BASE!$J:$J,$B16,BASE!$A:$A,R$6) -> 0 | T16: =IF(AND(N16=0),"ZERADO","COM TROCAS") -> ZERADO
B17: ARES TELECOM LTDA | C17: CO | D17: =COUNTIFS(PDVS!H:H,"SIM",PDVS!C:C,B17) -> 0 | E17: =COUNTIFS(PDVS!C:C,B17,PDVS!I:I,"SIM") -> 0 | F17: =IF(AND(D17=0,E17>=1),"Sim",IF(D17>=1,"Não",IF(AND(D17=0,E17=0),"Sim",""))) -> Sim | G17: =SUMIFS(BASE!$G:$G,BASE!$L:$L,$C17,BASE!$J:$J,$B17,BASE!$A:$A,G$6) -> 0 | H17: =SUMIFS(BASE!$G:$G,BASE!$L:$L,$C17,BASE!$J:$J,$B17,BASE!$A:$A,H$6) -> 0 | I17: =SUMIFS(BASE!$G:$G,BASE!$L:$L,$C17,BASE!$J:$J,$B17,BASE!$A:$A,I$6) -> 0 | J17: =SUMIFS(BASE!$G:$G,BASE!$L:$L,$C17,BASE!$J:$J,$B17,BASE!$A:$A,J$6) -> 0 | K17: =SUMIFS(BASE!$G:$G,BASE!$L:$L,$C17,BASE!$J:$J,$B17,BASE!$A:$A,K$6) -> 0 | L17: =SUMIFS(BASE!$G:$G,BASE!$L:$L,$C17,BASE!$J:$J,$B17,BASE!$A:$A,L$6) -> 0 | M17: =SUMIFS(BASE!$G:$G,BASE!$L:$L,$C17,BASE!$J:$J,$B17,BASE!$A:$A,M$6) -> 0 | N17: =SUMIFS(BASE!$G:$G,BASE!$L:$L,$C17,BASE!$J:$J,$B17,BASE!$A:$A,N$6) -> 0 | ... R17: =SUMIFS(BASE!$G:$G,BASE!$L:$L,$C17,BASE!$J:$J,$B17,BASE!$A:$A,R$6) -> 0 | T17: =IF(AND(N17=0),"ZERADO","COM TROCAS") -> ZERADO
B18: ATENDE CELULAR LTDA - ME | C18: MG | D18: =COUNTIFS(PDVS!H:H,"SIM",PDVS!C:C,B18) -> 1 | E18: =COUNTIFS(PDVS!C:C,B18,PDVS!I:I,"SIM") -> 1 | F18: =IF(AND(D18=0,E18>=1),"Sim",IF(D18>=1,"Não",IF(AND(D18=0,E18=0),"Sim",""))) -> Não | G18: =SUMIFS(BASE!$G:$G,BASE!$L:$L,$C18,BASE!$J:$J,$B18,BASE!$A:$A,G$6) -> 0 | H18: =SUMIFS(BASE!$G:$G,BASE!$L:$L,$C18,BASE!$J:$J,$B18,BASE!$A:$A,H$6) -> 0 | I18: =SUMIFS(BASE!$G:$G,BASE!$L:$L,$C18,BASE!$J:$J,$B18,BASE!$A:$A,I$6) -> 0 | J18: =SUMIFS(BASE!$G:$G,BASE!$L:$L,$C18,BASE!$J:$J,$B18,BASE!$A:$A,J$6) -> 0 | K18: =SUMIFS(BASE!$G:$G,BASE!$L:$L,$C18,BASE!$J:$J,$B18,BASE!$A:$A,K$6) -> 0 | L18: =SUMIFS(BASE!$G:$G,BASE!$L:$L,$C18,BASE!$J:$J,$B18,BASE!$A:$A,L$6) -> 0 | M18: =SUMIFS(BASE!$G:$G,BASE!$L:$L,$C18,BASE!$J:$J,$B18,BASE!$A:$A,M$6) -> 0 | N18: =SUMIFS(BASE!$G:$G,BASE!$L:$L,$C18,BASE!$J:$J,$B18,BASE!$A:$A,N$6) -> 0 | ... R18: =SUMIFS(BASE!$G:$G,BASE!$L:$L,$C18,BASE!$J:$J,$B18,BASE!$A:$A,R$6) -> 0 | T18: =IF(AND(N18=0),"ZERADO","COM TROCAS") -> ZERADO
... B177: VIRACLARO | C177: SP2 | D177: =COUNTIFS(PDVS!H:H,"SIM",PDVS!C:C,B177) -> 0 | E177: =COUNTIFS(PDVS!C:C,B177,PDVS!I:I,"SIM") -> 1 | F177: =IF(AND(D177=0,E177>=1),"Sim",IF(D177>=1,"Não",IF(AND(D177=0,E177=0),"Sim",""))) -> Sim | G177: =SUMIFS(BASE!$G:$G,BASE!$L:$L,$C177,BASE!$J:$J,$B177,BASE!$A:$A,G$6) -> 2 | H177: =SUMIFS(BASE!$G:$G,BASE!$L:$L,$C177,BASE!$J:$J,$B177,BASE!$A:$A,H$6) -> 0 | I177: =SUMIFS(BASE!$G:$G,BASE!$L:$L,$C177,BASE!$J:$J,$B177,BASE!$A:$A,I$6) -> 3 | J177: =SUMIFS(BASE!$G:$G,BASE!$L:$L,$C177,BASE!$J:$J,$B177,BASE!$A:$A,J$6) -> 1 | K177: =SUMIFS(BASE!$G:$G,BASE!$L:$L,$C177,BASE!$J:$J,$B177,BASE!$A:$A,K$6) -> 1 | L177: =SUMIFS(BASE!$G:$G,BASE!$L:$L,$C177,BASE!$J:$J,$B177,BASE!$A:$A,L$6) -> 2 | M177: =SUMIFS(BASE!$G:$G,BASE!$L:$L,$C177,BASE!$J:$J,$B177,BASE!$A:$A,M$6) -> 2 | N177: =SUMIFS(BASE!$G:$G,BASE!$L:$L,$C177,BASE!$J:$J,$B177,BASE!$A:$A,N$6) -> 6 | ... R177: =SUMIFS(BASE!$G:$G,BASE!$L:$L,$C177,BASE!$J:$J,$B177,BASE!$A:$A,R$6) -> 0 | T177: =IF(AND(N177=0),"ZERADO","COM TROCAS") -> COM TROCAS
G178: =SUM(G7:G177) -> 1992 | H178: =SUM(H7:H177) -> 1651 | I178: =SUM(I7:I177) -> 2955 | J178: =SUM(J7:J177) -> 2357 | K178: =SUM(K7:K177) -> 2919 | L178: =SUM(L7:L177) -> 3004 | M178: =SUM(M7:M177) -> 5021 | N178: =SUM(N7:N177) -> 3842 | ... R178: =SUM(R7:R177) -> 0

Sheet PDVS
B2: CÓD | C2: GRUPO | D2: GN | E2: GF | F2: CIDADE | G2: REG | H2: REPASSE? | I2: TEM BOOST? | J2: ELEGÍVEL? | K2: 46023 | L2: 46054 | M2: 46082 | N2: 46113 | O2: 46143 | P2: 46174 | Q2: 46204 | R2: 46235 | S2: 46266 | T2: 46296 | U2: 46327 | V2: 46357 | X2: STATUS
B3: 14HB | C3: FABIANA GONCALVES DA SILVA LINS E CIA LTDA | D3: ADILSON MARQUES DA SILVA | E3: LUIZ DE SOUSA LEAL NETO | F3: GARANHUNS | G3: NE | H3: =IFERROR(IF(_xlfn.XLOOKUP(B3,REPASSE!D:D,REPASSE!D:D)="","Não","Sim"),"Não") -> Não | I3: =IF(_xlfn.XLOOKUP(B3,'BOOST LIBERADO'!B:B,'BOOST LIBERADO'!B:B,"Não")="Não","Não","Sim") -> Sim | J3: =IF(AND(H3="Não",I3="Sim"),"Sim","Não") -> Sim | K3: =SUMIFS(BASE!$G:$G,BASE!$B:$B,$B3,BASE!$L:$L,$G3,BASE!$J:$J,$C3,BASE!$A:$A,K$2) -> 0 | L3: =SUMIFS(BASE!$G:$G,BASE!$B:$B,$B3,BASE!$L:$L,$G3,BASE!$J:$J,$C3,BASE!$A:$A,L$2) -> 0 | M3: =SUMIFS(BASE!$G:$G,BASE!$B:$B,$B3,BASE!$L:$L,$G3,BASE!$J:$J,$C3,BASE!$A:$A,M$2) -> 0 | N3: =SUMIFS(BASE!$G:$G,BASE!$B:$B,$B3,BASE!$L:$L,$G3,BASE!$J:$J,$C3,BASE!$A:$A,N$2) -> 0 | O3: =SUMIFS(BASE!$G:$G,BASE!$B:$B,$B3,BASE!$L:$L,$G3,BASE!$J:$J,$C3,BASE!$A:$A,O$2) -> 0 | P3: =SUMIFS(BASE!$G:$G,BASE!$B:$B,$B3,BASE!$L:$L,$G3,BASE!$J:$J,$C3,BASE!$A:$A,P$2) -> 0 | Q3: =SUMIFS(BASE!$G:$G,BASE!$B:$B,$B3,BASE!$L:$L,$G3,BASE!$J:$J,$C3,BASE!$A:$A,Q$2) -> 0 | R3: =SUMIFS(BASE!$G:$G,BASE!$B:$B,$B3,BASE!$L:$L,$G3,BASE!$J:$J,$C3,BASE!$A:$A,R$2) -> 0 | ... V3: =SUMIFS(BASE!$G:$G,BASE!$B:$B,$B3,BASE!$L:$L,$G3,BASE!$J:$J,$C3,BASE!$A:$A,V$2) -> 0 | X3: =IF(AND(R3=0),"ZERADO","COM TROCAS") -> ZERADO
B4: 4KDV | C4: CARLOS FREDERICO E FILHOS COMERCIO | D4: HELOISA IONE OLIVEIRA DE ARAUJO | E4: FLAVIO GOMES RODRIGUES DOS SANTOS | F4: JOAO PESSOA | G4: NE | H4: =IFERROR(IF(_xlfn.XLOOKUP(B4,REPASSE!D:D,REPASSE!D:D)="","Não","Sim"),"Não") -> Não | I4: =IF(_xlfn.XLOOKUP(B4,'BOOST LIBERADO'!B:B,'BOOST LIBERADO'!B:B,"Não")="Não","Não","Sim") -> Sim | J4: =IF(AND(H4="Não",I4="Sim"),"Sim","Não") -> Sim | K4: =SUMIFS(BASE!$G:$G,BASE!$B:$B,$B4,BASE!$L:$L,$G4,BASE!$J:$J,$C4,BASE!$A:$A,K$2) -> 0 | L4: =SUMIFS(BASE!$G:$G,BASE!$B:$B,$B4,BASE!$L:$L,$G4,BASE!$J:$J,$C4,BASE!$A:$A,L$2) -> 0 | M4: =SUMIFS(BASE!$G:$G,BASE!$B:$B,$B4,BASE!$L:$L,$G4,BASE!$J:$J,$C4,BASE!$A:$A,M$2) -> 0 | N4: =SUMIFS(BASE!$G:$G,BASE!$B:$B,$B4,BASE!$L:$L,$G4,BASE!$J:$J,$C4,BASE!$A:$A,N$2) -> 0 | O4: =SUMIFS(BASE!$G:$G,BASE!$B:$B,$B4,BASE!$L:$L,$G4,BASE!$J:$J,$C4,BASE!$A:$A,O$2) -> 0 | P4: =SUMIFS(BASE!$G:$G,BASE!$B:$B,$B4,BASE!$L:$L,$G4,BASE!$J:$J,$C4,BASE!$A:$A,P$2) -> 0 | Q4: =SUMIFS(BASE!$G:$G,BASE!$B:$B,$B4,BASE!$L:$L,$G4,BASE!$J:$J,$C4,BASE!$A:$A,Q$2) -> 0 | R4: =SUMIFS(BASE!$G:$G,BASE!$B:$B,$B4,BASE!$L:$L,$G4,BASE!$J:$J,$C4,BASE!$A:$A,R$2) -> 0 | ... V4: =SUMIFS(BASE!$G:$G,BASE!$B:$B,$B4,BASE!$L:$L,$G4,BASE!$J:$J,$C4,BASE!$A:$A,V$2) -> 0 | X4: =IF(AND(R4=0),"ZERADO","COM TROCAS") -> ZERADO
B5: 5LYK | C5: HARCOS COMERCIO E SERVICOS LTDA - EPP | D5: ISADORA NASCIMENTO SILVA | E5: ADNO KEVERSON DOS SANTOS CASTRO | F5: NATAL | G5: NE | H5: =IFERROR(IF(_xlfn.XLOOKUP(B5,REPASSE!D:D,REPASSE!D:D)="","Não","Sim"),"Não") -> Não | I5: =IF(_xlfn.XLOOKUP(B5,'BOOST LIBERADO'!B:B,'BOOST LIBERADO'!B:B,"Não")="Não","Não","Sim") -> Sim | J5: =IF(AND(H5="Não",I5="Sim"),"Sim","Não") -> Sim | K5: =SUMIFS(BASE!$G:$G,BASE!$B:$B,$B5,BASE!$L:$L,$G5,BASE!$J:$J,$C5,BASE!$A:$A,K$2) -> 28 | L5: =SUMIFS(BASE!$G:$G,BASE!$B:$B,$B5,BASE!$L:$L,$G5,BASE!$J:$J,$C5,BASE!$A:$A,L$2) -> 20 | M5: =SUMIFS(BASE!$G:$G,BASE!$B:$B,$B5,BASE!$L:$L,$G5,BASE!$J:$J,$C5,BASE!$A:$A,M$2) -> 9 | N5: =SUMIFS(BASE!$G:$G,BASE!$B:$B,$B5,BASE!$L:$L,$G5,BASE!$J:$J,$C5,BASE!$A:$A,N$2) -> 7 | O5: =SUMIFS(BASE!$G:$G,BASE!$B:$B,$B5,BASE!$L:$L,$G5,BASE!$J:$J,$C5,BASE!$A:$A,O$2) -> 8 | P5: =SUMIFS(BASE!$G:$G,BASE!$B:$B,$B5,BASE!$L:$L,$G5,BASE!$J:$J,$C5,BASE!$A:$A,P$2) -> 16 | Q5: =SUMIFS(BASE!$G:$G,BASE!$B:$B,$B5,BASE!$L:$L,$G5,BASE!$J:$J,$C5,BASE!$A:$A,Q$2) -> 29 | R5: =SUMIFS(BASE!$G:$G,BASE!$B:$B,$B5,BASE!$L:$L,$G5,BASE!$J:$J,$C5,BASE!$A:$A,R$2) -> 19 | ... V5: =SUMIFS(BASE!$G:$G,BASE!$B:$B,$B5,BASE!$L:$L,$G5,BASE!$J:$J,$C5,BASE!$A:$A,V$2) -> 0 | X5: =IF(AND(R5=0),"ZERADO","COM TROCAS") -> COM TROCAS
B6: 5QC8 | C6: HARCOS COMERCIO E SERVICOS LTDA - EPP | D6: MICHELLE SALUSTRE MARCATO | E6: FABRICIO SILVA DE ARAUJO | F6: MACEIO | G6: NE | H6: =IFERROR(IF(_xlfn.XLOOKUP(B6,REPASSE!D:D,REPASSE!D:D)="","Não","Sim"),"Não") -> Não | I6: =IF(_xlfn.XLOOKUP(B6,'BOOST LIBERADO'!B:B,'BOOST LIBERADO'!B:B,"Não")="Não","Não","Sim") -> Sim | J6: =IF(AND(H6="Não",I6="Sim"),"Sim","Não") -> Sim | K6: =SUMIFS(BASE!$G:$G,BASE!$B:$B,$B6,BASE!$L:$L,$G6,BASE!$J:$J,$C6,BASE!$A:$A,K$2) -> 8 | L6: =SUMIFS(BASE!$G:$G,BASE!$B:$B,$B6,BASE!$L:$L,$G6,BASE!$J:$J,$C6,BASE!$A:$A,L$2) -> 11 | M6: =SUMIFS(BASE!$G:$G,BASE!$B:$B,$B6,BASE!$L:$L,$G6,BASE!$J:$J,$C6,BASE!$A:$A,M$2) -> 17 | N6: =SUMIFS(BASE!$G:$G,BASE!$B:$B,$B6,BASE!$L:$L,$G6,BASE!$J:$J,$C6,BASE!$A:$A,N$2) -> 10 | O6: =SUMIFS(BASE!$G:$G,BASE!$B:$B,$B6,BASE!$L:$L,$G6,BASE!$J:$J,$C6,BASE!$A:$A,O$2) -> 15 | P6: =SUMIFS(BASE!$G:$G,BASE!$B:$B,$B6,BASE!$L:$L,$G6,BASE!$J:$J,$C6,BASE!$A:$A,P$2) -> 11 | Q6: =SUMIFS(BASE!$G:$G,BASE!$B:$B,$B6,BASE!$L:$L,$G6,BASE!$J:$J,$C6,BASE!$A:$A,Q$2) -> 20 | R6: =SUMIFS(BASE!$G:$G,BASE!$B:$B,$B6,BASE!$L:$L,$G6,BASE!$J:$J,$C6,BASE!$A:$A,R$2) -> 3 | ... V6: =SUMIFS(BASE!$G:$G,BASE!$B:$B,$B6,BASE!$L:$L,$G6,BASE!$J:$J,$C6,BASE!$A:$A,V$2) -> 0 | X6: =IF(AND(R6=0),"ZERADO","COM TROCAS") -> COM TROCAS
B7: B1RJ | C7: SELF COMERCIO E SERVICOS EM TELEFON | D7: FRANCISCA ALINE ALVES BENTO | E7: DIEGO HENRIQUE FERREIRA DANTAS | F7: FORTALEZA | G7: NE | H7: =IFERROR(IF(_xlfn.XLOOKUP(B7,REPASSE!D:D,REPASSE!D:D)="","Não","Sim"),"Não") -> Não | I7: =IF(_xlfn.XLOOKUP(B7,'BOOST LIBERADO'!B:B,'BOOST LIBERADO'!B:B,"Não")="Não","Não","Sim") -> Não | J7: =IF(AND(H7="Não",I7="Sim"),"Sim","Não") -> Não | K7: =SUMIFS(BASE!$G:$G,BASE!$B:$B,$B7,BASE!$L:$L,$G7,BASE!$J:$J,$C7,BASE!$A:$A,K$2) -> 0 | L7: =SUMIFS(BASE!$G:$G,BASE!$B:$B,$B7,BASE!$L:$L,$G7,BASE!$J:$J,$C7,BASE!$A:$A,L$2) -> 0 | M7: =SUMIFS(BASE!$G:$G,BASE!$B:$B,$B7,BASE!$L:$L,$G7,BASE!$J:$J,$C7,BASE!$A:$A,M$2) -> 0 | N7: =SUMIFS(BASE!$G:$G,BASE!$B:$B,$B7,BASE!$L:$L,$G7,BASE!$J:$J,$C7,BASE!$A:$A,N$2) -> 0 | O7: =SUMIFS(BASE!$G:$G,BASE!$B:$B,$B7,BASE!$L:$L,$G7,BASE!$J:$J,$C7,BASE!$A:$A,O$2) -> 0 | P7: =SUMIFS(BASE!$G:$G,BASE!$B:$B,$B7,BASE!$L:$L,$G7,BASE!$J:$J,$C7,BASE!$A:$A,P$2) -> 0 | Q7: =SUMIFS(BASE!$G:$G,BASE!$B:$B,$B7,BASE!$L:$L,$G7,BASE!$J:$J,$C7,BASE!$A:$A,Q$2) -> 0 | R7: =SUMIFS(BASE!$G:$G,BASE!$B:$B,$B7,BASE!$L:$L,$G7,BASE!$J:$J,$C7,BASE!$A:$A,R$2) -> 0 | ... V7: =SUMIFS(BASE!$G:$G,BASE!$B:$B,$B7,BASE!$L:$L,$G7,BASE!$J:$J,$C7,BASE!$A:$A,V$2) -> 0 | X7: =IF(AND(R7=0),"ZERADO","COM TROCAS") -> ZERADO
B8: DP0N | C8: SELF COMERCIO E SERVICOS EM TELEFON | D8: FRANCISCA ALINE ALVES BENTO | E8: DIEGO HENRIQUE FERREIRA DANTAS | F8: FORTALEZA | G8: NE | H8: =IFERROR(IF(_xlfn.XLOOKUP(B8,REPASSE!D:D,REPASSE!D:D)="","Não","Sim"),"Não") -> Não | I8: =IF(_xlfn.XLOOKUP(B8,'BOOST LIBERADO'!B:B,'BOOST LIBERADO'!B:B,"Não")="Não","Não","Sim") -> Não | J8: =IF(AND(H8="Não",I8="Sim"),"Sim","Não") -> Não | K8: =SUMIFS(BASE!$G:$G,BASE!$B:$B,$B8,BASE!$L:$L,$G8,BASE!$J:$J,$C8,BASE!$A:$A,K$2) -> 0 | L8: =SUMIFS(BASE!$G:$G,BASE!$B:$B,$B8,BASE!$L:$L,$G8,BASE!$J:$J,$C8,BASE!$A:$A,L$2) -> 0 | M8: =SUMIFS(BASE!$G:$G,BASE!$B:$B,$B8,BASE!$L:$L,$G8,BASE!$J:$J,$C8,BASE!$A:$A,M$2) -> 0 | N8: =SUMIFS(BASE!$G:$G,BASE!$B:$B,$B8,BASE!$L:$L,$G8,BASE!$J:$J,$C8,BASE!$A:$A,N$2) -> 0 | O8: =SUMIFS(BASE!$G:$G,BASE!$B:$B,$B8,BASE!$L:$L,$G8,BASE!$J:$J,$C8,BASE!$A:$A,O$2) -> 0 | P8: =SUMIFS(BASE!$G:$G,BASE!$B:$B,$B8,BASE!$L:$L,$G8,BASE!$J:$J,$C8,BASE!$A:$A,P$2) -> 0 | Q8: =SUMIFS(BASE!$G:$G,BASE!$B:$B,$B8,BASE!$L:$L,$G8,BASE!$J:$J,$C8,BASE!$A:$A,Q$2) -> 0 | R8: =SUMIFS(BASE!$G:$G,BASE!$B:$B,$B8,BASE!$L:$L,$G8,BASE!$J:$J,$C8,BASE!$A:$A,R$2) -> 0 | ... V8: =SUMIFS(BASE!$G:$G,BASE!$B:$B,$B8,BASE!$L:$L,$G8,BASE!$J:$J,$C8,BASE!$A:$A,V$2) -> 0 | X8: =IF(AND(R8=0),"ZERADO","COM TROCAS") -> ZERADO
B9: FCZ6 | C9: CARLOS FREDERICO E FILHOS COMERCIO | D9: IRANILDE VERISSIMO DE MEDEIROS | E9: FLAVIO GOMES RODRIGUES DOS SANTOS | F9: JOAO PESSOA | G9: NE | H9: =IFERROR(IF(_xlfn.XLOOKUP(B9,REPASSE!D:D,REPASSE!D:D)="","Não","Sim"),"Não") -> Não | I9: =IF(_xlfn.XLOOKUP(B9,'BOOST LIBERADO'!B:B,'BOOST LIBERADO'!B:B,"Não")="Não","Não","Sim") -> Sim | J9: =IF(AND(H9="Não",I9="Sim"),"Sim","Não") -> Sim | K9: =SUMIFS(BASE!$G:$G,BASE!$B:$B,$B9,BASE!$L:$L,$G9,BASE!$J:$J,$C9,BASE!$A:$A,K$2) -> 0 | L9: =SUMIFS(BASE!$G:$G,BASE!$B:$B,$B9,BASE!$L:$L,$G9,BASE!$J:$J,$C9,BASE!$A:$A,L$2) -> 0 | M9: =SUMIFS(BASE!$G:$G,BASE!$B:$B,$B9,BASE!$L:$L,$G9,BASE!$J:$J,$C9,BASE!$A:$A,M$2) -> 0 | N9: =SUMIFS(BASE!$G:$G,BASE!$B:$B,$B9,BASE!$L:$L,$G9,BASE!$J:$J,$C9,BASE!$A:$A,N$2) -> 0 | O9: =SUMIFS(BASE!$G:$G,BASE!$B:$B,$B9,BASE!$L:$L,$G9,BASE!$J:$J,$C9,BASE!$A:$A,O$2) -> 0 | P9: =SUMIFS(BASE!$G:$G,BASE!$B:$B,$B9,BASE!$L:$L,$G9,BASE!$J:$J,$C9,BASE!$A:$A,P$2) -> 0 | Q9: =SUMIFS(BASE!$G:$G,BASE!$B:$B,$B9,BASE!$L:$L,$G9,BASE!$J:$J,$C9,BASE!$A:$A,Q$2) -> 0 | R9: =SUMIFS(BASE!$G:$G,BASE!$B:$B,$B9,BASE!$L:$L,$G9,BASE!$J:$J,$C9,BASE!$A:$A,R$2) -> 0 | ... V9: =SUMIFS(BASE!$G:$G,BASE!$B:$B,$B9,BASE!$L:$L,$G9,BASE!$J:$J,$C9,BASE!$A:$A,V$2) -> 0 | X9: =IF(AND(R9=0),"ZERADO","COM TROCAS") -> ZERADO
B10: GR53 | C10: DELTA CELL TELECOMUNICACOES LTDA | D10: ALIENNY BARBOSA MACEDO | E10: DAVID OLIVEIRA DA COSTA | F10: PIRIPIRI | G10: NE | H10: =IFERROR(IF(_xlfn.XLOOKUP(B10,REPASSE!D:D,REPASSE!D:D)="","Não","Sim"),"Não") -> Não | I10: =IF(_xlfn.XLOOKUP(B10,'BOOST LIBERADO'!B:B,'BOOST LIBERADO'!B:B,"Não")="Não","Não","Sim") -> Sim | J10: =IF(AND(H10="Não",I10="Sim"),"Sim","Não") -> Sim | K10: =SUMIFS(BASE!$G:$G,BASE!$B:$B,$B10,BASE!$L:$L,$G10,BASE!$J:$J,$C10,BASE!$A:$A,K$2) -> 0 | L10: =SUMIFS(BASE!$G:$G,BASE!$B:$B,$B10,BASE!$L:$L,$G10,BASE!$J:$J,$C10,BASE!$A:$A,L$2) -> 0 | M10: =SUMIFS(BASE!$G:$G,BASE!$B:$B,$B10,BASE!$L:$L,$G10,BASE!$J:$J,$C10,BASE!$A:$A,M$2) -> 0 | N10: =SUMIFS(BASE!$G:$G,BASE!$B:$B,$B10,BASE!$L:$L,$G10,BASE!$J:$J,$C10,BASE!$A:$A,N$2) -> 0 | O10: =SUMIFS(BASE!$G:$G,BASE!$B:$B,$B10,BASE!$L:$L,$G10,BASE!$J:$J,$C10,BASE!$A:$A,O$2) -> 0 | P10: =SUMIFS(BASE!$G:$G,BASE!$B:$B,$B10,BASE!$L:$L,$G10,BASE!$J:$J,$C10,BASE!$A:$A,P$2) -> 0 | Q10: =SUMIFS(BASE!$G:$G,BASE!$B:$B,$B10,BASE!$L:$L,$G10,BASE!$J:$J,$C10,BASE!$A:$A,Q$2) -> 0 | R10: =SUMIFS(BASE!$G:$G,BASE!$B:$B,$B10,BASE!$L:$L,$G10,BASE!$J:$J,$C10,BASE!$A:$A,R$2) -> 0 | ... V10: =SUMIFS(BASE!$G:$G,BASE!$B:$B,$B10,BASE!$L:$L,$G10,BASE!$J:$J,$C10,BASE!$A:$A,V$2) -> 0 | X10: =IF(AND(R10=0),"ZERADO","COM TROCAS") -> ZERADO
B11: H0ZF | C11: R & R HIPER COMERCIO LTDA | D11: DENISE CIBELLY FERNANDES BATALHA | E11: ADNO KEVERSON DOS SANTOS CASTRO | F11: NATAL | G11: NE | H11: =IFERROR(IF(_xlfn.XLOOKUP(B11,REPASSE!D:D,REPASSE!D:D)="","Não","Sim"),"Não") -> Não | I11: =IF(_xlfn.XLOOKUP(B11,'BOOST LIBERADO'!B:B,'BOOST LIBERADO'!B:B,"Não")="Não","Não","Sim") -> Sim | J11: =IF(AND(H11="Não",I11="Sim"),"Sim","Não") -> Sim | K11: =SUMIFS(BASE!$G:$G,BASE!$B:$B,$B11,BASE!$L:$L,$G11,BASE!$J:$J,$C11,BASE!$A:$A,K$2) -> 3 | L11: =SUMIFS(BASE!$G:$G,BASE!$B:$B,$B11,BASE!$L:$L,$G11,BASE!$J:$J,$C11,BASE!$A:$A,L$2) -> 2 | M11: =SUMIFS(BASE!$G:$G,BASE!$B:$B,$B11,BASE!$L:$L,$G11,BASE!$J:$J,$C11,BASE!$A:$A,M$2) -> 0 | N11: =SUMIFS(BASE!$G:$G,BASE!$B:$B,$B11,BASE!$L:$L,$G11,BASE!$J:$J,$C11,BASE!$A:$A,N$2) -> 3 | O11: =SUMIFS(BASE!$G:$G,BASE!$B:$B,$B11,BASE!$L:$L,$G11,BASE!$J:$J,$C11,BASE!$A:$A,O$2) -> 8 | P11: =SUMIFS(BASE!$G:$G,BASE!$B:$B,$B11,BASE!$L:$L,$G11,BASE!$J:$J,$C11,BASE!$A:$A,P$2) -> 3 | Q11: =SUMIFS(BASE!$G:$G,BASE!$B:$B,$B11,BASE!$L:$L,$G11,BASE!$J:$J,$C11,BASE!$A:$A,Q$2) -> 16 | R11: =SUMIFS(BASE!$G:$G,BASE!$B:$B,$B11,BASE!$L:$L,$G11,BASE!$J:$J,$C11,BASE!$A:$A,R$2) -> 15 | ... V11: =SUMIFS(BASE!$G:$G,BASE!$B:$B,$B11,BASE!$L:$L,$G11,BASE!$J:$J,$C11,BASE!$A:$A,V$2) -> 0 | X11: =IF(AND(R11=0),"ZERADO","COM TROCAS") -> COM TROCAS
B12: IE2M | C12: HARCOS COMERCIO E SERVICOS LTDA - EPP | D12: MICHELLE SALUSTRE MARCATO | E12: FABRICIO SILVA DE ARAUJO | F12: MACEIO | G12: NE | H12: =IFERROR(IF(_xlfn.XLOOKUP(B12,REPASSE!D:D,REPASSE!D:D)="","Não","Sim"),"Não") -> Não | I12: =IF(_xlfn.XLOOKUP(B12,'BOOST LIBERADO'!B:B,'BOOST LIBERADO'!B:B,"Não")="Não","Não","Sim") -> Sim | J12: =IF(AND(H12="Não",I12="Sim"),"Sim","Não") -> Sim | K12: =SUMIFS(BASE!$G:$G,BASE!$B:$B,$B12,BASE!$L:$L,$G12,BASE!$J:$J,$C12,BASE!$A:$A,K$2) -> 20 | L12: =SUMIFS(BASE!$G:$G,BASE!$B:$B,$B12,BASE!$L:$L,$G12,BASE!$J:$J,$C12,BASE!$A:$A,L$2) -> 5 | M12: =SUMIFS(BASE!$G:$G,BASE!$B:$B,$B12,BASE!$L:$L,$G12,BASE!$J:$J,$C12,BASE!$A:$A,M$2) -> 22 | N12: =SUMIFS(BASE!$G:$G,BASE!$B:$B,$B12,BASE!$L:$L,$G12,BASE!$J:$J,$C12,BASE!$A:$A,N$2) -> 14 | O12: =SUMIFS(BASE!$G:$G,BASE!$B:$B,$B12,BASE!$L:$L,$G12,BASE!$J:$J,$C12,BASE!$A:$A,O$2) -> 10 | P12: =SUMIFS(BASE!$G:$G,BASE!$B:$B,$B12,BASE!$L:$L,$G12,BASE!$J:$J,$C12,BASE!$A:$A,P$2) -> 20 | Q12: =SUMIFS(BASE!$G:$G,BASE!$B:$B,$B12,BASE!$L:$L,$G12,BASE!$J:$J,$C12,BASE!$A:$A,Q$2) -> 23 | R12: =SUMIFS(BASE!$G:$G,BASE!$B:$B,$B12,BASE!$L:$L,$G12,BASE!$J:$J,$C12,BASE!$A:$A,R$2) -> 27 | ... V12: =SUMIFS(BASE!$G:$G,BASE!$B:$B,$B12,BASE!$L:$L,$G12,BASE!$J:$J,$C12,BASE!$A:$A,V$2) -> 0 | X12: =IF(AND(R12=0),"ZERADO","COM TROCAS") -> COM TROCAS
B13: IKFK | C13: HARCOS COMERCIO E SERVICOS LTDA - EPP | D13: MICHELLE SALUSTRE MARCATO | E13: FABRICIO SILVA DE ARAUJO | F13: MACEIO | G13: NE | H13: =IFERROR(IF(_xlfn.XLOOKUP(B13,REPASSE!D:D,REPASSE!D:D)="","Não","Sim"),"Não") -> Não | I13: =IF(_xlfn.XLOOKUP(B13,'BOOST LIBERADO'!B:B,'BOOST LIBERADO'!B:B,"Não")="Não","Não","Sim") -> Sim | J13: =IF(AND(H13="Não",I13="Sim"),"Sim","Não") -> Sim | K13: =SUMIFS(BASE!$G:$G,BASE!$B:$B,$B13,BASE!$L:$L,$G13,BASE!$J:$J,$C13,BASE!$A:$A,K$2) -> 10 | L13: =SUMIFS(BASE!$G:$G,BASE!$B:$B,$B13,BASE!$L:$L,$G13,BASE!$J:$J,$C13,BASE!$A:$A,L$2) -> 6 | M13: =SUMIFS(BASE!$G:$G,BASE!$B:$B,$B13,BASE!$L:$L,$G13,BASE!$J:$J,$C13,BASE!$A:$A,M$2) -> 10 | N13: =SUMIFS(BASE!$G:$G,BASE!$B:$B,$B13,BASE!$L:$L,$G13,BASE!$J:$J,$C13,BASE!$A:$A,N$2) -> 12 | O13: =SUMIFS(BASE!$G:$G,BASE!$B:$B,$B13,BASE!$L:$L,$G13,BASE!$J:$J,$C13,BASE!$A:$A,O$2) -> 9 | P13: =SUMIFS(BASE!$G:$G,BASE!$B:$B,$B13,BASE!$L:$L,$G13,BASE!$J:$J,$C13,BASE!$A:$A,P$2) -> 10 | Q13: =SUMIFS(BASE!$G:$G,BASE!$B:$B,$B13,BASE!$L:$L,$G13,BASE!$J:$J,$C13,BASE!$A:$A,Q$2) -> 20 | R13: =SUMIFS(BASE!$G:$G,BASE!$B:$B,$B13,BASE!$L:$L,$G13,BASE!$J:$J,$C13,BASE!$A:$A,R$2) -> 26 | ... V13: =SUMIFS(BASE!$G:$G,BASE!$B:$B,$B13,BASE!$L:$L,$G13,BASE!$J:$J,$C13,BASE!$A:$A,V$2) -> 0 | X13: =IF(AND(R13=0),"ZERADO","COM TROCAS") -> COM TROCAS
B14: LPK0 | C14: SANTOS E TENORIO TELECOM LTDA | D14: JULYANE CAVALCANTE GOMES DA SILVA | E14: FABRICIO SILVA DE ARAUJO | F14: PENEDO | G14: NE | H14: =IFERROR(IF(_xlfn.XLOOKUP(B14,REPASSE!D:D,REPASSE!D:D)="","Não","Sim"),"Não") -> Não | I14: =IF(_xlfn.XLOOKUP(B14,'BOOST LIBERADO'!B:B,'BOOST LIBERADO'!B:B,"Não")="Não","Não","Sim") -> Sim | J14: =IF(AND(H14="Não",I14="Sim"),"Sim","Não") -> Sim | K14: =SUMIFS(BASE!$G:$G,BASE!$B:$B,$B14,BASE!$L:$L,$G14,BASE!$J:$J,$C14,BASE!$A:$A,K$2) -> 0 | L14: =SUMIFS(BASE!$G:$G,BASE!$B:$B,$B14,BASE!$L:$L,$G14,BASE!$J:$J,$C14,BASE!$A:$A,L$2) -> 0 | M14: =SUMIFS(BASE!$G:$G,BASE!$B:$B,$B14,BASE!$L:$L,$G14,BASE!$J:$J,$C14,BASE!$A:$A,M$2) -> 0 | N14: =SUMIFS(BASE!$G:$G,BASE!$B:$B,$B14,BASE!$L:$L,$G14,BASE!$J:$J,$C14,BASE!$A:$A,N$2) -> 0 | O14: =SUMIFS(BASE!$G:$G,BASE!$B:$B,$B14,BASE!$L:$L,$G14,BASE!$J:$J,$C14,BASE!$A:$A,O$2) -> 0 | P14: =SUMIFS(BASE!$G:$G,BASE!$B:$B,$B14,BASE!$L:$L,$G14,BASE!$J:$J,$C14,BASE!$A:$A,P$2) -> 0 | Q14: =SUMIFS(BASE!$G:$G,BASE!$B:$B,$B14,BASE!$L:$L,$G14,BASE!$J:$J,$C14,BASE!$A:$A,Q$2) -> 0 | R14: =SUMIFS(BASE!$G:$G,BASE!$B:$B,$B14,BASE!$L:$L,$G14,BASE!$J:$J,$C14,BASE!$A:$A,R$2) -> 0 | ... V14: =SUMIFS(BASE!$G:$G,BASE!$B:$B,$B14,BASE!$L:$L,$G14,BASE!$J:$J,$C14,BASE!$A:$A,V$2) -> 0 | X14: =IF(AND(R14=0),"ZERADO","COM TROCAS") -> ZERADO
... B180: X8IF | C180: CENTERCELL TELECOMUNICACOES CARANGO | D180: JOSIANA EMILIA SILVA FARIA | E180: KAROLINE LAMAS DE ANDRADE | F180: ESPERA FELIZ | G180: MG | H180: =IFERROR(IF(_xlfn.XLOOKUP(B180,REPASSE!D:D,REPASSE!D:D)="","Não","Sim"),"Não") -> Não | I180: =IF(_xlfn.XLOOKUP(B180,'BOOST LIBERADO'!B:B,'BOOST LIBERADO'!B:B,"Não")="Não","Não","Sim") -> Sim | J180: =IF(AND(H180="Não",I180="Sim"),"Sim","Não") -> Sim | K180: =SUMIFS(BASE!$G:$G,BASE!$B:$B,$B180,BASE!$L:$L,$G180,BASE!$J:$J,$C180,BASE!$A:$A,K$2) -> 0 | L180: =SUMIFS(BASE!$G:$G,BASE!$B:$B,$B180,BASE!$L:$L,$G180,BASE!$J:$J,$C180,BASE!$A:$A,L$2) -> 0 | M180: =SUMIFS(BASE!$G:$G,BASE!$B:$B,$B180,BASE!$L:$L,$G180,BASE!$J:$J,$C180,BASE!$A:$A,M$2) -> 0 | N180: =SUMIFS(BASE!$G:$G,BASE!$B:$B,$B180,BASE!$L:$L,$G180,BASE!$J:$J,$C180,BASE!$A:$A,N$2) -> 0 | O180: =SUMIFS(BASE!$G:$G,BASE!$B:$B,$B180,BASE!$L:$L,$G180,BASE!$J:$J,$C180,BASE!$A:$A,O$2) -> 0 | P180: =SUMIFS(BASE!$G:$G,BASE!$B:$B,$B180,BASE!$L:$L,$G180,BASE!$J:$J,$C180,BASE!$A:$A,P$2) -> 0 | Q180: =SUMIFS(BASE!$G:$G,BASE!$B:$B,$B180,BASE!$L:$L,$G180,BASE!$J:$J,$C180,BASE!$A:$A,Q$2) -> 0 | R180: =SUMIFS(BASE!$G:$G,BASE!$B:$B,$B180,BASE!$L:$L,$G180,BASE!$J:$J,$C180,BASE!$A:$A,R$2) -> 0 | ... V180: =SUMIFS(BASE!$G:$G,BASE!$B:$B,$B180,BASE!$L:$L,$G180,BASE!$J:$J,$C180,BASE!$A:$A,V$2) -> 0 | X180: =IF(AND(R180=0),"ZERADO","COM TROCAS") -> ZERADO
B181: 4540 | C181: CELLULAR.COM | D181: LIZANDRA PERES DA SILVA | E181: JORGE PEREIRA AZAMBUJA FILHO | F181: VESPASIANO | G181: MG | H181: =IFERROR(IF(_xlfn.XLOOKUP(B181,REPASSE!D:D,REPASSE!D:D)="","Não","Sim"),"Não") -> Não | I181: =IF(_xlfn.XLOOKUP(B181,'BOOST LIBERADO'!B:B,'BOOST LIBERADO'!B:B,"Não")="Não","Não","Sim") -> Não | J181: =IF(AND(H181="Não",I181="Sim"),"Sim","Não") -> Não | K181: =SUMIFS(BASE!$G:$G,BASE!$B:$B,$B181,BASE!$L:$L,$G181,BASE!$J:$J,$C181,BASE!$A:$A,K$2) -> 0 | L181: =SUMIFS(BASE!$G:$G,BASE!$B:$B,$B181,BASE!$L:$L,$G181,BASE!$J:$J,$C181,BASE!$A:$A,L$2) -> 0 | M181: =SUMIFS(BASE!$G:$G,BASE!$B:$B,$B181,BASE!$L:$L,$G181,BASE!$J:$J,$C181,BASE!$A:$A,M$2) -> 0 | N181: =SUMIFS(BASE!$G:$G,BASE!$B:$B,$B181,BASE!$L:$L,$G181,BASE!$J:$J,$C181,BASE!$A:$A,N$2) -> 0 | O181: =SUMIFS(BASE!$G:$G,BASE!$B:$B,$B181,BASE!$L:$L,$G181,BASE!$J:$J,$C181,BASE!$A:$A,O$2) -> 0 | P181: =SUMIFS(BASE!$G:$G,BASE!$B:$B,$B181,BASE!$L:$L,$G181,BASE!$J:$J,$C181,BASE!$A:$A,P$2) -> 0 | Q181: =SUMIFS(BASE!$G:$G,BASE!$B:$B,$B181,BASE!$L:$L,$G181,BASE!$J:$J,$C181,BASE!$A:$A,Q$2) -> 0 | R181: =SUMIFS(BASE!$G:$G,BASE!$B:$B,$B181,BASE!$L:$L,$G181,BASE!$J:$J,$C181,BASE!$A:$A,R$2) -> 0 | ... V181: =SUMIFS(BASE!$G:$G,BASE!$B:$B,$B181,BASE!$L:$L,$G181,BASE!$J:$J,$C181,BASE!$A:$A,V$2) -> 0 | X181: =IF(AND(R181=0),"ZERADO","COM TROCAS") -> ZERADO
B182: Z404 | C182: CELLULAR.COM | D182: MABY APARECIDA DUARTE | E182: MARCOS LOPES PEDROSA JUNIOR | F182: NOVA LIMA | G182: MG | H182: =IFERROR(IF(_xlfn.XLOOKUP(B182,REPASSE!D:D,REPASSE!D:D)="","Não","Sim"),"Não") -> Não | I182: =IF(_xlfn.XLOOKUP(B182,'BOOST LIBERADO'!B:B,'BOOST LIBERADO'!B:B,"Não")="Não","Não","Sim") -> Sim | J182: =IF(AND(H182="Não",I182="Sim"),"Sim","Não") -> Sim | K182: =SUMIFS(BASE!$G:$G,BASE!$B:$B,$B182,BASE!$L:$L,$G182,BASE!$J:$J,$C182,BASE!$A:$A,K$2) -> 0 | L182: =SUMIFS(BASE!$G:$G,BASE!$B:$B,$B182,BASE!$L:$L,$G182,BASE!$J:$J,$C182,BASE!$A:$A,L$2) -> 0 | M182: =SUMIFS(BASE!$G:$G,BASE!$B:$B,$B182,BASE!$L:$L,$G182,BASE!$J:$J,$C182,BASE!$A:$A,M$2) -> 0 | N182: =SUMIFS(BASE!$G:$G,BASE!$B:$B,$B182,BASE!$L:$L,$G182,BASE!$J:$J,$C182,BASE!$A:$A,N$2) -> 0 | O182: =SUMIFS(BASE!$G:$G,BASE!$B:$B,$B182,BASE!$L:$L,$G182,BASE!$J:$J,$C182,BASE!$A:$A,O$2) -> 0 | P182: =SUMIFS(BASE!$G:$G,BASE!$B:$B,$B182,BASE!$L:$L,$G182,BASE!$J:$J,$C182,BASE!$A:$A,P$2) -> 0 | Q182: =SUMIFS(BASE!$G:$G,BASE!$B:$B,$B182,BASE!$L:$L,$G182,BASE!$J:$J,$C182,BASE!$A:$A,Q$2) -> 0 | R182: =SUMIFS(BASE!$G:$G,BASE!$B:$B,$B182,BASE!$L:$L,$G182,BASE!$J:$J,$C182,BASE!$A:$A,R$2) -> 0 | ... V182: =SUMIFS(BASE!$G:$G,BASE!$B:$B,$B182,BASE!$L:$L,$G182,BASE!$J:$J,$C182,BASE!$A:$A,V$2) -> 0 | X182: =IF(AND(R182=0),"ZERADO","COM TROCAS") -> ZERADO
B183: MXJG | C183: CELLULAR.COM | D183: MATEUS MARQUES VIANA | E183: MARCOS LOPES PEDROSA JUNIOR | F183: ITAUNA | G183: MG | H183: =IFERROR(IF(_xlfn.XLOOKUP(B183,REPASSE!D:D,REPASSE!D:D)="","Não","Sim"),"Não") -> Não | I183: =IF(_xlfn.XLOOKUP(B183,'BOOST LIBERADO'!B:B,'BOOST LIBERADO'!B:B,"Não")="Não","Não","Sim") -> Sim | J183: =IF(AND(H183="Não",I183="Sim"),"Sim","Não") -> Sim | K183: =SUMIFS(BASE!$G:$G,BASE!$B:$B,$B183,BASE!$L:$L,$G183,BASE!$J:$J,$C183,BASE!$A:$A,K$2) -> 0 | L183: =SUMIFS(BASE!$G:$G,BASE!$B:$B,$B183,BASE!$L:$L,$G183,BASE!$J:$J,$C183,BASE!$A:$A,L$2) -> 0 | M183: =SUMIFS(BASE!$G:$G,BASE!$B:$B,$B183,BASE!$L:$L,$G183,BASE!$J:$J,$C183,BASE!$A:$A,M$2) -> 0 | N183: =SUMIFS(BASE!$G:$G,BASE!$B:$B,$B183,BASE!$L:$L,$G183,BASE!$J:$J,$C183,BASE!$A:$A,N$2) -> 0 | O183: =SUMIFS(BASE!$G:$G,BASE!$B:$B,$B183,BASE!$L:$L,$G183,BASE!$J:$J,$C183,BASE!$A:$A,O$2) -> 0 | P183: =SUMIFS(BASE!$G:$G,BASE!$B:$B,$B183,BASE!$L:$L,$G183,BASE!$J:$J,$C183,BASE!$A:$A,P$2) -> 0 | Q183: =SUMIFS(BASE!$G:$G,BASE!$B:$B,$B183,BASE!$L:$L,$G183,BASE!$J:$J,$C183,BASE!$A:$A,Q$2) -> 0 | R183: =SUMIFS(BASE!$G:$G,BASE!$B:$B,$B183,BASE!$L:$L,$G183,BASE!$J:$J,$C183,BASE!$A:$A,R$2) -> 0 | ... V183: =SUMIFS(BASE!$G:$G,BASE!$B:$B,$B183,BASE!$L:$L,$G183,BASE!$J:$J,$C183,BASE!$A:$A,V$2) -> 0 | X183: =IF(AND(R183=0),"ZERADO","COM TROCAS") -> ZERADO
B184: 9PNA | C184: MAXMILIANO RODRIGUES | D184: JESSICA PEREIRA BOTELHO ARRUDA | E184: BRENNER SOUZA RODRIGUES | F184: TEOFILO OTONI | G184: MG | H184: =IFERROR(IF(_xlfn.XLOOKUP(B184,REPASSE!D:D,REPASSE!D:D)="","Não","Sim"),"Não") -> Não | I184: =IF(_xlfn.XLOOKUP(B184,'BOOST LIBERADO'!B:B,'BOOST LIBERADO'!B:B,"Não")="Não","Não","Sim") -> Sim | J184: =IF(AND(H184="Não",I184="Sim"),"Sim","Não") -> Sim | K184: =SUMIFS(BASE!$G:$G,BASE!$B:$B,$B184,BASE!$L:$L,$G184,BASE!$J:$J,$C184,BASE!$A:$A,K$2) -> 0 | L184: =SUMIFS(BASE!$G:$G,BASE!$B:$B,$B184,BASE!$L:$L,$G184,BASE!$J:$J,$C184,BASE!$A:$A,L$2) -> 0 | M184: =SUMIFS(BASE!$G:$G,BASE!$B:$B,$B184,BASE!$L:$L,$G184,BASE!$J:$J,$C184,BASE!$A:$A,M$2) -> 0 | N184: =SUMIFS(BASE!$G:$G,BASE!$B:$B,$B184,BASE!$L:$L,$G184,BASE!$J:$J,$C184,BASE!$A:$A,N$2) -> 0 | O184: =SUMIFS(BASE!$G:$G,BASE!$B:$B,$B184,BASE!$L:$L,$G184,BASE!$J:$J,$C184,BASE!$A:$A,O$2) -> 0 | P184: =SUMIFS(BASE!$G:$G,BASE!$B:$B,$B184,BASE!$L:$L,$G184,BASE!$J:$J,$C184,BASE!$A:$A,P$2) -> 0 | Q184: =SUMIFS(BASE!$G:$G,BASE!$B:$B,$B184,BASE!$L:$L,$G184,BASE!$J:$J,$C184,BASE!$A:$A,Q$2) -> 0 | R184: =SUMIFS(BASE!$G:$G,BASE!$B:$B,$B184,BASE!$L:$L,$G184,BASE!$J:$J,$C184,BASE!$A:$A,R$2) -> 0 | ... V184: =SUMIFS(BASE!$G:$G,BASE!$B:$B,$B184,BASE!$L:$L,$G184,BASE!$J:$J,$C184,BASE!$A:$A,V$2) -> 0 | X184: =IF(AND(R184=0),"ZERADO","COM TROCAS") -> ZERADO
B185: 63SQ | C185: MAX CEL GV LTDA | D185: JESSICA PEREIRA BOTELHO ARRUDA | E185: BRENNER SOUZA RODRIGUES | F185: GOVERNADOR VALADARES | G185: MG | H185: =IFERROR(IF(_xlfn.XLOOKUP(B185,REPASSE!D:D,REPASSE!D:D)="","Não","Sim"),"Não") -> Não | I185: =IF(_xlfn.XLOOKUP(B185,'BOOST LIBERADO'!B:B,'BOOST LIBERADO'!B:B,"Não")="Não","Não","Sim") -> Sim | J185: =IF(AND(H185="Não",I185="Sim"),"Sim","Não") -> Sim | K185: =SUMIFS(BASE!$G:$G,BASE!$B:$B,$B185,BASE!$L:$L,$G185,BASE!$J:$J,$C185,BASE!$A:$A,K$2) -> 0 | L185: =SUMIFS(BASE!$G:$G,BASE!$B:$B,$B185,BASE!$L:$L,$G185,BASE!$J:$J,$C185,BASE!$A:$A,L$2) -> 0 | M185: =SUMIFS(BASE!$G:$G,BASE!$B:$B,$B185,BASE!$L:$L,$G185,BASE!$J:$J,$C185,BASE!$A:$A,M$2) -> 0 | N185: =SUMIFS(BASE!$G:$G,BASE!$B:$B,$B185,BASE!$L:$L,$G185,BASE!$J:$J,$C185,BASE!$A:$A,N$2) -> 0 | O185: =SUMIFS(BASE!$G:$G,BASE!$B:$B,$B185,BASE!$L:$L,$G185,BASE!$J:$J,$C185,BASE!$A:$A,O$2) -> 0 | P185: =SUMIFS(BASE!$G:$G,BASE!$B:$B,$B185,BASE!$L:$L,$G185,BASE!$J:$J,$C185,BASE!$A:$A,P$2) -> 0 | Q185: =SUMIFS(BASE!$G:$G,BASE!$B:$B,$B185,BASE!$L:$L,$G185,BASE!$J:$J,$C185,BASE!$A:$A,Q$2) -> 0 | R185: =SUMIFS(BASE!$G:$G,BASE!$B:$B,$B185,BASE!$L:$L,$G185,BASE!$J:$J,$C185,BASE!$A:$A,R$2) -> 0 | ... V185: =SUMIFS(BASE!$G:$G,BASE!$B:$B,$B185,BASE!$L:$L,$G185,BASE!$J:$J,$C185,BASE!$A:$A,V$2) -> 0 | X185: =IF(AND(R185=0),"ZERADO","COM TROCAS") -> ZERADO
B186: M8XO | C186: TELECELL TELEFONIA LTDA - ME | D186: JOSIANA EMILIA SILVA FARIA | E186: KAROLINE LAMAS DE ANDRADE | F186: CATAGUASES | G186: MG | H186: =IFERROR(IF(_xlfn.XLOOKUP(B186,REPASSE!D:D,REPASSE!D:D)="","Não","Sim"),"Não") -> Não | I186: =IF(_xlfn.XLOOKUP(B186,'BOOST LIBERADO'!B:B,'BOOST LIBERADO'!B:B,"Não")="Não","Não","Sim") -> Sim | J186: =IF(AND(H186="Não",I186="Sim"),"Sim","Não") -> Sim | K186: =SUMIFS(BASE!$G:$G,BASE!$B:$B,$B186,BASE!$L:$L,$G186,BASE!$J:$J,$C186,BASE!$A:$A,K$2) -> 9 | L186: =SUMIFS(BASE!$G:$G,BASE!$B:$B,$B186,BASE!$L:$L,$G186,BASE!$J:$J,$C186,BASE!$A:$A,L$2) -> 7 | M186: =SUMIFS(BASE!$G:$G,BASE!$B:$B,$B186,BASE!$L:$L,$G186,BASE!$J:$J,$C186,BASE!$A:$A,M$2) -> 19 | N186: =SUMIFS(BASE!$G:$G,BASE!$B:$B,$B186,BASE!$L:$L,$G186,BASE!$J:$J,$C186,BASE!$A:$A,N$2) -> 16 | O186: =SUMIFS(BASE!$G:$G,BASE!$B:$B,$B186,BASE!$L:$L,$G186,BASE!$J:$J,$C186,BASE!$A:$A,O$2) -> 10 | P186: =SUMIFS(BASE!$G:$G,BASE!$B:$B,$B186,BASE!$L:$L,$G186,BASE!$J:$J,$C186,BASE!$A:$A,P$2) -> 13 | Q186: =SUMIFS(BASE!$G:$G,BASE!$B:$B,$B186,BASE!$L:$L,$G186,BASE!$J:$J,$C186,BASE!$A:$A,Q$2) -> 13 | R186: =SUMIFS(BASE!$G:$G,BASE!$B:$B,$B186,BASE!$L:$L,$G186,BASE!$J:$J,$C186,BASE!$A:$A,R$2) -> 4 | ... V186: =SUMIFS(BASE!$G:$G,BASE!$B:$B,$B186,BASE!$L:$L,$G186,BASE!$J:$J,$C186,BASE!$A:$A,V$2) -> 0 | X186: =IF(AND(R186=0),"ZERADO","COM TROCAS") -> COM TROCAS
B187: 9VBP | C187: FAJULUTI | D187: LUIS CARLOS DE ASSIS | E187: JORGE PEREIRA AZAMBUJA FILHO | F187: LAVRAS | G187: MG | H187: =IFERROR(IF(_xlfn.XLOOKUP(B187,REPASSE!D:D,REPASSE!D:D)="","Não","Sim"),"Não") -> Não | I187: =IF(_xlfn.XLOOKUP(B187,'BOOST LIBERADO'!B:B,'BOOST LIBERADO'!B:B,"Não")="Não","Não","Sim") -> Sim | J187: =IF(AND(H187="Não",I187="Sim"),"Sim","Não") -> Sim | K187: =SUMIFS(BASE!$G:$G,BASE!$B:$B,$B187,BASE!$L:$L,$G187,BASE!$J:$J,$C187,BASE!$A:$A,K$2) -> 0 | L187: =SUMIFS(BASE!$G:$G,BASE!$B:$B,$B187,BASE!$L:$L,$G187,BASE!$J:$J,$C187,BASE!$A:$A,L$2) -> 0 | M187: =SUMIFS(BASE!$G:$G,BASE!$B:$B,$B187,BASE!$L:$L,$G187,BASE!$J:$J,$C187,BASE!$A:$A,M$2) -> 0 | N187: =SUMIFS(BASE!$G:$G,BASE!$B:$B,$B187,BASE!$L:$L,$G187,BASE!$J:$J,$C187,BASE!$A:$A,N$2) -> 0 | O187: =SUMIFS(BASE!$G:$G,BASE!$B:$B,$B187,BASE!$L:$L,$G187,BASE!$J:$J,$C187,BASE!$A:$A,O$2) -> 1 | P187: =SUMIFS(BASE!$G:$G,BASE!$B:$B,$B187,BASE!$L:$L,$G187,BASE!$J:$J,$C187,BASE!$A:$A,P$2) -> 1 | Q187: =SUMIFS(BASE!$G:$G,BASE!$B:$B,$B187,BASE!$L:$L,$G187,BASE!$J:$J,$C187,BASE!$A:$A,Q$2) -> 4 | R187: =SUMIFS(BASE!$G:$G,BASE!$B:$B,$B187,BASE!$L:$L,$G187,BASE!$J:$J,$C187,BASE!$A:$A,R$2) -> 4 | ... V187: =SUMIFS(BASE!$G:$G,BASE!$B:$B,$B187,BASE!$L:$L,$G187,BASE!$J:$J,$C187,BASE!$A:$A,V$2) -> 0 | X187: =IF(AND(R187=0),"ZERADO","COM TROCAS") -> COM TROCAS
B188: OBT4 | C188: P.G.L CELULARES LTDA | D188: LUANA PAULA PICANCO CASTRO INOUE | E188: BRENNER SOUZA RODRIGUES | F188: MARIANA | G188: MG | H188: =IFERROR(IF(_xlfn.XLOOKUP(B188,REPASSE!D:D,REPASSE!D:D)="","Não","Sim"),"Não") -> Não | I188: =IF(_xlfn.XLOOKUP(B188,'BOOST LIBERADO'!B:B,'BOOST LIBERADO'!B:B,"Não")="Não","Não","Sim") -> Sim | J188: =IF(AND(H188="Não",I188="Sim"),"Sim","Não") -> Sim | K188: =SUMIFS(BASE!$G:$G,BASE!$B:$B,$B188,BASE!$L:$L,$G188,BASE!$J:$J,$C188,BASE!$A:$A,K$2) -> 0 | L188: =SUMIFS(BASE!$G:$G,BASE!$B:$B,$B188,BASE!$L:$L,$G188,BASE!$J:$J,$C188,BASE!$A:$A,L$2) -> 0 | M188: =SUMIFS(BASE!$G:$G,BASE!$B:$B,$B188,BASE!$L:$L,$G188,BASE!$J:$J,$C188,BASE!$A:$A,M$2) -> 0 | N188: =SUMIFS(BASE!$G:$G,BASE!$B:$B,$B188,BASE!$L:$L,$G188,BASE!$J:$J,$C188,BASE!$A:$A,N$2) -> 0 | O188: =SUMIFS(BASE!$G:$G,BASE!$B:$B,$B188,BASE!$L:$L,$G188,BASE!$J:$J,$C188,BASE!$A:$A,O$2) -> 0 | P188: =SUMIFS(BASE!$G:$G,BASE!$B:$B,$B188,BASE!$L:$L,$G188,BASE!$J:$J,$C188,BASE!$A:$A,P$2) -> 0 | Q188: =SUMIFS(BASE!$G:$G,BASE!$B:$B,$B188,BASE!$L:$L,$G188,BASE!$J:$J,$C188,BASE!$A:$A,Q$2) -> 0 | R188: =SUMIFS(BASE!$G:$G,BASE!$B:$B,$B188,BASE!$L:$L,$G188,BASE!$J:$J,$C188,BASE!$A:$A,R$2) -> 1 | ... V188: =SUMIFS(BASE!$G:$G,BASE!$B:$B,$B188,BASE!$L:$L,$G188,BASE!$J:$J,$C188,BASE!$A:$A,V$2) -> 0 | X188: =IF(AND(R188=0),"ZERADO","COM TROCAS") -> COM TROCAS
B189: H5LD | C189: TELECELL TELEFONIA LTDA - ME | D189: CYNTIA SILVA BIANCHETTI | E189: KAROLINE LAMAS DE ANDRADE | F189: OURO BRANCO | G189: MG | H189: =IFERROR(IF(_xlfn.XLOOKUP(B189,REPASSE!D:D,REPASSE!D:D)="","Não","Sim"),"Não") -> Não | I189: =IF(_xlfn.XLOOKUP(B189,'BOOST LIBERADO'!B:B,'BOOST LIBERADO'!B:B,"Não")="Não","Não","Sim") -> Sim | J189: =IF(AND(H189="Não",I189="Sim"),"Sim","Não") -> Sim | K189: =SUMIFS(BASE!$G:$G,BASE!$B:$B,$B189,BASE!$L:$L,$G189,BASE!$J:$J,$C189,BASE!$A:$A,K$2) -> 0 | L189: =SUMIFS(BASE!$G:$G,BASE!$B:$B,$B189,BASE!$L:$L,$G189,BASE!$J:$J,$C189,BASE!$A:$A,L$2) -> 0 | M189: =SUMIFS(BASE!$G:$G,BASE!$B:$B,$B189,BASE!$L:$L,$G189,BASE!$J:$J,$C189,BASE!$A:$A,M$2) -> 0 | N189: =SUMIFS(BASE!$G:$G,BASE!$B:$B,$B189,BASE!$L:$L,$G189,BASE!$J:$J,$C189,BASE!$A:$A,N$2) -> 0 | O189: =SUMIFS(BASE!$G:$G,BASE!$B:$B,$B189,BASE!$L:$L,$G189,BASE!$J:$J,$C189,BASE!$A:$A,O$2) -> 0 | P189: =SUMIFS(BASE!$G:$G,BASE!$B:$B,$B189,BASE!$L:$L,$G189,BASE!$J:$J,$C189,BASE!$A:$A,P$2) -> 0 | Q189: =SUMIFS(BASE!$G:$G,BASE!$B:$B,$B189,BASE!$L:$L,$G189,BASE!$J:$J,$C189,BASE!$A:$A,Q$2) -> 2 | R189: =SUMIFS(BASE!$G:$G,BASE!$B:$B,$B189,BASE!$L:$L,$G189,BASE!$J:$J,$C189,BASE!$A:$A,R$2) -> 0 | ... V189: =SUMIFS(BASE!$G:$G,BASE!$B:$B,$B189,BASE!$L:$L,$G189,BASE!$J:$J,$C189,BASE!$A:$A,V$2) -> 0 | X189: =IF(AND(R189=0),"ZERADO","COM TROCAS") -> ZERADO
B190: JFQ0 | C190: MOBILE TELECOM LTDA | D190: LUCAS FERREIRA BERTOZZI | E190: JORGE PEREIRA AZAMBUJA FILHO | F190: GUAXUPE | G190: MG | H190: =IFERROR(IF(_xlfn.XLOOKUP(B190,REPASSE!D:D,REPASSE!D:D)="","Não","Sim"),"Não") -> Não | I190: =IF(_xlfn.XLOOKUP(B190,'BOOST LIBERADO'!B:B,'BOOST LIBERADO'!B:B,"Não")="Não","Não","Sim") -> Sim | J190: =IF(AND(H190="Não",I190="Sim"),"Sim","Não") -> Sim | K190: =SUMIFS(BASE!$G:$G,BASE!$B:$B,$B190,BASE!$L:$L,$G190,BASE!$J:$J,$C190,BASE!$A:$A,K$2) -> 0 | L190: =SUMIFS(BASE!$G:$G,BASE!$B:$B,$B190,BASE!$L:$L,$G190,BASE!$J:$J,$C190,BASE!$A:$A,L$2) -> 0 | M190: =SUMIFS(BASE!$G:$G,BASE!$B:$B,$B190,BASE!$L:$L,$G190,BASE!$J:$J,$C190,BASE!$A:$A,M$2) -> 0 | N190: =SUMIFS(BASE!$G:$G,BASE!$B:$B,$B190,BASE!$L:$L,$G190,BASE!$J:$J,$C190,BASE!$A:$A,N$2) -> 0 | O190: =SUMIFS(BASE!$G:$G,BASE!$B:$B,$B190,BASE!$L:$L,$G190,BASE!$J:$J,$C190,BASE!$A:$A,O$2) -> 0 | P190: =SUMIFS(BASE!$G:$G,BASE!$B:$B,$B190,BASE!$L:$L,$G190,BASE!$J:$J,$C190,BASE!$A:$A,P$2) -> 0 | Q190: =SUMIFS(BASE!$G:$G,BASE!$B:$B,$B190,BASE!$L:$L,$G190,BASE!$J:$J,$C190,BASE!$A:$A,Q$2) -> 0 | R190: =SUMIFS(BASE!$G:$G,BASE!$B:$B,$B190,BASE!$L:$L,$G190,BASE!$J:$J,$C190,BASE!$A:$A,R$2) -> 0 | ... V190: =SUMIFS(BASE!$G:$G,BASE!$B:$B,$B190,BASE!$L:$L,$G190,BASE!$J:$J,$C190,BASE!$A:$A,V$2) -> 0 | X190: =IF(AND(R190=0),"ZERADO","COM TROCAS") -> ZERADO
B191: JQUQ | C191: RCM CAPITAL PARTICIPACOES LTDA | D191: CYNTIA SILVA BIANCHETTI | E191: KAROLINE LAMAS DE ANDRADE | F191: CONSELHEIRO LAFAIETE | G191: MG | H191: =IFERROR(IF(_xlfn.XLOOKUP(B191,REPASSE!D:D,REPASSE!D:D)="","Não","Sim"),"Não") -> Não | I191: =IF(_xlfn.XLOOKUP(B191,'BOOST LIBERADO'!B:B,'BOOST LIBERADO'!B:B,"Não")="Não","Não","Sim") -> Sim | J191: =IF(AND(H191="Não",I191="Sim"),"Sim","Não") -> Sim | K191: =SUMIFS(BASE!$G:$G,BASE!$B:$B,$B191,BASE!$L:$L,$G191,BASE!$J:$J,$C191,BASE!$A:$A,K$2) -> 0 | L191: =SUMIFS(BASE!$G:$G,BASE!$B:$B,$B191,BASE!$L:$L,$G191,BASE!$J:$J,$C191,BASE!$A:$A,L$2) -> 0 | M191: =SUMIFS(BASE!$G:$G,BASE!$B:$B,$B191,BASE!$L:$L,$G191,BASE!$J:$J,$C191,BASE!$A:$A,M$2) -> 0 | N191: =SUMIFS(BASE!$G:$G,BASE!$B:$B,$B191,BASE!$L:$L,$G191,BASE!$J:$J,$C191,BASE!$A:$A,N$2) -> 0 | O191: =SUMIFS(BASE!$G:$G,BASE!$B:$B,$B191,BASE!$L:$L,$G191,BASE!$J:$J,$C191,BASE!$A:$A,O$2) -> 0 | P191: =SUMIFS(BASE!$G:$G,BASE!$B:$B,$B191,BASE!$L:$L,$G191,BASE!$J:$J,$C191,BASE!$A:$A,P$2) -> 0 | Q191: =SUMIFS(BASE!$G:$G,BASE!$B:$B,$B191,BASE!$L:$L,$G191,BASE!$J:$J,$C191,BASE!$A:$A,Q$2) -> 0 | R191: =SUMIFS(BASE!$G:$G,BASE!$B:$B,$B191,BASE!$L:$L,$G191,BASE!$J:$J,$C191,BASE!$A:$A,R$2) -> 0 | ... V191: =SUMIFS(BASE!$G:$G,BASE!$B:$B,$B191,BASE!$L:$L,$G191,BASE!$J:$J,$C191,BASE!$A:$A,V$2) -> 0 | X191: =IF(AND(R191=0),"ZERADO","COM TROCAS") -> ZERADO
B192: VSGL | C192: CELNET COMERCIO E SERVICOS DE TELEFONIA LTDA ME | D192: AMANDA DE CASTRO SILVA VAZ | E192: MARIA BEATRIZ AGUIAR MARRA | F192: GOIANIA | G192: CO | H192: =IFERROR(IF(_xlfn.XLOOKUP(B192,REPASSE!D:D,REPASSE!D:D)="","Não","Sim"),"Não") -> Não | I192: =IF(_xlfn.XLOOKUP(B192,'BOOST LIBERADO'!B:B,'BOOST LIBERADO'!B:B,"Não")="Não","Não","Sim") -> Sim | J192: =IF(AND(H192="Não",I192="Sim"),"Sim","Não") -> Sim | K192: =SUMIFS(BASE!$G:$G,BASE!$B:$B,$B192,BASE!$L:$L,$G192,BASE!$J:$J,$C192,BASE!$A:$A,K$2) -> 0 | L192: =SUMIFS(BASE!$G:$G,BASE!$B:$B,$B192,BASE!$L:$L,$G192,BASE!$J:$J,$C192,BASE!$A:$A,L$2) -> 0 | M192: =SUMIFS(BASE!$G:$G,BASE!$B:$B,$B192,BASE!$L:$L,$G192,BASE!$J:$J,$C192,BASE!$A:$A,M$2) -> 2 | N192: =SUMIFS(BASE!$G:$G,BASE!$B:$B,$B192,BASE!$L:$L,$G192,BASE!$J:$J,$C192,BASE!$A:$A,N$2) -> 1 | O192: =SUMIFS(BASE!$G:$G,BASE!$B:$B,$B192,BASE!$L:$L,$G192,BASE!$J:$J,$C192,BASE!$A:$A,O$2) -> 2 | P192: =SUMIFS(BASE!$G:$G,BASE!$B:$B,$B192,BASE!$L:$L,$G192,BASE!$J:$J,$C192,BASE!$A:$A,P$2) -> 2 | Q192: =SUMIFS(BASE!$G:$G,BASE!$B:$B,$B192,BASE!$L:$L,$G192,BASE!$J:$J,$C192,BASE!$A:$A,Q$2) -> 2 | R192: =SUMIFS(BASE!$G:$G,BASE!$B:$B,$B192,BASE!$L:$L,$G192,BASE!$J:$J,$C192,BASE!$A:$A,R$2) -> 2 | ... V192: =SUMIFS(BASE!$G:$G,BASE!$B:$B,$B192,BASE!$L:$L,$G192,BASE!$J:$J,$C192,BASE!$A:$A,V$2) -> 0 | X192: =IF(AND(R192=0),"ZERADO","COM TROCAS") -> COM TROCAS
B193: 4Z2T | C193: TELECELL TELEFONIA LTDA - ME | D193: DAVID GOMES DA SILVA | E193: MARIA BEATRIZ AGUIAR MARRA | F193: GOIANIA | G193: CO | H193: =IFERROR(IF(_xlfn.XLOOKUP(B193,REPASSE!D:D,REPASSE!D:D)="","Não","Sim"),"Não") -> Não | I193: =IF(_xlfn.XLOOKUP(B193,'BOOST LIBERADO'!B:B,'BOOST LIBERADO'!B:B,"Não")="Não","Não","Sim") -> Sim | J193: =IF(AND(H193="Não",I193="Sim"),"Sim","Não") -> Sim | K193: =SUMIFS(BASE!$G:$G,BASE!$B:$B,$B193,BASE!$L:$L,$G193,BASE!$J:$J,$C193,BASE!$A:$A,K$2) -> 2 | L193: =SUMIFS(BASE!$G:$G,BASE!$B:$B,$B193,BASE!$L:$L,$G193,BASE!$J:$J,$C193,BASE!$A:$A,L$2) -> 0 | M193: =SUMIFS(BASE!$G:$G,BASE!$B:$B,$B193,BASE!$L:$L,$G193,BASE!$J:$J,$C193,BASE!$A:$A,M$2) -> 4 | N193: =SUMIFS(BASE!$G:$G,BASE!$B:$B,$B193,BASE!$L:$L,$G193,BASE!$J:$J,$C193,BASE!$A:$A,N$2) -> 2 | O193: =SUMIFS(BASE!$G:$G,BASE!$B:$B,$B193,BASE!$L:$L,$G193,BASE!$J:$J,$C193,BASE!$A:$A,O$2) -> 0 | P193: =SUMIFS(BASE!$G:$G,BASE!$B:$B,$B193,BASE!$L:$L,$G193,BASE!$J:$J,$C193,BASE!$A:$A,P$2) -> 1 | Q193: =SUMIFS(BASE!$G:$G,BASE!$B:$B,$B193,BASE!$L:$L,$G193,BASE!$J:$J,$C193,BASE!$A:$A,Q$2) -> 2 | R193: =SUMIFS(BASE!$G:$G,BASE!$B:$B,$B193,BASE!$L:$L,$G193,BASE!$J:$J,$C193,BASE!$A:$A,R$2) -> 0 | ... V193: =SUMIFS(BASE!$G:$G,BASE!$B:$B,$B193,BASE!$L:$L,$G193,BASE!$J:$J,$C193,BASE!$A:$A,V$2) -> 0 | X193: =IF(AND(R193=0),"ZERADO","COM TROCAS") -> ZERADO
... B1008: 6UK0 | C1008: S D COMERCIO DE CELULARES LTDA - ME | D1008: TAINA MISTURINI | E1008: CASSIO VENTURA LORENZET | F1008: VERANOPOLIS | G1008: RS | H1008: =IFERROR(IF(_xlfn.XLOOKUP(B1008,REPASSE!D:D,REPASSE!D:D)="","Não","Sim"),"Não") -> Não | I1008: =IF(_xlfn.XLOOKUP(B1008,'BOOST LIBERADO'!B:B,'BOOST LIBERADO'!B:B,"Não")="Não","Não","Sim") -> Sim | J1008: =IF(AND(H1008="Não",I1008="Sim"),"Sim","Não") -> Sim | K1008: =SUMIFS(BASE!$G:$G,BASE!$B:$B,$B1008,BASE!$L:$L,$G1008,BASE!$J:$J,$C1008,BASE!$A:$A,K$2) -> 0 | L1008: =SUMIFS(BASE!$G:$G,BASE!$B:$B,$B1008,BASE!$L:$L,$G1008,BASE!$J:$J,$C1008,BASE!$A:$A,L$2) -> 3 | M1008: =SUMIFS(BASE!$G:$G,BASE!$B:$B,$B1008,BASE!$L:$L,$G1008,BASE!$J:$J,$C1008,BASE!$A:$A,M$2) -> 2 | N1008: =SUMIFS(BASE!$G:$G,BASE!$B:$B,$B1008,BASE!$L:$L,$G1008,BASE!$J:$J,$C1008,BASE!$A:$A,N$2) -> 3 | O1008: =SUMIFS(BASE!$G:$G,BASE!$B:$B,$B1008,BASE!$L:$L,$G1008,BASE!$J:$J,$C1008,BASE!$A:$A,O$2) -> 3 | P1008: =SUMIFS(BASE!$G:$G,BASE!$B:$B,$B1008,BASE!$L:$L,$G1008,BASE!$J:$J,$C1008,BASE!$A:$A,P$2) -> 0 | Q1008: =SUMIFS(BASE!$G:$G,BASE!$B:$B,$B1008,BASE!$L:$L,$G1008,BASE!$J:$J,$C1008,BASE!$A:$A,Q$2) -> 3 | R1008: =SUMIFS(BASE!$G:$G,BASE!$B:$B,$B1008,BASE!$L:$L,$G1008,BASE!$J:$J,$C1008,BASE!$A:$A,R$2) -> 1 | ... V1008: =SUMIFS(BASE!$G:$G,BASE!$B:$B,$B1008,BASE!$L:$L,$G1008,BASE!$J:$J,$C1008,BASE!$A:$A,V$2) -> 0 | X1008: =IF(AND(R1008=0),"ZERADO","COM TROCAS") -> COM TROCAS
K1009: =SUMIFS(BASE!$G:$G,BASE!$B:$B,$B1009,BASE!$L:$L,$G1009,BASE!$J:$J,$C1009,BASE!$A:$A,K$2) -> 0 | L1009: =SUMIFS(BASE!$G:$G,BASE!$B:$B,$B1009,BASE!$L:$L,$G1009,BASE!$J:$J,$C1009,BASE!$A:$A,L$2) -> 0 | M1009: =SUMIFS(BASE!$G:$G,BASE!$B:$B,$B1009,BASE!$L:$L,$G1009,BASE!$J:$J,$C1009,BASE!$A:$A,M$2) -> 0 | N1009: =SUMIFS(BASE!$G:$G,BASE!$B:$B,$B1009,BASE!$L:$L,$G1009,BASE!$J:$J,$C1009,BASE!$A:$A,N$2) -> 0 | O1009: =SUMIFS(BASE!$G:$G,BASE!$B:$B,$B1009,BASE!$L:$L,$G1009,BASE!$J:$J,$C1009,BASE!$A:$A,O$2) -> 0 | P1009: =SUMIFS(BASE!$G:$G,BASE!$B:$B,$B1009,BASE!$L:$L,$G1009,BASE!$J:$J,$C1009,BASE!$A:$A,P$2) -> 0 | Q1009: =SUMIFS(BASE!$G:$G,BASE!$B:$B,$B1009,BASE!$L:$L,$G1009,BASE!$J:$J,$C1009,BASE!$A:$A,Q$2) -> 0 | R1009: =SUMIFS(BASE!$G:$G,BASE!$B:$B,$B1009,BASE!$L:$L,$G1009,BASE!$J:$J,$C1009,BASE!$A:$A,R$2) -> 0 | ... V1009: =SUMIFS(BASE!$G:$G,BASE!$B:$B,$B1009,BASE!$L:$L,$G1009,BASE!$J:$J,$C1009,BASE!$A:$A,V$2) -> 0
B1010: QNRC | C1010: TELEMAIS TELEFONIA LTDA - ME | F1010: SAO LUIS DE MONTES BELOS | G1010: CO | H1010: =IFERROR(IF(_xlfn.XLOOKUP(B1010,REPASSE!D:D,REPASSE!D:D)="","Não","Sim"),"Não") -> Não | I1010: =IF(_xlfn.XLOOKUP(B1010,'BOOST LIBERADO'!B:B,'BOOST LIBERADO'!B:B,"Não")="Não","Não","Sim") -> Sim | J1010: =IF(AND(H1010="Não",I1010="Sim"),"Sim","Não") -> Sim | K1010: =SUMIFS(BASE!$G:$G,BASE!$B:$B,$B1010,BASE!$L:$L,$G1010,BASE!$J:$J,$C1010,BASE!$A:$A,K$2) -> 0 | L1010: =SUMIFS(BASE!$G:$G,BASE!$B:$B,$B1010,BASE!$L:$L,$G1010,BASE!$J:$J,$C1010,BASE!$A:$A,L$2) -> 0 | M1010: =SUMIFS(BASE!$G:$G,BASE!$B:$B,$B1010,BASE!$L:$L,$G1010,BASE!$J:$J,$C1010,BASE!$A:$A,M$2) -> 0 | N1010: =SUMIFS(BASE!$G:$G,BASE!$B:$B,$B1010,BASE!$L:$L,$G1010,BASE!$J:$J,$C1010,BASE!$A:$A,N$2) -> 0 | O1010: =SUMIFS(BASE!$G:$G,BASE!$B:$B,$B1010,BASE!$L:$L,$G1010,BASE!$J:$J,$C1010,BASE!$A:$A,O$2) -> 0 | P1010: =SUMIFS(BASE!$G:$G,BASE!$B:$B,$B1010,BASE!$L:$L,$G1010,BASE!$J:$J,$C1010,BASE!$A:$A,P$2) -> 0 | Q1010: =SUMIFS(BASE!$G:$G,BASE!$B:$B,$B1010,BASE!$L:$L,$G1010,BASE!$J:$J,$C1010,BASE!$A:$A,Q$2) -> 10 | R1010: =SUMIFS(BASE!$G:$G,BASE!$B:$B,$B1010,BASE!$L:$L,$G1010,BASE!$J:$J,$C1010,BASE!$A:$A,R$2) -> 4 | ... V1010: =SUMIFS(BASE!$G:$G,BASE!$B:$B,$B1010,BASE!$L:$L,$G1010,BASE!$J:$J,$C1010,BASE!$A:$A,V$2) -> 0 | X1010: =IF(AND(R1010=0),"ZERADO","COM TROCAS") -> COM TROCAS

Sheet BASE
A1: MÊS | B1: COMTA | C1: CIDADE | D1: PARCEIRO | E1: REG | F1: Sellout | G1: Claro troca | H1: Share | I1: Attachment | J1: GRUPO REDE | K1: REPASSE? | L1: REGIONAL | M1: REPETE
A2: 46023 | B2: 5Z2B | C2: CAMPINAS | D2: FLEX CELL | E2: SP2 | F2: 147 | G2: 60 | H2: 0.029985007 | I2: 0.40816327 | J2: =_xlfn.XLOOKUP(B2,CAD_PDV!A:A,CAD_PDV!B:B) -> FLEX CELL | K2: =IF(IFERROR(_xlfn.XLOOKUP(B2,Planilha2!D:D,Planilha2!H:H),0)="SIM",1,0) -> 0 | L2: =_xlfn.XLOOKUP(B2,CAD_PDV!A:A,CAD_PDV!C:C) -> SP2 | M2: =IFERROR(_xlfn.XLOOKUP(B2,repete!A:A,repete!A:A),"-") -> -
A3: 46023 | B3: PNYS | C3: BRASILIA | D3: CELNET COMERCIO E SERVICOS DE TELEFONIA LTDA ME | E3: CO | F3: 171 | G3: 56 | H3: 0.027986007 | I3: 0.32748538 | J3: =_xlfn.XLOOKUP(B3,CAD_PDV!A:A,CAD_PDV!B:B) -> CELNET COMERCIO E SERVICOS DE TELEFONIA LTDA ME | K3: =IF(IFERROR(_xlfn.XLOOKUP(B3,Planilha2!D:D,Planilha2!H:H),0)="SIM",1,0) -> 0 | L3: =_xlfn.XLOOKUP(B3,CAD_PDV!A:A,CAD_PDV!C:C) -> CO | M3: =IFERROR(_xlfn.XLOOKUP(B3,repete!A:A,repete!A:A),"-") -> -
A4: 46023 | B4: PG9B | C4: ARARAQUARA | D4: HS TELECOM | E4: SP2 | F4: 230 | G4: 43 | H4: 0.021489255 | I4: 0.18695652 | J4: =_xlfn.XLOOKUP(B4,CAD_PDV!A:A,CAD_PDV!B:B) -> HS TELECOM | K4: =IF(IFERROR(_xlfn.XLOOKUP(B4,Planilha2!D:D,Planilha2!H:H),0)="SIM",1,0) -> 0 | L4: =_xlfn.XLOOKUP(B4,CAD_PDV!A:A,CAD_PDV!C:C) -> SP2 | M4: =IFERROR(_xlfn.XLOOKUP(B4,repete!A:A,repete!A:A),"-") -> -
A5: 46023 | B5: PG8N | C5: SAO JOSE DO RIO PRETO | D5: HS TELECOM | E5: SP2 | F5: 220 | G5: 41 | H5: 0.020489755 | I5: 0.18636364 | J5: =_xlfn.XLOOKUP(B5,CAD_PDV!A:A,CAD_PDV!B:B) -> HS TELECOM | K5: =IF(IFERROR(_xlfn.XLOOKUP(B5,Planilha2!D:D,Planilha2!H:H),0)="SIM",1,0) -> 0 | L5: =_xlfn.XLOOKUP(B5,CAD_PDV!A:A,CAD_PDV!C:C) -> SP2 | M5: =IFERROR(_xlfn.XLOOKUP(B5,repete!A:A,repete!A:A),"-") -> -
A6: 46023 | B6: G1NS | C6: BRASILIA | D6: CELNET COMERCIO E SERVICOS DE TELEFONIA LTDA ME | E6: CO | F6: 241 | G6: 37 | H6: 0.018490755 | I6: 0.15352697 | J6: =_xlfn.XLOOKUP(B6,CAD_PDV!A:A,CAD_PDV!B:B) -> CELNET COMERCIO E SERVICOS DE TELEFONIA LTDA ME | K6: =IF(IFERROR(_xlfn.XLOOKUP(B6,Planilha2!D:D,Planilha2!H:H),0)="SIM",1,0) -> 0 | L6: =_xlfn.XLOOKUP(B6,CAD_PDV!A:A,CAD_PDV!C:C) -> CO | M6: =IFERROR(_xlfn.XLOOKUP(B6,repete!A:A,repete!A:A),"-") -> -
A7: 46023 | B7: JTX8 | C7: RIBEIRAO PRETO | D7: HS TELECOM | E7: SP2 | F7: 266 | G7: 33 | H7: 0.016491754 | I7: 0.12406015 | J7: =_xlfn.XLOOKUP(B7,CAD_PDV!A:A,CAD_PDV!B:B) -> HS TELECOM | K7: =IF(IFERROR(_xlfn.XLOOKUP(B7,Planilha2!D:D,Planilha2!H:H),0)="SIM",1,0) -> 0 | L7: =_xlfn.XLOOKUP(B7,CAD_PDV!A:A,CAD_PDV!C:C) -> SP2 | M7: =IFERROR(_xlfn.XLOOKUP(B7,repete!A:A,repete!A:A),"-") -> -
A8: 46023 | B8: PT9F | C8: RIBEIRAO PRETO | D8: HS TELECOM | E8: SP2 | F8: 139 | G8: 33 | H8: 0.016491754 | I8: 0.23741007 | J8: =_xlfn.XLOOKUP(B8,CAD_PDV!A:A,CAD_PDV!B:B) -> HS TELECOM | K8: =IF(IFERROR(_xlfn.XLOOKUP(B8,Planilha2!D:D,Planilha2!H:H),0)="SIM",1,0) -> 0 | L8: =_xlfn.XLOOKUP(B8,CAD_PDV!A:A,CAD_PDV!C:C) -> SP2 | M8: =IFERROR(_xlfn.XLOOKUP(B8,repete!A:A,repete!A:A),"-") -> -
A9: 46023 | B9: HS2M | C9: BRASILIA | D9: CELNET COMERCIO E SERVICOS DE TELEFONIA LTDA ME | E9: CO | F9: 137 | G9: 32 | H9: 0.015992004 | I9: 0.23357664 | J9: =_xlfn.XLOOKUP(B9,CAD_PDV!A:A,CAD_PDV!B:B) -> CELNET COMERCIO E SERVICOS DE TELEFONIA LTDA ME | K9: =IF(IFERROR(_xlfn.XLOOKUP(B9,Planilha2!D:D,Planilha2!H:H),0)="SIM",1,0) -> 0 | L9: =_xlfn.XLOOKUP(B9,CAD_PDV!A:A,CAD_PDV!C:C) -> CO | M9: =IFERROR(_xlfn.XLOOKUP(B9,repete!A:A,repete!A:A),"-") -> -
A10: 46023 | B10: ERH6 | C10: SAO JOSE DOS CAMPOS | D10: HS TELECOM | E10: SP2 | F10: 149 | G10: 29 | H10: 0.014492754 | I10: 0.19463087 | J10: =_xlfn.XLOOKUP(B10,CAD_PDV!A:A,CAD_PDV!B:B) -> HS TELECOM | K10: =IF(IFERROR(_xlfn.XLOOKUP(B10,Planilha2!D:D,Planilha2!H:H),0)="SIM",1,0) -> 0 | L10: =_xlfn.XLOOKUP(B10,CAD_PDV!A:A,CAD_PDV!C:C) -> SP2 | M10: =IFERROR(_xlfn.XLOOKUP(B10,repete!A:A,repete!A:A),"-") -> -
A11: 46023 | B11: 5LYK | C11: NATAL | D11: HARCOS COMERCIO E SERVICOS LTDA - EPP | E11: NE | F11: 205 | G11: 28 | H11: 0.013993003 | I11: 0.13658537 | J11: =_xlfn.XLOOKUP(B11,CAD_PDV!A:A,CAD_PDV!B:B) -> HARCOS COMERCIO E SERVICOS LTDA - EPP | K11: =IF(IFERROR(_xlfn.XLOOKUP(B11,Planilha2!D:D,Planilha2!H:H),0)="SIM",1,0) -> 0 | L11: =_xlfn.XLOOKUP(B11,CAD_PDV!A:A,CAD_PDV!C:C) -> NE | M11: =IFERROR(_xlfn.XLOOKUP(B11,repete!A:A,repete!A:A),"-") -> -
A12: 46023 | B12: PT2E | C12: BARRETOS | D12: HS TELECOM | E12: SP2 | F12: 117 | G12: 27 | H12: 0.013493253 | I12: 0.23076923 | J12: =_xlfn.XLOOKUP(B12,CAD_PDV!A:A,CAD_PDV!B:B) -> HS TELECOM | K12: =IF(IFERROR(_xlfn.XLOOKUP(B12,Planilha2!D:D,Planilha2!H:H),0)="SIM",1,0) -> 0 | L12: =_xlfn.XLOOKUP(B12,CAD_PDV!A:A,CAD_PDV!C:C) -> SP2 | M12: =IFERROR(_xlfn.XLOOKUP(B12,repete!A:A,repete!A:A),"-") -> -
A13: 46023 | B13: 4O0E | C13: ITABUNA | D13: HS TELECOM | E13: BA/SE | F13: 65 | G13: 24 | H13: 0.011994003 | I13: 0.36923077 | J13: =_xlfn.XLOOKUP(B13,CAD_PDV!A:A,CAD_PDV!B:B) -> HS TELECOM | K13: =IF(IFERROR(_xlfn.XLOOKUP(B13,Planilha2!D:D,Planilha2!H:H),0)="SIM",1,0) -> 0 | L13: =_xlfn.XLOOKUP(B13,CAD_PDV!A:A,CAD_PDV!C:C) -> BA/SE | M13: =IFERROR(_xlfn.XLOOKUP(B13,repete!A:A,repete!A:A),"-") -> -
... A3030: 46235 | B3030: ZORH | C3030: JARAGUA | D3030: TELECELL TELEFONIA LTDA - ME | E3030: CO | F3030: 20 | G3030: 1 | H3030: 0.00026014568 | I3030: 0.052631579 | J3030: =_xlfn.XLOOKUP(B3030,CAD_PDV!A:A,CAD_PDV!B:B) -> TELECELL TELEFONIA LTDA - ME | K3030: =IF(IFERROR(_xlfn.XLOOKUP(B3030,Planilha2!D:D,Planilha2!H:H),0)="SIM",1,0) -> 0 | L3030: =_xlfn.XLOOKUP(B3030,CAD_PDV!A:A,CAD_PDV!C:C) -> CO | M3030: =IFERROR(_xlfn.XLOOKUP(B3030,repete!A:A,repete!A:A),"-") -> -
A3031: 46235 | B3031: 05RO | C3031: FOZ DO IGUACU | D3031: S D COMERCIO DE CELULARES LTDA - ME | E3031: SUL | F3031: 31 | J3031: =_xlfn.XLOOKUP(B3031,CAD_PDV!A:A,CAD_PDV!B:B) -> S D COMERCIO DE CELULARES LTDA - ME | K3031: =IF(IFERROR(_xlfn.XLOOKUP(B3031,Planilha2!D:D,Planilha2!H:H),0)="SIM",1,0) -> 0 | L3031: =_xlfn.XLOOKUP(B3031,CAD_PDV!A:A,CAD_PDV!C:C) -> PR/SC | M3031: =IFERROR(_xlfn.XLOOKUP(B3031,repete!A:A,repete!A:A),"-") -> -
A3032: 46235 | B3032: 07AB | C3032: OSORIO | D3032: EDUARDO JUNQUEIRA DA SILVEIRA ADMIN | E3032: SUL | F3032: 7 | J3032: =_xlfn.XLOOKUP(B3032,CAD_PDV!A:A,CAD_PDV!B:B) -> EDUARDO JUNQUEIRA DA SILVEIRA ADMIN | K3032: =IF(IFERROR(_xlfn.XLOOKUP(B3032,Planilha2!D:D,Planilha2!H:H),0)="SIM",1,0) -> 0 | L3032: =_xlfn.XLOOKUP(B3032,CAD_PDV!A:A,CAD_PDV!C:C) -> RS | M3032: =IFERROR(_xlfn.XLOOKUP(B3032,repete!A:A,repete!A:A),"-") -> -
A3033: 46235 | B3033: 08GH | C3033: PERUIBE | D3033: DIEGO FERNANDES PEREIRA - ME | E3033: SP2 | F3033: 30 | J3033: =_xlfn.XLOOKUP(B3033,CAD_PDV!A:A,CAD_PDV!B:B) -> DIEGO FERNANDES PEREIRA - ME | K3033: =IF(IFERROR(_xlfn.XLOOKUP(B3033,Planilha2!D:D,Planilha2!H:H),0)="SIM",1,0) -> 1 | L3033: =_xlfn.XLOOKUP(B3033,CAD_PDV!A:A,CAD_PDV!C:C) -> SP2 | M3033: =IFERROR(_xlfn.XLOOKUP(B3033,repete!A:A,repete!A:A),"-") -> -
A3034: 46235 | B3034: 0BRK | C3034: BELO HORIZONTE | D3034: CELLULAR.COM | E3034: MG | F3034: 6 | J3034: =_xlfn.XLOOKUP(B3034,CAD_PDV!A:A,CAD_PDV!B:B) -> CELLULAR.COM | K3034: =IF(IFERROR(_xlfn.XLOOKUP(B3034,Planilha2!D:D,Planilha2!H:H),0)="SIM",1,0) -> 0 | L3034: =_xlfn.XLOOKUP(B3034,CAD_PDV!A:A,CAD_PDV!C:C) -> MG | M3034: =IFERROR(_xlfn.XLOOKUP(B3034,repete!A:A,repete!A:A),"-") -> -
A3035: 46235 | B3035: 0KNX | C3035: ACAILANDIA | D3035: AM3 TELECOM LTDA | E3035: NO | F3035: 2 | J3035: =_xlfn.XLOOKUP(B3035,CAD_PDV!A:A,CAD_PDV!B:B) -> AM3 TELECOM LTDA | K3035: =IF(IFERROR(_xlfn.XLOOKUP(B3035,Planilha2!D:D,Planilha2!H:H),0)="SIM",1,0) -> 0 | L3035: =_xlfn.XLOOKUP(B3035,CAD_PDV!A:A,CAD_PDV!C:C) -> NO | M3035: =IFERROR(_xlfn.XLOOKUP(B3035,repete!A:A,repete!A:A),"-") -> -
A3036: 46235 | B3036: 0O92 | C3036: CAMPO FORMOSO | D3036: MARIA JOSEFA DOS SANTOS - ME | E3036: BA/SE | F3036: 12 | J3036: =_xlfn.XLOOKUP(B3036,CAD_PDV!A:A,CAD_PDV!B:B) -> MARIA JOSEFA DOS SANTOS - ME | K3036: =IF(IFERROR(_xlfn.XLOOKUP(B3036,Planilha2!D:D,Planilha2!H:H),0)="SIM",1,0) -> 0 | L3036: =_xlfn.XLOOKUP(B3036,CAD_PDV!A:A,CAD_PDV!C:C) -> BA/SE | M3036: =IFERROR(_xlfn.XLOOKUP(B3036,repete!A:A,repete!A:A),"-") -> -
A3037: 46235 | B3037: 0ZP0 | C3037: CASTANHAL | D3037: INOVACELL LTDA | E3037: NO | F3037: 10 | J3037: =_xlfn.XLOOKUP(B3037,CAD_PDV!A:A,CAD_PDV!B:B) -> INOVACELL LTDA | K3037: =IF(IFERROR(_xlfn.XLOOKUP(B3037,Planilha2!D:D,Planilha2!H:H),0)="SIM",1,0) -> 0 | L3037: =_xlfn.XLOOKUP(B3037,CAD_PDV!A:A,CAD_PDV!C:C) -> NO | M3037: =IFERROR(_xlfn.XLOOKUP(B3037,repete!A:A,repete!A:A),"-") -> -
A3038: 46235 | B3038: 14HB | C3038: GARANHUNS | D3038: FABIANA GONCALVES DA SILVA LINS E CIA LTDA | E3038: NE | F3038: 9 | J3038: =_xlfn.XLOOKUP(B3038,CAD_PDV!A:A,CAD_PDV!B:B) -> FABIANA GONCALVES DA SILVA LINS E CIA LTDA | K3038: =IF(IFERROR(_xlfn.XLOOKUP(B3038,Planilha2!D:D,Planilha2!H:H),0)="SIM",1,0) -> 0 | L3038: =_xlfn.XLOOKUP(B3038,CAD_PDV!A:A,CAD_PDV!C:C) -> NE | M3038: =IFERROR(_xlfn.XLOOKUP(B3038,repete!A:A,repete!A:A),"-") -> -
A3039: 46235 | B3039: 14Q6 | C3039: APARECIDA DE GOIANIA | D3039: CELNET COMERCIO E SERVICOS DE TELEFONIA LTDA ME | E3039: CO | F3039: 22 | J3039: =_xlfn.XLOOKUP(B3039,CAD_PDV!A:A,CAD_PDV!B:B) -> CELNET COMERCIO E SERVICOS DE TELEFONIA LTDA ME | K3039: =IF(IFERROR(_xlfn.XLOOKUP(B3039,Planilha2!D:D,Planilha2!H:H),0)="SIM",1,0) -> 0 | L3039: =_xlfn.XLOOKUP(B3039,CAD_PDV!A:A,CAD_PDV!C:C) -> CO | M3039: =IFERROR(_xlfn.XLOOKUP(B3039,repete!A:A,repete!A:A),"-") -> -
A3040: 46235 | B3040: 18FJ | C3040: GOIANIA | D3040: CALDAS CELULARES LTDA - ME | E3040: CO | F3040: 2 | J3040: =_xlfn.XLOOKUP(B3040,CAD_PDV!A:A,CAD_PDV!B:B) -> CALDAS CELULARES LTDA - ME | K3040: =IF(IFERROR(_xlfn.XLOOKUP(B3040,Planilha2!D:D,Planilha2!H:H),0)="SIM",1,0) -> 0 | L3040: =_xlfn.XLOOKUP(B3040,CAD_PDV!A:A,CAD_PDV!C:C) -> CO | M3040: =IFERROR(_xlfn.XLOOKUP(B3040,repete!A:A,repete!A:A),"-") -> -
A3041: 46235 | B3041: 198Y | C3041: CONGONHAS | D3041: P.G.L CELULARES LTDA | E3041: MG | F3041: 7 | J3041: =_xlfn.XLOOKUP(B3041,CAD_PDV!A:A,CAD_PDV!B:B) -> P.G.L CELULARES LTDA | K3041: =IF(IFERROR(_xlfn.XLOOKUP(B3041,Planilha2!D:D,Planilha2!H:H),0)="SIM",1,0) -> 0 | L3041: =_xlfn.XLOOKUP(B3041,CAD_PDV!A:A,CAD_PDV!C:C) -> MG | M3041: =IFERROR(_xlfn.XLOOKUP(B3041,repete!A:A,repete!A:A),"-") -> -
A3042: 46235 | B3042: 1AP6 | C3042: PITANGUEIRAS | D3042: CELLULAR.COM | E3042: SP2 | F3042: 12 | J3042: =_xlfn.XLOOKUP(B3042,CAD_PDV!A:A,CAD_PDV!B:B) -> CELLULAR.COM | K3042: =IF(IFERROR(_xlfn.XLOOKUP(B3042,Planilha2!D:D,Planilha2!H:H),0)="SIM",1,0) -> 0 | L3042: =_xlfn.XLOOKUP(B3042,CAD_PDV!A:A,CAD_PDV!C:C) -> SP2 | M3042: =IFERROR(_xlfn.XLOOKUP(B3042,repete!A:A,repete!A:A),"-") -> -
... A3532: 46235 | B3532: ZULC | C3532: CALDAS NOVAS | D3532: MEGA CELULAR | E3532: CO | F3532: 29 | J3532: =_xlfn.XLOOKUP(B3532,CAD_PDV!A:A,CAD_PDV!B:B) -> MEGA CELULAR | K3532: =IF(IFERROR(_xlfn.XLOOKUP(B3532,Planilha2!D:D,Planilha2!H:H),0)="SIM",1,0) -> 0 | L3532: =_xlfn.XLOOKUP(B3532,CAD_PDV!A:A,CAD_PDV!C:C) -> CO | M3532: =IFERROR(_xlfn.XLOOKUP(B3532,repete!A:A,repete!A:A),"-") -> -

Sheet INSTRUÇÕES
A1: INSTRUÇÕES — ATUALIZAÇÃO
A2: Guia para exportar o BI, atualizar a BASE e validar o fechamento do relatório.
A4: 📥 ETAPAS DA ATUALIZAÇÃO
A5: ETAPA | B5: AÇÃO | C5: VALIDAÇÃO
A6: 1 | B6: No BI: Gestão de Vendas → Claro Troca - Reg. Selecione AA e somente o mês que será atualizado. | C6: Confirme que o período mostra apenas o mês desejado e que Regional/Parceiro estão em Todos.
A7: 2 | B7: Atualize o BI e exporte os dados resumidos para Excel. | C7: Compare no BI os totais de Sellout, Claro Troca e Attachment.
A8: 3 | B8: Abra este relatório, anexe a extração e envie o prompt semanal abaixo. | C8: Não faça colagem manual em células filtradas ou intervalos descontínuos.
A9: 4 | B9: Aguarde a atualização das abas BASE, CAD_PDV, PDVS e dos resumos. | C9: BASE e PDVS precisam fechar no mesmo total de Claro Troca.
A10: 5 | B10: Consulte o Dashboard e selecione o mês atualizado. | C10: Revise KPIs, regionais prioritárias e TOP parceiros.
A12: 🔗 ORIGEM DOS DADOS
A13: Power BI | B13: Bi aparelhos | C13: Acesse o relatório corporativo usado para a exportação semanal.
A14: 🤖 PROMPT SEMANAL — COPIE E ENVIE COM A EXTRAÇÃO ANEXADA
A15: Atualize este relatório com o arquivo do BI anexado. 1. Identifique o mês da extração pelos filtros e pelos dados do arquivo. 2. Antes de alterar a BASE, leia toda a extração e informe a quantidade de linhas, Sellout, Claro Troca e Attachment. 3. Na aba BASE, exclua somente os registros existentes do mês identificado, preservando os demais meses. 4. Importe todas as linhas da extração, sem ignorar linhas filtradas, intervalos ocultos ou registros com Claro Troca em branco/zero. 5. Preencha o mês em todas as linhas importadas e copie as fórmulas das colunas J:M para todas as novas linhas. 6. Atualize o CAD_PDV para códigos novos. Use Grupo Rede = parceiro da extração. Para Regional, converta SUL em PR/SC ou RS conforme o cadastro e sinalize qualquer dúvida. 7. Inclua códigos novos na aba PDVS e estenda todas as fórmulas mensais e de status. 8. Recalcule Dashboard, TOP 10 Parceiros, REGIONAL, GRUPOS ZERADOS, GRUPOS e PDVS. 9. Compare a extração, BASE e PDVS em: quantidade de linhas, Sellout, Claro Troca e Attachment. 10. Verifique se todas as linhas importadas têm mês e fórmulas auxiliares, e se não existem erros #N/D, #REF!, #VALOR! ou #DIV/0!. 11. Não finalize enquanto BASE e PDVS não estiverem reconciliadas no total de Claro Troca. 12. Ao concluir, informe: mês atualizado, totais finais, códigos novos, cadastros corrigidos e qualquer divergência restante.
A31: ✅ CHECKLIST DE FECHAMENTO
A32: CONTROLE | B32: RESULTADO ESPERADO | C32: AÇÃO SE DIVERGIR
A33: Linhas importadas | B33: Igual à quantidade da extração do BI | C33: Verificar filtros, linhas ocultas e mês vazio na BASE.
A34: Sellout | B34: BASE igual ao arquivo exportado | C34: Reimportar o mês completo.
A35: Claro Troca | B35: BI = extração = BASE = PDVS | C35: Localizar códigos ausentes ou fórmulas não preenchidas.
A36: Attachment | B36: Claro Troca ÷ Sellout | C36: Confirmar que o indicador está ponderado, não como média simples.
A37: Erros de cadastro | B37: Nenhum #N/D em GRUPO REDE ou REGIONAL | C37: Atualizar o CAD_PDV e normalizar códigos numéricos como texto.

Sheet REPASSE
A1: REGIONAL | B1: CIDADE | C1: PARCEIRO | D1: CODIGO | E1: PARCEIRO | F1: PRAZO | G1: DATA REPASSE | H1: REPASSE
A2: BA/SE | B2: SANTO ANTONIO DE JESUS | C2: PRIME | D2: 3YN8 | E2: PAULA NIELLA | F2: 46174 | H2: SIM
A3: CO | B3: SIDROLANDIA | C3: FELIAN | D3: 63X0 | E3: AMERICOM | F3: 46024 | H3: SIM
A4: CO | B4: BONITO | C4: SANDRI | D4: LH5E | E4: DR MEDEIROS | F4: 46024 | H4: SIM
A5: CO | B5: APARECIDA DE GOIANIA | C5: ATUAL | D5: 07E8 | E5: CELNET | F5: 46082 | H5: SIM
A6: CO | B6: GOIANIRA | C6: ATUAL | D6: 9KY0 | E6: TATIANE CONCEIÇÃO | F6: 46082 | H6: SIM
A7: CO | B7: GOIANIA | C7: ATUAL | D7: KVL8 | E7: CELNET | F7: 46082 | H7: SIM
A8: CO | B8: NEROPOLIS | C8: ATUAL | D8: QB3V | E8: CELNET | F8: 46082 | H8: SIM
A9: CO | B9: GOIANIA | C9: ATUAL | D9: QRH5 | E9: CELNET | F9: 46082 | H9: SIM
A10: CO | B10: APARECIDA DE GOIANIA | C10: ATUAL | D10: U5HE | E10: CELNET | F10: 46082 | H10: SIM
A11: CO | B11: INHUMAS | C11: ATUAL | D11: WGRQ | E11: CELNET | F11: 46082 | H11: SIM
A12: CO | B12: JARDIM | C12: SANDRI | D12: AFOM | E12: DR MEDEIROS | F12: 46082 | H12: SIM
A13: CO | B13: BOM JESUS DE GOIAS | C13: CONTATO | D13: 5LQA | E13: MEGA CELULAR | F13: 46113 | H13: SIM
... A22: CO | B22: ESPIGÃO D'OESTE | C22: MASTER COMERCIO | D22: 4SDV | E22: JUCELL CELULARES LTDA | F22: 46174 | H22: SIM
A23: CO | B23: VILHENA | C23: MASTER COMERCIO | D23: 5I62 | E23: TELECELL | F23: 46235 | G23: NÃO FINALZIADA | H23: SIM
A24: CO | B24: PORTO VELHO | C24: MASTERCELL | D24: A7O4 | E24: TELECELL | F24: 46235 | G24: NÃO FINALZIADA | H24: SIM
A25: CO | B25: PORTO VELHO | C25: MASTERCELL | D25: UMX1 | E25: TELECELL | F25: 46235 | G25: NÃO FINALZIADA | H25: SIM
A26: CO | B26: PARANAÍBA | C26: ESTULANO | D26: HXPE | E26: FELIAN | F26: 46235 | G26: NÃO FINALZIADA | H26: SIM
A27: CO | B27: CORUMBÁ | C27: SANDRI | D27: LCGM | E27: AMERICOM | F27: 46204 | H27: SIM
A28: CO | B28: AQUIDAUANA | C28: SANDRI | D28: 9PN8 | E28: AMERICOM | F28: 46204 | H28: SIM
A29: MG | B29: MONTES CLAROS | C29: CARIBE E PAULINO | D29: Q0E0 | E29: PRIME TELECOM COMERCIO E SERVIÇOS | F29: 46174 | G29: ENCERROU OPERAÇÃO EM 25, REPASSOU EM 26. | H29: SIM
A30: MG | B30: ITABIRA | C30: INOVA TELECOM LTDA | D30: 6EST | E30: TELECELL | F30: 46204 | H30: SIM
A31: MG | B31: PONTE NOVA | C31: ATENDE | D31: LG93 | E31: TELECELL | F31: 46266 | H31: SIM
A32: MG | B32: UBA | C32: ALFA CELULAR LTDA | D32: O1I5 | E32: TELECELL | F32: 46296 | H32: SIM
A33: NO | B33: MANAUS | C33: DP SERVIÇOS | D33: HKYJ | E33: FLEXCELL | F33: 46023 | H33: SIM
A34: NO | B34: MANAUS | C34: DP SERVIÇOS | D34: NQXT | E34: FLEXCELL | F34: 46023 | H34: SIM
A35: NO | B35: CHAPADINHA | C35: J P OLIVEIRA COMERCIO - ME | D35: D7CU | E35: BRUNO DE OLIVEIRA | F35: 46024 | H35: SIM
A36: NO | B36: BARREIRINHAS | C36: NEWINFOR TECNOLOGIA & TELECOMUNICACOES EIRELI | D36: WEFK | E36: DSX | F36: 46025 | H36: SIM
A37: NO | B37: MANAUS | C37: DIN | D37: R1U4 | E37: FLEXCELL | F37: 46143 | H37: SIM
A38: NO | B38: SÃO LUIS | C38: EGALENO | D38: 0U4T | E38: DSX | F38: 46174 | H38: SIM
A39: NO | B39: SANTAREM | C39: EMERSSON | D39: 64ZB | E39: DIN | F39: 46204 | H39: SIM
A40: PR/SC | B40: GUARAPUAVA | C40: PACCO COMERCIO | D40: ISDF | E40: CELL.COM | F40: 46082 | H40: SIM
A41: PR/SC | B41: FRANCISCO BELTRÃO | C41: CELL.COM | D41: XPTO | E41: NORTEL (S.D) | F41: 46113 | H41: SIM
... A66: PR/SC | B66: RIO NEGRINHO | C66: CLINTEL | D66: AH4B | E66: BANDEIRA | F66: 46143 | H66: SIM
A67: RJ/ES | B67: PARAIBA DO SUL | C67: CAVALINHO | E67: GSM FREE | F67: 46082 | H67: SIM
A68: RS | B68: ALVORADA | C68: CELULAR BRASIL | D68: KB6L | E68: CELL.COM | F68: 46204 | H68: SIM
A69: RS | B69: CACHOEIRINHA | C69: CELULAR BRASIL | D69: 72Z0 | E69: CELL.COM | F69: 46204 | H69: SIM
A70: RS | B70: CACHOEIRINHA | C70: CELULAR BRASIL | D70: 82I2 | E70: CELL.COM | F70: 46204 | H70: SIM
A71: RS | B71: CACHOEIRINHA | C71: CELULAR BRASIL | D71: TBQ0 | E71: CELL.COM | F71: 46204 | H71: SIM
A72: RS | B72: CANOAS | C72: CELULAR BRASIL | D72: 7BH0 | E72: CELL.COM | F72: 46204 | H72: SIM
A73: RS | B73: ALEGRETE | C73: DICERE | D73: XPTO1222 | E73: A DEFINIR | H73: SIM
A74: RS | B74: ROSARIO DO SUL | C74: DICERE | D74: 2I91 | E74: A DEFINIR | H74: SIM
A75: RS | B75: URUGUAIANA | C75: DICERE | D75: UZJ2 | E75: A DEFINIR | H75: SIM
A76: SP1 | B76: SÃO PAULO | C76: KG COMERCIO | D76: XX | E76: CLARICELL | F76: 46082 | H76: SIM
A77: SP1 | B77: SÃO PAULO | C77: KG COMERCIO | D77: XX | E77: CLARICELL | F77: 46204 | H77: SIM
A78: SP1 | B78: SÃO PAULO | C78: KG COMERCIO | D78: XX | E78: CLARICELL | F78: 46204 | H78: SIM
A79: SP2 | B79: PERUIBE | C79: DIEGO | D79: 08GH | E79: FLEX CELL | F79: 46327 | G79: PARCEIRO EM PROCESSO DE NOTIFICAÇÃO | H79: SIM
A80: SP2 | B80: PRAIA GRANDE | C80: DIEGO | D80: 2LOC | E80: FLEX CELL | F80: 46327 | G80: PARCEIRO EM PROCESSO DE NOTIFICAÇÃO | H80: SIM
A81: SP2 | B81: ITANHAEM | C81: DIEGO | D81: 3Q90 | E81: FLEX CELL | F81: 46327 | G81: PARCEIRO EM PROCESSO DE NOTIFICAÇÃO | H81: SIM
A82: SP2 | B82: REGISTRO | C82: DIEGO | D82: FP4S | E82: FLEX CELL | F82: 46327 | G82: PARCEIRO EM PROCESSO DE NOTIFICAÇÃO | H82: SIM
A83: SP2 | B83: MONGAGUA | C83: DIEGO | D83: NK1R | E83: FLEX CELL | F83: 46327 | G83: PARCEIRO EM PROCESSO DE NOTIFICAÇÃO | H83: SIM
A84: SP1 | B84: SALTO | C84: LINK | D84: PEGAR | E84: RP COMERCIO | F84: 46113
A85: SP1 | B85: SÃO ROQUE | C85: LINK | D85: PEGAR | E85: RP COMERCIO | F85: 46113
A86: SP1 | B86: MAIRINQUE | C86: LINK | D86: PEGAR | E86: RP COMERCIO | F86: 46113
A87: BA/SE | B87: JACOBINA | C87: CASA NOVA | E87: HS TELECOM | F87: 46235
A88: BA/SE | B88: CASA NOVA | C88: CASA NOVA | E88: HS TELECOM | F88: 46235
A89: NE | B89: MOSSORÓ | C89: R&R Hiper | D89: 1LTD | E89: NAUM RAONI VARELA DOS SANTOS TELEFONIA E SERVICOS EIRELI | F89: 46204 | G89: XPTO1527 | H89: SIM
A90: NE | B90: SERRA TALHADA | C90: JF EQUIPAMENTOS | D90: N405 | E90: ITALO CARVALHO CAVALCANTI & CIA LTDA | F90: 46204 | G90: XPTO1538 | H90: SIM
A91: NE | B91: SALGUEIRO | C91: Fabiana Gonçalves | D91: U2R4 | E91: ITALO CARVALHO CAVALCANTI & CIA LTDA | F91: 46204 | G91: XPTO1539 | H91: SIM
A92: NE | B92: GOIANA | C92: Carlos Frederico | D92: QNDL | E92: J L DE VASCONCELOS | F92: 46113 | G92: XPTO1517 | H92: SIM
A93: NE | B93: PICOS | C93: G Mobile | D93: 7 1 E 5 | E93: DELTA CELL TELECOMUNICACOES LTDA | F93: 46082 | G93: XPTO1432 | H93: SIM
A94: NE | B94: FLORIANO | C94: G Mobile | D94: YAPF | E94: DELTA CELL TELECOMUNICACOES LTDA | F94: 46082 | G94: XPTO1435 | H94: SIM
A95: NE | B95: TERESINA | C95: G Mobile | D95: L0I3 | E95: SELF TELECOM PI COMERCIO E SERVICOS EM TELEFONIA LTDA | F95: 45901 | G95: XPTO1433 | H95: SIM

Sheet BOOST LIBERADO
A1: REGIONAL | B1: CÓDIGO LOJA | C1: CNPJ | D1: RAZÃO SOCIAL (CONFORME CADASTRO IW)
A2: NE | B2: XTRJ | C2: 3006494000100 | D2: R & R HIPER COMERCIO LTDA
A3: NE | B3: IH1V | C3: 3006494001262 | D3: R & R HIPER COMERCIO LTDA
A4: NE | B4: 0QEA | C4: 3006494001696 | D4: R & R HIPER COMERCIO LTDA
A5: NE | B5: Z0VH | C5: 3006494001777 | D5: R & R HIPER COMERCIO LTDA
A6: NE | B6: 1LTD | C6: 3006494001858 | D6: R & R HIPER COMERCIO LTDA
A7: NE | B7: H0ZF | C7: 3006494001939 | D7: R & R HIPER COMERCIO LTDA
A8: SPC | B8: CB2A | C8: 3243382000172 | D8: FLEX CELL COMERCIO DE CELULARES LTDA
A9: SPC | B9: H9LX | C9: 3243382000253 | D9: FLEX CELL COMERCIO DE CELULARES LTDA
A10: SPC | B10: K5RE | C10: 3243382000334 | D10: FLEX CELL COMERCIO DE CELULARES LTDA
A11: SPC | B11: 0L6Z | C11: 3243382000415 | D11: FLEX CELL COMERCIO DE CELULARES LTDA
A12: SPC | B12: 2GJ0 | C12: 3243382000504 | D12: FLEX CELL COMERCIO DE CELULARES LTDA
A13: SPC | B13: 8CLM | C13: 3243382000687 | D13: FLEX CELL COMERCIO DE CELULARES LTDA
... A784: NE | B784: R9S5 | C784: 3006494002234 | D784: R & R HIPER COMERCIO LTDA
A785: MG | B785: M8XO | C785: 03.555.618/0058-41 | D785: TELECELL TELEFONIA LTDA
A786: NO | B786: QL1X | C786: 58092747000520 | D786: INOVACELL LTDA
A787: SP2 | B787: ZIK2 | C787: 3243382004402 | D787: FLEX CELL COMERCIO DE CELULARES LTDA
A788: BA/SE | B788: 0O92 | C788: '21.783.328/0002-82 | D788: J B DOS SANTOS RODRIGUES LTDA
A789: BA/SE | B789: 32JL | C789: '16.835.059/0001-30 | D789: PARCELL ELETRO E TELECOMUNICACAO EIRELI
A790: BA/SE | B790: 3WC6 | C790: '23.001.614/0001-93 | D790: QUERO CELL COMUNICACAO EIRELI
A791: BA/SE | B791: 3YN8 | C791: '36.768.551/0003-09 | D791: E-MEAN SERVICOS DE MARKETING DIRETO LTDA
A792: BA/SE | B792: 4UKO | C792: '57.179.494/0001-30 | D792: TELECOM EXPRESS LTDA
A793: BA/SE | B793: 8H3Z | C793: '37.575.053/0001-40 | D793: SHEILA RIOS OLIVEIRA LTDA
A794: BA/SE | B794: 9YT6 | C794: '35.366.419/0002-27 | D794: SIM MAGAZINE CONQUISTA LTDA
A795: BA/SE | B795: CTI7 | C795: '27.605.332/0001-56 | D795: R & J CELULARES E ACESSORIOS EIRELI
A796: BA/SE | B796: DCYP | C796: '35.645.088/0001-83 | D796: SILVA SILVA TELEFONIA E COMUNICAO LTDA
A797: BA/SE | B797: IT27 | C797: '31.102.019/0001-72 | D797: C A SANTOS COMUNICACAO LTDA
A798: BA/SE | B798: JVSV | C798: '54.534.832/0001-17 | D798: TELECOMUNICACOES CASA NOVA LTDA
A799: BA/SE | B799: L2H5 | C799: '09.587.919/0001-06 | D799: VIAFONE-COMERCIO DE ELETRO-ELETRONICOS LTDA
... A810: BA/SE | B810: 9XE2 | C810: 26.080.840/0002-86 | D810: A PLAY S COMERCIO E SERVICOS LTDA
A811: RJ/ES | B811: KDBX | C811: 26117255004381 | D811: FAJULUTI GAVEA TELECOM COMERCIO DE MATERIAL DE TELECOMUNICACAO LTDA
A812: RJ/ES | B812: 37W8 | C812: 26117255004462 | D812: FAJULUTI GAVEA TELECOM COMERCIO DE MATERIAL DE TELECOMUNICACAO LTDA
A813: RJ/ES | B813: G0XH | C813: 26117255004705 | D813: FAJULUTI GAVEA TELECOM COMERCIO DE MATERIAL DE TELECOMUNICACAO LTDA
A814: RJ/ES | B814: UT2F | C814: 26117255004896 | D814: FAJULUTI GAVEA TELECOM COMERCIO DE MATERIAL DE TELECOMUNICACAO LTDA
A815: RJ/ES | B815: FEYW | C815: 26117255004624 | D815: FAJULUTI GAVEA TELECOM COMERCIO DE MATERIAL DE TELECOMUNICACAO LTDA
A816: RJ/ES | B816: WQ3S | C816: 26117255004209 | D816: FAJULUTI GAVEA TELECOM COMERCIO DE MATERIAL DE TELECOMUNICACAO LTDA
A817: RJ/ES | B817: POGA | C817: 26117255004543 | D817: FAJULUTI GAVEA TELECOM COMERCIO DE MATERIAL DE TELECOMUNICACAO LTDA
A818: RJ/ES | B818: I5TV | C818: 26117255004977 | D818: FAJULUTI GAVEA TELECOM COMERCIO DE MATERIAL DE TELECOMUNICACAO LTDA
A819: SP1 | B819: BIDJ | C819: 21848907001580 | D819: CLARICELL SANTO AMARO TELECOMUNICACOES LTDA
A820: SP1 | B820: HT50 | C820: 21848907001904 | D820: CLARICELL SANTO AMARO TELECOMUNICACOES LTDA
A821: SP2 | B821: KBV1 | C821: 5949641013008 | D821: RP COMERCIO E REPRESENTAÇÃO EM TELECOMUNICAÇÃO LTDA
A822: SP2 | B822: ANJT | C822: 5949641014403 | D822: RP COMERCIO E REPRESENTAÇÃO EM TELECOMUNICAÇÃO LTDA
... A878: RJ/ES | B878: H928 | C878: 5142929004913 | D878: PONTO CERTO COMERCIO E COMUNICACOES LTDA
A879: RJ/ES | B879: KBVT | C879: 08457462000144 | D879: LEINAD COMERCIO E SERVICO LTDA
A880: MG | B880: 8PVZ | C880: 05949641016880 | D880: RP COMERCIO E REPRESENTACAO EM TELECOMUNICACOES LTDA
A881: MG | B881: UTIQ | C881: 05949641016295 | D881: RP COMERCIO E REPRESENTACAO EM TELECOMUNICACOES LTDA
A882: MG | B882: 6SRL | C882: 05949641017186 | D882: RP COMERCIO E REPRESENTACAO EM TELECOMUNICACOES LTDA
A883: MG | B883: 2WDY | C883: 05949641017267 | D883: RP COMERCIO E REPRESENTACAO EM TELECOMUNICACOES LTDA
A884: MG | B884: Q40H | C884: 05949641016457 | D884: RP COMERCIO E REPRESENTACAO EM TELECOMUNICACOES LTDA
A885: MG | B885: EFD6 | C885: 05949641016023 | D885: RP COMERCIO E REPRESENTACAO EM TELECOMUNICACOES LTDA
A886: MG | B886: LW7S | C886: 05949641017003 | D886: RP COMERCIO E REPRESENTACAO EM TELECOMUNICACOES LTDA
A887: MG | B887: 7A4U | C887: 05949641017348 | D887: RP COMERCIO E REPRESENTACAO EM TELECOMUNICACOES LTDA
A888: CO | B888: ELJV | C888: 4601016002740 | D888: CELNET COMERCIO E SERVICOS DE TELEFONIA LTDA
A889: CO | B889: AMBF | C889: 24230714000235 | D889: DERZE & VIDAL LTDA
A890: RJ/ES | B890: G21T | C890: 5923253008216 | D890: HS TELECOM COM SERV E REPRES DE TEL MOVEL LTDA
A891: RJ/ES | B891: K9XU | C891: 5923253008305 | D891: HS TELECOM COM SERV E REPRES DE TEL MOVEL LTDA
A892: BA/SE | B892: 8PUR | C892: 5923253007830 | D892: HS TELECOM COMERCIO, SERVICOS E REPRESENTACAO DE TELEFONIA MOVEL LTDA
A893: CO | B893: FRFI | C893: 03555618007119 | D893: TELECELL TELEFONIA LTDA
A894: CO | B894: IESP | C894: 58659783000280 | D894: M. F TELECOMUNICACAO LTDA
A895: CO | B895: P4WC | C895: 58659783000108 | D895: M. F TELECOMUNICACAO LTDA
A896: CO | B896: BLSY | C896: 58659783000604 | D896: M. F TELECOMUNICACAO LTDA
A897: CO | B897: U5ES | C897: 58659783000876 | D897: M. F TELECOMUNICACAO LTDA
A898: CO | B898: 3SZM | C898: 58659783000442 | D898: M. F TELECOMUNICACAO LTDA
A899: CO | B899: HA0B | C899: 58659783000523 | D899: M. F TELECOMUNICACAO LTDA
A900: CO | B900: HPSI | C900: 58659783000795 | D900: M. F TELECOMUNICACAO LTDA
A901: RJ/ES | B901: 4Z0R | C901: 05142929005057 | D901: PONTO CERTO COMERCIO E COMUNICACOES LTDA
A902: RJ/ES | B902: 5BCS | C902: 08457462000810 | D902: LEINAD COMERCIO E SERVICO LTDA
A903: SP2 | B903: PMA1 | C903: 5949641013199 | D903: RP COMERCIO E REPRESENTACAO EM TELECOMUNICACOES LTDA
A904: SP2 | B904: FOXW | C904: 5949641017771 | D904: RP COMERCIO E REPRESENTACAO EM TELECOMUNICACOES LTDA
A905: PR/SC | B905: UVQG | C905: 5949641015213 | D905: RP COMERCIO E REPRESENTACAO EM TELECOMUNICACOES LTDA
A906: SP2 | B906: 5MEN | C906: 5949641015132 | D906: RP COMERCIO E REPRESENTACAO EM TELECOMUNICACOES LTDA
A907: SP2 | B907: 57HL | C907: 5949641001778 | D907: RP COMERCIO E REPRESENTACAO EM TELECOMUNICACOES LTDA
A908: SP2 | B908: X762 | C908: 5949641015051 | D908: RP COMERCIO E REPRESENTACAO EM TELECOMUNICACOES LTDA
A909: PR/SC | B909: Y4M4 | C909: 5949641014837 | D909: RP COMERCIO E REPRESENTACAO EM TELECOMUNICACOES LTDA
A910: PR/SC | B910: 7WTZ | C910: 5949641014918 | D910: RP COMERCIO E REPRESENTACAO EM TELECOMUNICACOES LTDA
A911: PR/SC | B911: IL79 | C911: 5949641015809 | D911: RP COMERCIO E REPRESENTACAO EM TELECOMUNICACOES LTDA
A912: PR/SC | B912: 8GWC | C912: 5949641015566 | D912: RP COMERCIO E REPRESENTACAO EM TELECOMUNICACOES LTDA
A913: PR/SC | B913: VEWQ | C913: 5949641015485 | D913: RP COMERCIO E REPRESENTACAO EM TELECOMUNICACOES LTDA
A914: PR/SC | B914: 9K9M | C914: 5949641015302 | D914: RP COMERCIO E REPRESENTACAO EM TELECOMUNICACOES LTDA
... A923: MG | B923: JFQ0 | C923: 42245037000200 | D923: MOBILE TELECOM LTDA
A924: MG | B924: I3L2 | C924: 05949641016961 | D924: RP COMERCIO E REPRESENTACAO EM TELECOMUNICACOES LTDA
A925: MG | B925: LBX4 | C925: 05949641017429 | D925: RP COMERCIO E REPRESENTACAO EM TELECOMUNICACOES LTDA
A926: MG | B926: MXJG | C926: 05949641016708 | D926: RP COMERCIO E REPRESENTACAO EM TELECOMUNICACOES LTDA
A927: MG | B927: KVHA | C927: 03555618006813 | D927: TELECELL TELEFONIA LTDA
A928: MG | B928: LE5A | C928: 03555618007208 | D928: TELECELL TELEFONIA LTDA
A929: MG | B929: 32SE | C929: 03555618006651 | D929: TELECELL TELEFONIA LTDA
A930: MG | B930: JQUQ | C930: 64343235000169 | D930: RCM CAPITAL PARTICIPACOES LTDA
A931: RJ/ES | B931: LRM4 | C931: 05923253008640 | D931: HS TELECOM COMERCIO, SERVICOS E REPRESENTACAO DE TELEFONIA MOVEL LTDA
A932: RJ/ES | B932: W5Q0 | C932: 05923253008488 | D932: HS TELECOM COMERCIO, SERVICOS E REPRESENTACAO DE TELEFONIA MOVEL LTDA
A933: RJ/ES | B933: ALED | C933: 05923253008569 | D933: HS TELECOM COMERCIO, SERVICOS E REPRESENTACAO DE TELEFONIA MOVEL LTDA
A934: RJ/ES | B934: F979 | C934: 05923253008720 | D934: HS TELECOM COMERCIO, SERVICOS E REPRESENTACAO DE TELEFONIA MOVEL LTDA
A935: SP2 | B935: CJIB | C935: 5923253008954 | D935: HS TELECOM COMERCIO, SERVICOS E REPRESENTACAO DE TELEFONIA MOVEL LTDA
A936: SP2 | B936: 6WBY | C936: 5923253007910 | D936: HS TELECOM COMERCIO, SERVICOS E REPRESENTACAO DE TELEFONIA MOVEL LTDA
A937: PR/SC | B937: P7YR | C937: 34324935001206 | D937: INTEGRA CONNECT TELECOMUNICACOES LTDA
A938: PR/SC | B938: 6C31 | C938: 29686678004815 | D938: EDUARDO JUNQUEIRA DA SILVEIRA LTDA
A939: PR/SC | B939: SR8N | C939: 29686678005200 | D939: EDUARDO JUNQUEIRA DA SILVEIRA LTDA
A940: RS | B940: L6TX | C940: 29686678005030 | D940: EDUARDO JUNQUEIRA DA SILVEIRA LTDA
A941: PR/SC | B941: ZA1P | C941: 29686678004491 | D941: EDUARDO JUNQUEIRA DA SILVEIRA LTDA
A942: RS | B942: 2M0Z | C942: 29686678005110 | D942: EDUARDO JUNQUEIRA DA SILVEIRA LTDA
A943: PR/SC | B943: X5FL | C943: 29686678004572 | D943: EDUARDO JUNQUEIRA DA SILVEIRA LTDA
...

Sheet repete
A1: repete
A2: 1NRI
A3: QLEQ
A4: NDTZ
A5: WD3T
A6: MHRS
A7: YEZ1
A8: FMBI
A9: 6J3J
A10: 5D78
A11: H83T

Sheet Planilha2
A1: REGIONAL | B1: CIDADE | C1: PARCEIRO | D1: CODIGO | E1: PARCEIRO | F1: PRAZO | G1: DATA REPASSE | H1: REPASSE
A2: BA/SE | B2: SANTO ANTONIO DE JESUS | C2: PRIME | D2: 3YN8 | E2: PAULA NIELLA | F2: 46174 | H2: SIM
A3: CO | B3: PARANAÍBA | C3: ESTULANO | D3: HXPE | E3: FELIAN | F3: 46204 | H3: SIM
A4: CO | B4: CORUMBÁ | C4: SANDRI | D4: LCGM | E4: AMERICOM | F4: 46204 | H4: SIM
A5: CO | B5: AQUIDAUANA | C5: SANDRI | D5: 9PN8 | E5: AMERICOM | F5: 46204 | H5: SIM
A6: CO | B6: CERES | C6: CONTATO | D6: PBK7 | E6: INFORCEL | F6: 46174 | H6: SIM
A7: CO | B7: CACOAL | C7: M JHUAN | D7: KORY | E7: TELECELL | F7: 46174 | H7: SIM
A8: CO | B8: PIMENTA BUENO | C8: MASTER COMERCIO | D8: HX95 | E8: TELECELL | F8: 46174 | H8: SIM
A9: CO | B9: ESPIGÃO D'OESTE | C9: MASTER COMERCIO | D9: 4SDV | E9: TELECELL | F9: 46174 | H9: SIM
A10: CO | B10: VILHENA | C10: MASTER COMERCIO | D10: 5I62 | E10: TELECELL | F10: 46174 | H10: SIM
A11: CO | B11: PORTO VELHO | C11: MASTERCELL | D11: A7O4 | E11: TELECELL | F11: 46174 | H11: SIM
A12: CO | B12: PORTO VELHO | C12: MASTERCELL | D12: UMX1 | E12: TELECELL | F12: 46174 | H12: SIM
A13: CO | B13: APARECIDA DE GOIANIA | C13: ATUAL | D13: TIR6 | E13: CALDAS CELULAR | F13: 46143 | H13: SIM
... A31: MG | B31: UBA | C31: ALFA CELULAR LTDA | D31: O1I5 | E31: TELECELL | F31: 46296 | H31: SIM
A32: MG | B32: MONTES CLAROS | C32: CARIBE E PAULINO | D32: Q0E0 | E32: PRIME TELECOM COMERCIO E SERVIÇOS | F32: 46174 | G32: ENCERROU OPERAÇÃO EM 25, REPASSOU EM 26. | H32: SIM
A33: NE | B33: MOSSORÓ | E33: NAUM | F33: 46204 | H33: SIM
A34: NO | B34: MANAUS | C34: DP SERVIÇOS | D34: HKYJ | E34: FLEXCELL | F34: 46023 | H34: SIM
A35: NO | B35: MANAUS | C35: DP SERVIÇOS | D35: NQXT | E35: FLEXCELL | F35: 46023 | H35: SIM
A36: NO | B36: CHAPADINHA | C36: J P OLIVEIRA COMERCIO - ME | D36: D7CU | E36: BRUNO DE OLIVEIRA | F36: 46024 | H36: SIM
A37: NO | B37: BARREIRINHAS | C37: NEWINFOR TECNOLOGIA & TELECOMUNICACOES EIRELI | D37: WEFK | E37: DSX | F37: 46025 | H37: SIM
A38: NO | B38: MANAUS | C38: DIN | D38: R1U4 | E38: FLEXCELL | F38: 46143 | H38: SIM
A39: NO | B39: SÃO LUIS | C39: EGALENO | D39: 0U4T | E39: DSX | F39: 46174 | H39: SIM
A40: PR/SC | B40: FRANCISCO BELTRÃO | C40: CELL.COM | D40: XPTO | E40: NORTEL (S.D) | F40: 46113 | H40: SIM
A41: PR/SC | B41: ARAUCARIA | C41: JOAO RENATO LEAL AFONSO - ME | D41: ENYJ | E41: RDJ | F41: 46113 | H41: SIM
A42: PR/SC | B42: CURITIBA | C42: JOAO RENATO LEAL AFONSO - ME | D42: HXDI | E42: RDJ | F42: 46113 | H42: SIM
A43: PR/SC | B43: FAZENDA RIO GRANDE | C43: JOAO RENATO LEAL AFONSO - ME | D43: HFSP | E43: RDJ | F43: 46113 | H43: SIM
A44: PR/SC | B44: CHAPECO GETÚLIO | C44: MRZ | D44: AB3W | E44: EDUARDO JUNQUEIRA | F44: 46113 | H44: SIM
A45: PR/SC | B45: CHAPECO MARECHAL | C45: MRZ | D45: HPRG | E45: EDUARDO JUNQUEIRA | F45: 46113 | H45: SIM
... A66: PR/SC | B66: RIO NEGRINHO | C66: CLINTEL | D66: AH4B | E66: BANDEIRA | F66: 46143 | H66: SIM
A67: RJ/ES | B67: PARAIBA DO SUL | C67: CAVALINHO | E67: GSM FREE | F67: 46082 | H67: SIM
A68: RS | B68: ALVORADA | C68: CELULAR BRASIL | D68: KB6L | E68: CELL.COM | F68: 46235 | H68: SIM
A69: RS | B69: CACHOEIRINHA | C69: CELULAR BRASIL | D69: 72Z0 | E69: CELL.COM | F69: 46235 | H69: SIM
A70: RS | B70: CACHOEIRINHA | C70: CELULAR BRASIL | D70: 82I2 | E70: CELL.COM | F70: 46235 | H70: SIM
A71: RS | B71: CACHOEIRINHA | C71: CELULAR BRASIL | D71: TBQ0 | E71: CELL.COM | F71: 46235 | H71: SIM
A72: RS | B72: CANOAS | C72: CELULAR BRASIL | D72: 7BH0 | E72: CELL.COM | F72: 46235 | H72: SIM
A73: RS | B73: ALEGRETE | C73: DICERE | D73: XPTO1222 | E73: A DEFINIR | H73: SIM
A74: RS | B74: ROSARIO DO SUL | C74: DICERE | D74: 2I91 | E74: A DEFINIR | H74: SIM
A75: RS | B75: URUGUAIANA | C75: DICERE | D75: UZJ2 | E75: A DEFINIR | H75: SIM
A76: SP1 | B76: SÃO PAULO | C76: KG COMERCIO | D76: XX | E76: CLARICELL | F76: 46204 | H76: SIM
A77: SP1 | B77: SÃO PAULO | C77: KG COMERCIO | D77: XX | E77: CLARICELL | F77: 46204 | H77: SIM
A78: SP1 | B78: SÃO PAULO | C78: KG COMERCIO | D78: XX | E78: CLARICELL | F78: 46082 | H78: SIM
A79: SP2 | B79: PERUIBE | C79: DIEGO | D79: 08GH | E79: FLEX CELL | F79: 46204 | H79: SIM
A80: SP2 | B80: PRAIA GRANDE | C80: DIEGO | D80: 2LOC | E80: FLEX CELL | F80: 46205 | H80: SIM
A81: SP2 | B81: ITANHAEM | C81: DIEGO | D81: 3Q90 | E81: FLEX CELL | F81: 46206 | H81: SIM
A82: SP2 | B82: REGISTRO | C82: DIEGO | D82: FP4S | E82: FLEX CELL | F82: 46207 | H82: SIM
A83: SP2 | B83: MONGAGUA | C83: DIEGO | D83: NK1R | E83: FLEX CELL | F83: 46208 | H83: SIM

Sheet CAD_PDV
A1: 1 | B1: 5 | C1: 19
A2: CODIGO AGENTE | B2: GRUPO_CREDITO | C2: LOCAL_NEGOCIO
A3: 14HB | B3: FABIANA GONCALVES DA SILVA LINS E CIA LTDA | C3: NE
A4: 4KDV | B4: CARLOS FREDERICO E FILHOS COMERCIO | C4: NE
A5: 5LYK | B5: HARCOS COMERCIO E SERVICOS LTDA - EPP | C5: NE
A6: 5QC8 | B6: HARCOS COMERCIO E SERVICOS LTDA - EPP | C6: NE
A7: B1RJ | B7: SELF COMERCIO E SERVICOS EM TELEFON | C7: NE
A8: DP0N | B8: SELF COMERCIO E SERVICOS EM TELEFON | C8: NE
A9: FCZ6 | B9: CARLOS FREDERICO E FILHOS COMERCIO | C9: NE
A10: GR53 | B10: DELTA CELL TELECOMUNICACOES LTDA | C10: NE
A11: H0ZF | B11: R & R HIPER COMERCIO LTDA | C11: NE
A12: IE2M | B12: HARCOS COMERCIO E SERVICOS LTDA - EPP | C12: NE
A13: IKFK | B13: HARCOS COMERCIO E SERVICOS LTDA - EPP | C13: NE
... A1113: Y3OP | B1113: EDUARDO JUNQUEIRA DA SILVEIRA ADMIN | C1113: PR/SC

Sheet Planilha6
A1: GRUPO | B1: (Tudo)
A3: REG | B3: Contagem de CÓD
A4: SP1 | B4: 70
A5: SP2 | B5: 180
A6: RJ/ES | B6: 97
A7: MG | B7: 93
A8: PR/SC | B8: 88
A9: RS | B9: 81
A10: CO | B10: 196
A11: BA/SE | B11: 62
A12: NE | B12: 96
A13: NO | B13: 43
A14: Total Geral | B14: 1006

Sheet Dashboard Calc
A1: REGIONAL | B1: SELLOUT | C1: CLARO TROCA | D1: ATTACHMENT | E1: ELEGÍVEIS | F1: ATIVOS | G1: CONVERSÃO | I1: MÊS | J1: CLARO TROCA | K1: ATTACHMENT | M1: REGIONAL | N1: ATTACHMENT | P1: REGIONAL | Q1: CLARO TROCA
A2: SP1 | B2: =SUMIFS(BASE!$F:$F,BASE!$A:$A,Dashboard!$B$3,BASE!$L:$L,$A2) -> 3011 | C2: =SUMIFS(BASE!$G:$G,BASE!$A:$A,Dashboard!$B$3,BASE!$L:$L,$A2) -> 321 | D2: =IFERROR(C2/B2,0) -> 0.1066091 | E2: =COUNTIFS(PDVS!$G$3:$G$5000,$A2,PDVS!$J$3:$J$5000,"Sim") -> 70 | F2: {=SUMPRODUCT(--(PDVS!$G$3:$G$5000=$A2),--(PDVS!$J$3:$J$5000="Sim"),--(INDEX(PDVS!$K$3:$V$5000,0,MATCH(Dashboard!$B$3,PDVS!$K$2:$V$2,0))>0))} -> 40 | G2: =IFERROR(F2/E2,0) -> 0.57142857 | I2: 46023 | J2: =IF(COUNTIFS(BASE!$A:$A,I2)>0,SUMIFS(BASE!$G:$G,BASE!$A:$A,I2),"") -> 2001 | K2: =IF(I2<=Dashboard!$B$3,IFERROR(SUMIFS(BASE!$G:$G,BASE!$A:$A,I2)/SUMIFS(BASE!$F:$F,BASE!$A:$A,I2),0),"") -> 0.083444537 | M2: {=_xlfn.SORTBY(_xlfn.HSTACK($A$2:$A$11,$D$2:$D$11),$D$2:$D$11,-1)} -> SP2 | N2: 0.20684908 | P2: {=_xlfn.SORTBY(_xlfn.HSTACK($A$2:$A$11,$C$2:$C$11),$C$2:$C$11,1)} -> NO | Q2: 4
A3: SP2 | B3: =SUMIFS(BASE!$F:$F,BASE!$A:$A,Dashboard!$B$3,BASE!$L:$L,$A3) -> 5811 | C3: =SUMIFS(BASE!$G:$G,BASE!$A:$A,Dashboard!$B$3,BASE!$L:$L,$A3) -> 1202 | D3: =IFERROR(C3/B3,0) -> 0.20684908 | E3: =COUNTIFS(PDVS!$G$3:$G$5000,$A3,PDVS!$J$3:$J$5000,"Sim") -> 170 | F3: {=SUMPRODUCT(--(PDVS!$G$3:$G$5000=$A3),--(PDVS!$J$3:$J$5000="Sim"),--(INDEX(PDVS!$K$3:$V$5000,0,MATCH(Dashboard!$B$3,PDVS!$K$2:$V$2,0))>0))} -> 110 | G3: =IFERROR(F3/E3,0) -> 0.64705882 | I3: 46054 | J3: =IF(COUNTIFS(BASE!$A:$A,I3)>0,SUMIFS(BASE!$G:$G,BASE!$A:$A,I3),"") -> 1657 | K3: =IF(I3<=Dashboard!$B$3,IFERROR(SUMIFS(BASE!$G:$G,BASE!$A:$A,I3)/SUMIFS(BASE!$F:$F,BASE!$A:$A,I3),0),"") -> 0.082709394 | M3: RJ/ES | N3: 0.13767123 | P3: BA/SE | Q3: 167
A4: RJ/ES | B4: =SUMIFS(BASE!$F:$F,BASE!$A:$A,Dashboard!$B$3,BASE!$L:$L,$A4) -> 4380 | C4: =SUMIFS(BASE!$G:$G,BASE!$A:$A,Dashboard!$B$3,BASE!$L:$L,$A4) -> 603 | D4: =IFERROR(C4/B4,0) -> 0.13767123 | E4: =COUNTIFS(PDVS!$G$3:$G$5000,$A4,PDVS!$J$3:$J$5000,"Sim") -> 97 | F4: {=SUMPRODUCT(--(PDVS!$G$3:$G$5000=$A4),--(PDVS!$J$3:$J$5000="Sim"),--(INDEX(PDVS!$K$3:$V$5000,0,MATCH(Dashboard!$B$3,PDVS!$K$2:$V$2,0))>0))} -> 72 | G4: =IFERROR(F4/E4,0) -> 0.74226804 | I4: 46082 | J4: =IF(COUNTIFS(BASE!$A:$A,I4)>0,SUMIFS(BASE!$G:$G,BASE!$A:$A,I4),"") -> 2965 | K4: =IF(I4<=Dashboard!$B$3,IFERROR(SUMIFS(BASE!$G:$G,BASE!$A:$A,I4)/SUMIFS(BASE!$F:$F,BASE!$A:$A,I4),0),"") -> 0.10160721 | M4: PR/SC | N4: 0.12022569 | P4: RS | Q4: 178
A5: MG | B5: =SUMIFS(BASE!$F:$F,BASE!$A:$A,Dashboard!$B$3,BASE!$L:$L,$A5) -> 2059 | C5: =SUMIFS(BASE!$G:$G,BASE!$A:$A,Dashboard!$B$3,BASE!$L:$L,$A5) -> 236 | D5: =IFERROR(C5/B5,0) -> 0.11461875 | E5: =COUNTIFS(PDVS!$G$3:$G$5000,$A5,PDVS!$J$3:$J$5000,"Sim") -> 89 | F5: {=SUMPRODUCT(--(PDVS!$G$3:$G$5000=$A5),--(PDVS!$J$3:$J$5000="Sim"),--(INDEX(PDVS!$K$3:$V$5000,0,MATCH(Dashboard!$B$3,PDVS!$K$2:$V$2,0))>0))} -> 30 | G5: =IFERROR(F5/E5,0) -> 0.33707865 | I5: 46113 | J5: =IF(COUNTIFS(BASE!$A:$A,I5)>0,SUMIFS(BASE!$G:$G,BASE!$A:$A,I5),"") -> 2364 | K5: =IF(I5<=Dashboard!$B$3,IFERROR(SUMIFS(BASE!$G:$G,BASE!$A:$A,I5)/SUMIFS(BASE!$F:$F,BASE!$A:$A,I5),0),"") -> 0.09834838 | M5: MG | N5: 0.11461875 | P5: MG | Q5: 236
A6: PR/SC | B6: =SUMIFS(BASE!$F:$F,BASE!$A:$A,Dashboard!$B$3,BASE!$L:$L,$A6) -> 2304 | C6: =SUMIFS(BASE!$G:$G,BASE!$A:$A,Dashboard!$B$3,BASE!$L:$L,$A6) -> 277 | D6: =IFERROR(C6/B6,0) -> 0.12022569 | E6: =COUNTIFS(PDVS!$G$3:$G$5000,$A6,PDVS!$J$3:$J$5000,"Sim") -> 85 | F6: {=SUMPRODUCT(--(PDVS!$G$3:$G$5000=$A6),--(PDVS!$J$3:$J$5000="Sim"),--(INDEX(PDVS!$K$3:$V$5000,0,MATCH(Dashboard!$B$3,PDVS!$K$2:$V$2,0))>0))} -> 49 | G6: =IFERROR(F6/E6,0) -> 0.57647059 | I6: 46143 | J6: =IF(COUNTIFS(BASE!$A:$A,I6)>0,SUMIFS(BASE!$G:$G,BASE!$A:$A,I6),"") -> 2940 | K6: =IF(I6<=Dashboard!$B$3,IFERROR(SUMIFS(BASE!$G:$G,BASE!$A:$A,I6)/SUMIFS(BASE!$F:$F,BASE!$A:$A,I6),0),"") -> 0.10131293 | M6: CO | N6: 0.10840059 | P6: NE | Q6: 265
A7: RS | B7: =SUMIFS(BASE!$F:$F,BASE!$A:$A,Dashboard!$B$3,BASE!$L:$L,$A7) -> 2450 | C7: =SUMIFS(BASE!$G:$G,BASE!$A:$A,Dashboard!$B$3,BASE!$L:$L,$A7) -> 178 | D7: =IFERROR(C7/B7,0) -> 0.072653061 | E7: =COUNTIFS(PDVS!$G$3:$G$5000,$A7,PDVS!$J$3:$J$5000,"Sim") -> 79 | F7: {=SUMPRODUCT(--(PDVS!$G$3:$G$5000=$A7),--(PDVS!$J$3:$J$5000="Sim"),--(INDEX(PDVS!$K$3:$V$5000,0,MATCH(Dashboard!$B$3,PDVS!$K$2:$V$2,0))>0))} -> 46 | G7: =IFERROR(F7/E7,0) -> 0.58227848 | I7: 46174 | J7: =IF(COUNTIFS(BASE!$A:$A,I7)>0,SUMIFS(BASE!$G:$G,BASE!$A:$A,I7),"") -> 3007 | K7: =IF(I7<=Dashboard!$B$3,IFERROR(SUMIFS(BASE!$G:$G,BASE!$A:$A,I7)/SUMIFS(BASE!$F:$F,BASE!$A:$A,I7),0),"") -> 0.12537525 | M7: SP1 | N7: 0.1066091 | P7: PR/SC | Q7: 277
A8: CO | B8: =SUMIFS(BASE!$F:$F,BASE!$A:$A,Dashboard!$B$3,BASE!$L:$L,$A8) -> 5452 | C8: =SUMIFS(BASE!$G:$G,BASE!$A:$A,Dashboard!$B$3,BASE!$L:$L,$A8) -> 591 | D8: =IFERROR(C8/B8,0) -> 0.10840059 | E8: =COUNTIFS(PDVS!$G$3:$G$5000,$A8,PDVS!$J$3:$J$5000,"Sim") -> 187 | F8: {=SUMPRODUCT(--(PDVS!$G$3:$G$5000=$A8),--(PDVS!$J$3:$J$5000="Sim"),--(INDEX(PDVS!$K$3:$V$5000,0,MATCH(Dashboard!$B$3,PDVS!$K$2:$V$2,0))>0))} -> 88 | G8: =IFERROR(F8/E8,0) -> 0.47058824 | I8: 46204 | J8: =IF(COUNTIFS(BASE!$A:$A,I8)>0,SUMIFS(BASE!$G:$G,BASE!$A:$A,I8),"") -> 5021 | K8: =IF(I8<=Dashboard!$B$3,IFERROR(SUMIFS(BASE!$G:$G,BASE!$A:$A,I8)/SUMIFS(BASE!$F:$F,BASE!$A:$A,I8),0),"") -> 0.16826408 | M8: BA/SE | N8: 0.1026429 | P8: SP1 | Q8: 321
A9: BA/SE | B9: =SUMIFS(BASE!$F:$F,BASE!$A:$A,Dashboard!$B$3,BASE!$L:$L,$A9) -> 1627 | C9: =SUMIFS(BASE!$G:$G,BASE!$A:$A,Dashboard!$B$3,BASE!$L:$L,$A9) -> 167 | D9: =IFERROR(C9/B9,0) -> 0.1026429 | E9: =COUNTIFS(PDVS!$G$3:$G$5000,$A9,PDVS!$J$3:$J$5000,"Sim") -> 61 | F9: {=SUMPRODUCT(--(PDVS!$G$3:$G$5000=$A9),--(PDVS!$J$3:$J$5000="Sim"),--(INDEX(PDVS!$K$3:$V$5000,0,MATCH(Dashboard!$B$3,PDVS!$K$2:$V$2,0))>0))} -> 26 | G9: =IFERROR(F9/E9,0) -> 0.42622951 | I9: 46235 | J9: =IF(COUNTIFS(BASE!$A:$A,I9)>0,SUMIFS(BASE!$G:$G,BASE!$A:$A,I9),"") -> 3844 | K9: =IF(I9<=Dashboard!$B$3,IFERROR(SUMIFS(BASE!$G:$G,BASE!$A:$A,I9)/SUMIFS(BASE!$F:$F,BASE!$A:$A,I9),0),"") -> 0.12726791 | M9: NE | N9: 0.10011334 | P9: CO | Q9: 591
A10: NE | B10: =SUMIFS(BASE!$F:$F,BASE!$A:$A,Dashboard!$B$3,BASE!$L:$L,$A10) -> 2647 | C10: =SUMIFS(BASE!$G:$G,BASE!$A:$A,Dashboard!$B$3,BASE!$L:$L,$A10) -> 265 | D10: =IFERROR(C10/B10,0) -> 0.10011334 | E10: =COUNTIFS(PDVS!$G$3:$G$5000,$A10,PDVS!$J$3:$J$5000,"Sim") -> 75 | F10: {=SUMPRODUCT(--(PDVS!$G$3:$G$5000=$A10),--(PDVS!$J$3:$J$5000="Sim"),--(INDEX(PDVS!$K$3:$V$5000,0,MATCH(Dashboard!$B$3,PDVS!$K$2:$V$2,0))>0))} -> 27 | G10: =IFERROR(F10/E10,0) -> 0.36 | I10: 46266 | J10: =IF(COUNTIFS(BASE!$A:$A,I10)>0,SUMIFS(BASE!$G:$G,BASE!$A:$A,I10),"") | K10: =IF(I10<=Dashboard!$B$3,IFERROR(SUMIFS(BASE!$G:$G,BASE!$A:$A,I10)/SUMIFS(BASE!$F:$F,BASE!$A:$A,I10),0),"") | M10: RS | N10: 0.072653061 | P10: RJ/ES | Q10: 603
A11: NO | B11: =SUMIFS(BASE!$F:$F,BASE!$A:$A,Dashboard!$B$3,BASE!$L:$L,$A11) -> 457 | C11: =SUMIFS(BASE!$G:$G,BASE!$A:$A,Dashboard!$B$3,BASE!$L:$L,$A11) -> 4 | D11: =IFERROR(C11/B11,0) -> 0.0087527352 | E11: =COUNTIFS(PDVS!$G$3:$G$5000,$A11,PDVS!$J$3:$J$5000,"Sim") -> 24 | F11: {=SUMPRODUCT(--(PDVS!$G$3:$G$5000=$A11),--(PDVS!$J$3:$J$5000="Sim"),--(INDEX(PDVS!$K$3:$V$5000,0,MATCH(Dashboard!$B$3,PDVS!$K$2:$V$2,0))>0))} -> 2 | G11: =IFERROR(F11/E11,0) -> 0.083333333 | I11: 46296 | J11: =IF(COUNTIFS(BASE!$A:$A,I11)>0,SUMIFS(BASE!$G:$G,BASE!$A:$A,I11),"") | K11: =IF(I11<=Dashboard!$B$3,IFERROR(SUMIFS(BASE!$G:$G,BASE!$A:$A,I11)/SUMIFS(BASE!$F:$F,BASE!$A:$A,I11),0),"") | M11: NO | N11: 0.0087527352 | P11: SP2 | Q11: 1202
I12: 46327 | J12: =IF(COUNTIFS(BASE!$A:$A,I12)>0,SUMIFS(BASE!$G:$G,BASE!$A:$A,I12),"") | K12: =IF(I12<=Dashboard!$B$3,IFERROR(SUMIFS(BASE!$G:$G,BASE!$A:$A,I12)/SUMIFS(BASE!$F:$F,BASE!$A:$A,I12),0),"")
I13: 46357 | J13: =IF(COUNTIFS(BASE!$A:$A,I13)>0,SUMIFS(BASE!$G:$G,BASE!$A:$A,I13),"") | K13: =IF(I13<=Dashboard!$B$3,IFERROR(SUMIFS(BASE!$G:$G,BASE!$A:$A,I13)/SUMIFS(BASE!$F:$F,BASE!$A:$A,I13),0),"")
